Workbook

Sheet 月数据汇总
A2: 1月 | B2: Cost 花费 | C2: IMP 展示 | D2: Click 点击 | E2: Order 订单 | F2: Sales 销量 | G2: ShoppingCart 加入购物车 | H2: Bookmark-Product 宝贝收藏 | I2: Bookmark-Store 店铺收藏 | J2: CTR 点击率 | K2: CPC 点击成本 | L2: CPM 千次展现成本 | M2: ROI 投资回报率 | N2: CVR 点击转化率 | O2: ASP 订单均价 | P2: Cporder 订单成本 | Q2: CPshopping cart 加购成本
A3: 钻展 | B3: 6.05 | C3: 1427 | D3: 1 | E3: - | F3: - | G3: - | H3: - | I3: - | J3: - | K3: - | L3: - | M3: - | N3: - | O3: - | P3: - | Q3: -
A4: 明星店铺 | B4: 2731.45 | C4: 7691 | D4: 349 | E4: 0 | F4: 0 | G4: 2 | H4: 2 | I4: 11 | J4: =D4/C4 -> 0.045377714 | K4: =B4/D4 -> 7.8265043 | L4: =(B4/C4)*1000 -> 355.14888 | M4: =F4/B4 -> 0 | N4: =E4/D4 -> 0 | O4: =F4/E4 -> #DIV/0! | P4: =B4/E4 -> #DIV/0! | Q4: =B4/G4 -> 1365.725
A5: 直通车 | B5: 1952.96 | C5: 39544 | D5: 1253 | E5: 2 | F5: 198 | G5: 46 | H5: 4 | I5: 8 | J5: =D5/C5 -> 0.031686223 | K5: =B5/D5 -> 1.5586273 | L5: =(B5/C5)*1000 -> 49.387012 | M5: =F5/B5 -> 0.10138456 | N5: =E5/D5 -> 0.0015961692 | O5: =F5/E5 -> 99 | P5: =B5/E5 -> 976.48 | Q5: =B5/G5 -> 42.455652
A6: 引力魔方 | B6: - | C6: - | D6: - | E6: - | F6: - | G6: - | H6: - | I6: - | J6: - | K6: - | L6: - | M6: - | N6: - | O6: - | P6: - | Q6: -
A7: 总计 | B7: =SUM(B3:B6) -> 4690.46 | C7: =SUM(C3:C6) -> 48662 | D7: =SUM(D3:D6) -> 1603 | E7: =SUM(E3:E6) -> 2 | F7: =SUM(F3:F6) -> 198 | G7: =SUM(G3:G6) -> 48 | H7: =SUM(H3:H6) -> 6 | I7: =SUM(I3:I6) -> 19 | J7: =D7/C7 -> 0.032941515 | K7: =B7/D7 -> 2.9260512 | L7: =(B7/C7)*1000 -> 96.388558 | M7: =F7/B7 -> 0.042213344 | N7: =E7/D7 -> 0.0012476606 | O7: =F7/E7 -> 99 | P7: =B7/E7 -> 2345.23 | Q7: =B7/G7 -> 97.717917
A10: 2月 | B10: Cost 花费 | C10: IMP 展示 | D10: Click 点击 | E10: Order 订单 | F10: Sales 销量 | G10: ShoppingCart 加入购物车 | H10: Bookmark-Product 宝贝收藏 | I10: Bookmark-Store 店铺收藏 | J10: CTR 点击率 | K10: CPC 点击成本 | L10: CPM 千次展现成本 | M10: ROI 投资回报率 | N10: CVR 点击转化率 | O10: ASP 订单均价 | P10: Cporder 订单成本 | Q10: CPshopping cart 加购成本
A11: 明星店铺 | B11: 22646 | C11: 24719 | D11: 1047 | E11: 1 | F11: 99 | G11: 13 | H11: 3 | I11: 20 | J11: =D11/C11 -> 0.042356082 | K11: =B11/D11 -> 21.629417 | L11: =(B11/C11)*1000 -> 916.13738 | M11: =F11/B11 -> 0.004371633 | N11: =E11/D11 -> 0.00095510984 | O11: =F11/E11 -> 99 | P11: =B11/E11 -> 22646 | Q11: =B11/G11 -> 1742
A12: 直通车 | B12: 5688.53 | C12: 84202 | D12: 2773 | E12: 2 | F12: 198 | G12: 51 | H12: 14 | I12: 14 | J12: =D12/C12 -> 0.032932709 | K12: =B12/D12 -> 2.0513992 | L12: =(B12/C12)*1000 -> 67.558134 | M12: =F12/B12 -> 0.034806883 | N12: =E12/D12 -> 0.00072124053 | O12: =F12/E12 -> 99 | P12: =B12/E12 -> 2844.265 | Q12: =B12/G12 -> 111.5398
A13: 引力魔方 | B13: 1337.93 | C13: 197627 | D13: 1649 | E13: 0 | F13: 0 | G13: 8 | H13: 12 | I13: 2 | J13: =D13/C13 -> 0.0083440016 | K13: =B13/D13 -> 0.8113584 | L13: =(B13/C13)*1000 -> 6.7699758 | M13: =F13/B13 -> 0 | N13: =E13/D13 -> 0 | O13: =F13/E13 -> #DIV/0! | P13: =B13/E13 -> #DIV/0! | Q13: =B13/G13 -> 167.24125
A14: 总计 | B14: =SUM(B11:B13) -> 29672.46 | C14: =SUM(C11:C13) -> 306548 | D14: =SUM(D11:D13) -> 5469 | E14: =SUM(E11:E13) -> 3 | F14: =SUM(F11:F13) -> 297 | G14: =SUM(G11:G13) -> 72 | H14: =SUM(H11:H13) -> 29 | I14: =SUM(I11:I13) -> 36 | J14: =D14/C14 -> 0.017840599 | K14: =B14/D14 -> 5.4255732 | L14: =(B14/C14)*1000 -> 96.795477 | M14: =F14/B14 -> 0.010009281 | N14: =E14/D14 -> 0.00054854635 | O14: =F14/E14 -> 99 | P14: =B14/E14 -> 9890.82 | Q14: =B14/G14 -> 412.1175
A17: 3月 | B17: Cost 花费 | C17: IMP 展示 | D17: Click 点击 | E17: Order 订单 | F17: Sales 销量 | G17: ShoppingCart 加入购物车 | H17: Bookmark-Product 宝贝收藏 | I17: Bookmark-Store 店铺收藏 | J17: CTR 点击率 | K17: CPC 点击成本 | L17: CPM 千次展现成本 | M17: ROI 投资回报率 | N17: CVR 点击转化率 | O17: ASP 订单均价 | P17: Cporder 订单成本 | Q17: CPshopping cart 加购成本
A18: 明星店铺 | B18: 2866.29 | C18: 12670 | D18: 404 | E18: 3 | F18: 600 | G18: 2 | H18: 1 | I18: 12 | J18: =D18/C18 -> 0.031886346 | K18: =B18/D18 -> 7.0947772 | L18: =(B18/C18)*1000 -> 226.22652 | M18: =F18/B18 -> 0.20932983 | N18: =E18/D18 -> 0.0074257426 | O18: =F18/E18 -> 200 | P18: =B18/E18 -> 955.43 | Q18: =B18/G18 -> 1433.145
A19: 直通车 | B19: 3311.5 | C19: 120004 | D19: 2346 | E19: 0 | F19: 0 | G19: 1 | H19: 2 | I19: 8 | J19: =D19/C19 -> 0.019549348 | K19: =B19/D19 -> 1.4115516 | L19: =(B19/C19)*1000 -> 27.594914 | M19: =F19/B19 -> 0 | N19: =E19/D19 -> 0 | O19: =F19/E19 -> #DIV/0! | P19: =B19/E19 -> #DIV/0! | Q19: =B19/G19 -> 3311.5
A20: 引力魔方 | B20: 2031.5 | C20: 219571 | D20: 1511 | E20: 0 | F20: 0 | G20: 2 | H20: 14 | I20: 0 | J20: =D20/C20 -> 0.0068816009 | K20: =B20/D20 -> 1.3444739 | L20: =(B20/C20)*1000 -> 9.2521326 | M20: =F20/B20 -> 0 | N20: =E20/D20 -> 0 | O20: =F20/E20 -> #DIV/0! | P20: =B20/E20 -> #DIV/0! | Q20: =B20/G20 -> 1015.75
A21: 总计 | B21: =SUM(B18:B20) -> 8209.29 | C21: =SUM(C18:C20) -> 352245 | D21: =SUM(D18:D20) -> 4261 | E21: =SUM(E18:E20) -> 3 | F21: =SUM(F18:F20) -> 600 | G21: =SUM(G18:G20) -> 5 | H21: =SUM(H18:H20) -> 17 | I21: =SUM(I18:I20) -> 20 | J21: =D21/C21 -> 0.012096694 | K21: =B21/D21 -> 1.9266111 | L21: =(B21/C21)*1000 -> 23.305625 | M21: =F21/B21 -> 0.073087928 | N21: =E21/D21 -> 0.00070406008 | O21: =F21/E21 -> 200 | P21: =B21/E21 -> 2736.43 | Q21: =B21/G21 -> 1641.858
A25: 2023年
A26: 8月 | B26: Cost 花费 | C26: IMP 展示 | D26: Click 点击 | E26: Order 订单 | F26: Sales 销量 | G26: ShoppingCart 加入购物车 | H26: Bookmark-Product 宝贝收藏 | I26: Bookmark-Store 店铺收藏 | J26: CTR 点击率 | K26: CPC 点击成本 | L26: CPM 千次展现成本 | M26: ROI 投资回报率 | N26: CVR 点击转化率 | O26: ASP 订单均价 | P26: Cporder 订单成本 | Q26: CPshopping cart 加购成本
A27: 明星店铺 | B27: =SUM(明星店铺!B514:B522) -> 496.42 | C27: =SUM(明星店铺!C514:C522) -> 670 | D27: =SUM(明星店铺!D514:D522) -> 180 | E27: =SUM(明星店铺!E514:E522) -> 3 | F27: =SUM(明星店铺!F514:F522) -> 3 | G27: =SUM(明星店铺!G514:G522) -> 38 | H27: =SUM(明星店铺!H514:H522) -> 8 | I27: =SUM(明星店铺!I514:I522) -> 6 | J27: =D27/C27 -> 0.26865672 | K27: =B27/D27 -> 2.7578889 | L27: =(B27/C27)*1000 -> 740.92537 | M27: =F27/B27 -> 0.0060432698 | N27: =E27/D27 -> 0.016666667 | O27: =F27/E27 -> 1 | P27: =B27/E27 -> 165.47333 | Q27: =B27/G27 -> 13.063684
A28: 直通车 | B28: =SUM(直通车!B514:B522) -> 8646.78 | C28: =SUM(直通车!C514:C522) -> 32943 | D28: =SUM(直通车!D514:D522) -> 2523 | E28: =SUM(直通车!E514:E522) -> 1 | F28: =SUM(直通车!F514:F522) -> 1 | G28: =SUM(直通车!G514:G522) -> 62 | H28: =SUM(直通车!H514:H522) -> 37 | I28: =SUM(直通车!I514:I522) -> 12 | J28: =D28/C28 -> 0.076586832 | K28: =B28/D28 -> 3.4271819 | L28: =(B28/C28)*1000 -> 262.47701 | M28: =F28/B28 -> 0.00011564999 | N28: =E28/D28 -> 0.00039635355 | O28: =F28/E28 -> 1 | P28: =B28/E28 -> 8646.78 | Q28: =B28/G28 -> 139.46419
A29: 引力魔方 | B29: =SUM(引力魔方!B413:B421) -> 4176.9 | C29: =SUM(引力魔方!C413:C421) -> 444197 | D29: =SUM(引力魔方!D413:D421) -> 2732 | E29: =SUM(引力魔方!E413:E421) -> 0 | F29: =SUM(引力魔方!F413:F421) -> 0 | G29: =SUM(引力魔方!G413:G421) -> 25 | H29: =SUM(引力魔方!H413:H421) -> 14 | I29: =SUM(引力魔方!I413:I421) -> 2 | J29: =D29/C29 -> 0.0061504242 | K29: =B29/D29 -> 1.5288799 | L29: =(B29/C29)*1000 -> 9.4032603 | M29: =F29/B29 -> 0 | N29: =E29/D29 -> 0 | O29: =F29/E29 -> #DIV/0! | P29: =B29/E29 -> #DIV/0! | Q29: =B29/G29 -> 167.076
A30: 万相台 | B30: =SUM(万相台!B2:B10) -> 1014.03 | C30: =SUM(万相台!C2:C10) -> 96394 | D30: =SUM(万相台!D2:D10) -> 1126 | E30: =SUM(万相台!E2:E10) -> 0 | F30: =SUM(万相台!F2:F10) -> 0 | G30: =SUM(万相台!G2:G10) -> 22 | H30: =SUM(万相台!H2:H10) -> 12 | J30: =D30/C30 -> 0.011681225 | K30: =B30/D30 -> 0.9005595 | L30: =(B30/C30)*1000 -> 10.519638 | M30: =F30/B30 -> 0 | N30: =E30/D30 -> 0 | O30: =F30/E30 -> #DIV/0! | P30: =B30/E30 -> #DIV/0! | Q30: =B30/G30 -> 46.092273
A31: 总计 | B31: =SUM(B27:B30) -> 14334.13 | C31: =SUM(C27:C30) -> 574204 | D31: =SUM(D27:D30) -> 6561 | E31: =SUM(E27:E30) -> 4 | F31: =SUM(F27:F30) -> 4 | G31: =SUM(G27:G30) -> 147 | H31: =SUM(H27:H30) -> 71 | I31: =SUM(I27:I30) -> 20 | J31: =D31/C31 -> 0.011426253 | K31: =B31/D31 -> 2.1847478 | L31: =(B31/C31)*1000 -> 24.96348 | M31: =F31/B31 -> 0.00027905426 | N31: =E31/D31 -> 0.00060966316 | O31: =F31/E31 -> 1 | P31: =B31/E31 -> 3583.5325 | Q31: =B31/G31 -> 97.511088
A33: 9月 | B33: Cost 花费 | C33: IMP 展示 | D33: Click 点击 | E33: Order 订单 | F33: Sales 销量 | G33: ShoppingCart 加入购物车 | H33: Bookmark-Product 宝贝收藏 | I33: Bookmark-Store 店铺收藏 | J33: CTR 点击率 | K33: CPC 点击成本 | L33: CPM 千次展现成本 | M33: ROI 投资回报率 | N33: CVR 点击转化率 | O33: ASP 订单均价 | P33: Cporder 订单成本 | Q33: CPshopping cart 加购成本
A34: 明星店铺 | B34: =SUM(明星店铺!B523:B552) -> 1129.72 | C34: =SUM(明星店铺!C523:C552) -> 1507 | D34: =SUM(明星店铺!D523:D552) -> 586 | E34: =SUM(明星店铺!E523:E552) -> 5 | F34: =SUM(明星店铺!F523:F552) -> 7282.8 | G34: =SUM(明星店铺!G523:G552) -> 84 | H34: =SUM(明星店铺!H523:H552) -> 17 | I34: =SUM(明星店铺!I523:I552) -> 26 | J34: =D34/C34 -> 0.38885202 | K34: =B34/D34 -> 1.9278498 | L34: =(B34/C34)*1000 -> 749.64831 | M34: =F34/B34 -> 6.4465531 | N34: =E34/D34 -> 0.0085324232 | O34: =F34/E34 -> 1456.56 | P34: =B34/E34 -> 225.944 | Q34: =B34/G34 -> 13.449048
A35: 直通车 | B35: =SUM(直通车!B523:B552) -> 38763.28 | C35: =SUM(直通车!C523:C552) -> 174099 | D35: =SUM(直通车!D523:D552) -> 10706 | E35: =SUM(直通车!E523:E552) -> 19 | F35: =SUM(直通车!F523:F552) -> 24965.1 | G35: =SUM(直通车!G523:G552) -> 252 | H35: =SUM(直通车!H523:H552) -> 177 | I35: =SUM(直通车!I523:I552) -> 88 | J35: =D35/C35 -> 0.061493748 | K35: =B35/D35 -> 3.6207061 | L35: =(B35/C35)*1000 -> 222.65079 | M35: =F35/B35 -> 0.64403993 | N35: =E35/D35 -> 0.0017747058 | O35: =F35/E35 -> 1313.9526 | P35: =B35/E35 -> 2040.1726 | Q35: =B35/G35 -> 153.82254
A36: 引力魔方 | B36: =SUM(引力魔方!B422:B451) -> 21321.69 | C36: =SUM(引力魔方!C422:C451) -> 1533981 | D36: =SUM(引力魔方!D422:D451) -> 11155 | E36: =SUM(引力魔方!E422:E451) -> 0 | F36: =SUM(引力魔方!F422:F451) -> 0 | G36: =SUM(引力魔方!G422:G451) -> 103 | H36: =SUM(引力魔方!H422:H451) -> 64 | I36: =SUM(引力魔方!I422:I451) -> 16 | J36: =D36/C36 -> 0.0072719284 | K36: =B36/D36 -> 1.9114021 | L36: =(B36/C36)*1000 -> 13.899579 | M36: =F36/B36 -> 0 | N36: =E36/D36 -> 0 | O36: =F36/E36 -> #DIV/0! | P36: =B36/E36 -> #DIV/0! | Q36: =B36/G36 -> 207.0067
A37: 万相台 | B37: =SUM(万相台!B11:B40) -> 6066.03 | C37: =SUM(万相台!C11:C40) -> 756412 | D37: =SUM(万相台!D11:D40) -> 9008 | E37: =SUM(万相台!E11:E40) -> 7 | F37: =SUM(万相台!F11:F40) -> 6379.9 | G37: =SUM(万相台!G11:G40) -> 115 | H37: =SUM(万相台!H11:H40) -> 96 | J37: =D37/C37 -> 0.011908854 | K37: =B37/D37 -> 0.67340475 | L37: =(B37/C37)*1000 -> 8.0194788 | M37: =F37/B37 -> 1.0517422 | N37: =E37/D37 -> 0.00077708703 | O37: =F37/E37 -> 911.41429 | P37: =B37/E37 -> 866.57571 | Q37: =B37/G37 -> 52.748087
A38: 总计 | B38: =SUM(B34:B37) -> 67280.72 | C38: =SUM(C34:C37) -> 2465999 | D38: =SUM(D34:D37) -> 31455 | E38: =SUM(E34:E37) -> 31 | F38: =SUM(F34:F37) -> 38627.8 | G38: =SUM(G34:G37) -> 554 | H38: =SUM(H34:H37) -> 354 | I38: =SUM(I34:I37) -> 130 | J38: =D38/C38 -> 0.01275548 | K38: =B38/D38 -> 2.1389515 | L38: =(B38/C38)*1000 -> 27.283353 | M38: =F38/B38 -> 0.57412881 | N38: =E38/D38 -> 0.00098553489 | O38: =F38/E38 -> 1246.0581 | P38: =B38/E38 -> 2170.3458 | Q38: =B38/G38 -> 121.44534
A40: 10月 | B40: Cost 花费 | C40: IMP 展示 | D40: Click 点击 | E40: Order 订单 | F40: Sales 销量 | G40: ShoppingCart 加入购物车 | H40: Bookmark-Product 宝贝收藏 | I40: Bookmark-Store 店铺收藏 | J40: CTR 点击率 | K40: CPC 点击成本 | L40: CPM 千次展现成本 | M40: ROI 投资回报率 | N40: CVR 点击转化率 | O40: ASP 订单均价 | P40: Cporder 订单成本 | Q40: CPshopping cart 加购成本
A41: 明星店铺 | B41: =SUM(明星店铺!B553:B583) -> 8005.24 | C41: =SUM(明星店铺!C553:C583) -> 9248 | D41: =SUM(明星店铺!D553:D583) -> 3856 | E41: =SUM(明星店铺!E553:E583) -> 129 | F41: =SUM(明星店铺!F553:F583) -> 1401487.2 | G41: =SUM(明星店铺!G553:G583) -> 747 | H41: =SUM(明星店铺!H553:H583) -> 232 | I41: =SUM(明星店铺!I553:I583) -> 442 | J41: =D41/C41 -> 0.41695502 | K41: =B41/D41 -> 2.0760477 | L41: =(B41/C41)*1000 -> 865.61851 | M41: =F41/B41 -> 175.07123 | N41: =E41/D41 -> 0.033454357 | O41: =F41/E41 -> 10864.242 | P41: =B41/E41 -> 62.056124 | Q41: =B41/G41 -> 10.716519
A42: 直通车 | B42: =SUM(直通车!B553:B583) -> 57558.86 | C42: =SUM(直通车!C553:C583) -> 219210 | D42: =SUM(直通车!D553:D583) -> 18951 | E42: =SUM(直通车!E553:E583) -> 133 | F42: =SUM(直通车!F553:F583) -> 1640797.3 | G42: =SUM(直通车!G553:G583) -> 924 | H42: =SUM(直通车!H553:H583) -> 626 | I42: =SUM(直通车!I553:I583) -> 336 | J42: =D42/C42 -> 0.086451348 | K42: =B42/D42 -> 3.0372466 | L42: =(B42/C42)*1000 -> 262.57406 | M42: =F42/B42 -> 28.506425 | N42: =E42/D42 -> 0.0070180993 | O42: =F42/E42 -> 12336.822 | P42: =B42/E42 -> 432.77338 | Q42: =B42/G42 -> 62.293139
A43: 引力魔方 | B43: =SUM(引力魔方!B452:B482) -> 30457.64 | C43: =SUM(引力魔方!C452:C482) -> 806896 | D43: =SUM(引力魔方!D452:D482) -> 10898 | E43: =SUM(引力魔方!E452:E482) -> 64 | F43: =SUM(引力魔方!F452:F482) -> 665174.8 | G43: =SUM(引力魔方!G452:G482) -> 206 | H43: =SUM(引力魔方!H452:H482) -> 94 | I43: =SUM(引力魔方!I452:I482) -> 78 | J43: =D43/C43 -> 0.013506078 | K43: =B43/D43 -> 2.7947917 | L43: =(B43/C43)*1000 -> 37.746674 | M43: =F43/B43 -> 21.839341 | N43: =E43/D43 -> 0.0058726372 | O43: =F43/E43 -> 10393.356 | P43: =B43/E43 -> 475.90062 | Q43: =B43/G43 -> 147.85262
A44: 万相台 | B44: =SUM(万相台!B41:B71) -> 9480.74 | C44: =SUM(万相台!C41:C71) -> 91699 | D44: =SUM(万相台!D41:D71) -> 4467 | E44: =SUM(万相台!E41:E71) -> 12 | F44: =SUM(万相台!F41:F71) -> 67545.5 | G44: =SUM(万相台!G41:G71) -> 114 | H44: =SUM(万相台!H41:H71) -> 60 | J44: =D44/C44 -> 0.048713726 | K44: =B44/D44 -> 2.1223953 | L44: =(B44/C44)*1000 -> 103.38979 | M44: =F44/B44 -> 7.1244966 | N44: =E44/D44 -> 0.0026863667 | O44: =F44/E44 -> 5628.7917 | P44: =B44/E44 -> 790.06167 | Q44: =B44/G44 -> 83.164386
A45: 总计 | B45: =SUM(B41:B44) -> 105502.48 | C45: =SUM(C41:C44) -> 1127053 | D45: =SUM(D41:D44) -> 38172 | E45: =SUM(E41:E44) -> 338 | F45: =SUM(F41:F44) -> 3775004.8 | G45: =SUM(G41:G44) -> 1991 | H45: =SUM(H41:H44) -> 1012 | I45: =SUM(I41:I44) -> 856 | J45: =D45/C45 -> 0.03386886 | K45: =B45/D45 -> 2.7638709 | L45: =(B45/C45)*1000 -> 93.609156 | M45: =F45/B45 -> 35.781195 | N45: =E45/D45 -> 0.0088546579 | O45: =F45/E45 -> 11168.653 | P45: =B45/E45 -> 312.13751 | Q45: =B45/G45 -> 52.989694
A47: 11月 | B47: Cost 花费 | C47: IMP 展示 | D47: Click 点击 | E47: Order 订单 | F47: Sales 销量 | G47: ShoppingCart 加入购物车 | H47: Bookmark-Product 宝贝收藏 | I47: Bookmark-Store 店铺收藏 | J47: CTR 点击率 | K47: CPC 点击成本 | L47: CPM 千次展现成本 | M47: ROI 投资回报率 | N47: CVR 点击转化率 | O47: ASP 订单均价 | P47: Cporder 订单成本 | Q47: CPshopping cart 加购成本
A48: 明星店铺 | B48: =SUM(明星店铺!B584:B613) -> 6386.06 | C48: =SUM(明星店铺!C584:C613) -> 6596 | D48: =SUM(明星店铺!D584:D613) -> 2650 | E48: =SUM(明星店铺!E584:E613) -> 63 | F48: =SUM(明星店铺!F584:F613) -> 477277.22 | G48: =SUM(明星店铺!G584:G613) -> 661 | H48: =SUM(明星店铺!H584:H613) -> 121 | I48: =SUM(明星店铺!I584:I613) -> 280 | J48: =D48/C48 -> 0.40175864 | K48: =B48/D48 -> 2.409834 | L48: =(B48/C48)*1000 -> 968.17162 | M48: =F48/B48 -> 74.737353 | N48: =E48/D48 -> 0.023773585 | O48: =F48/E48 -> 7575.8289 | P48: =B48/E48 -> 101.36603 | Q48: =B48/G48 -> 9.6612103
A49: 直通车 | B49: =SUM(直通车!B584:B613) -> 85001.26 | C49: =SUM(直通车!C584:C613) -> 273932 | D49: =SUM(直通车!D584:D613) -> 22062 | E49: =SUM(直通车!E584:E613) -> 111 | F49: =SUM(直通车!F584:F613) -> 872404.39 | G49: =SUM(直通车!G584:G613) -> 1099 | H49: =SUM(直通车!H584:H613) -> 513 | I49: =SUM(直通车!I584:I613) -> 285 | J49: =D49/C49 -> 0.080538236 | K49: =B49/D49 -> 3.8528356 | L49: =(B49/C49)*1000 -> 310.30059 | M49: =F49/B49 -> 10.263429 | N49: =E49/D49 -> 0.0050312755 | O49: =F49/E49 -> 7859.499 | P49: =B49/E49 -> 765.77712 | Q49: =B49/G49 -> 77.344186
A50: 引力魔方 | B50: =SUM(引力魔方!B483:B512) -> 47468.12 | C50: =SUM(引力魔方!C483:C512) -> 3705258 | D50: =SUM(引力魔方!D483:D512) -> 43076 | E50: =SUM(引力魔方!E483:E512) -> 48 | F50: =SUM(引力魔方!F483:F512) -> 489457.12 | G50: =SUM(引力魔方!G483:G512) -> 606 | H50: =SUM(引力魔方!H483:H512) -> 175 | I50: =SUM(引力魔方!I483:I512) -> 79 | J50: =D50/C50 -> 0.011625641 | K50: =B50/D50 -> 1.1019621 | L50: =(B50/C50)*1000 -> 12.811016 | M50: =F50/B50 -> 10.311281 | N50: =E50/D50 -> 0.0011143096 | O50: =F50/E50 -> 10197.023 | P50: =B50/E50 -> 988.91917 | Q50: =B50/G50 -> 78.330231
A51: 万相台 | B51: =SUM(万相台!B72:B101) -> 10182.62 | C51: =SUM(万相台!C72:C101) -> 257113 | D51: =SUM(万相台!D72:D101) -> 10905 | E51: =SUM(万相台!E72:E101) -> 29 | F51: =SUM(万相台!F72:F101) -> 265570.08 | G51: =SUM(万相台!G72:G101) -> 231 | H51: =SUM(万相台!H72:H101) -> 56 | J51: =D51/C51 -> 0.042413258 | K51: =B51/D51 -> 0.93375699 | L51: =(B51/C51)*1000 -> 39.603676 | M51: =F51/B51 -> 26.080722 | N51: =E51/D51 -> 0.0026593306 | O51: =F51/E51 -> 9157.589 | P51: =B51/E51 -> 351.12483 | Q51: =B51/G51 -> 44.080606
A52: 总计 | B52: =SUM(B48:B51) -> 149038.06 | C52: =SUM(C48:C51) -> 4242899 | D52: =SUM(D48:D51) -> 78693 | E52: =SUM(E48:E51) -> 251 | F52: =SUM(F48:F51) -> 2104708.8 | G52: =SUM(G48:G51) -> 2597 | H52: =SUM(H48:H51) -> 865 | I52: =SUM(I48:I51) -> 644 | J52: =D52/C52 -> 0.018546989 | K52: =B52/D52 -> 1.8939176 | L52: =(B52/C52)*1000 -> 35.126469 | M52: =F52/B52 -> 14.121955 | N52: =E52/D52 -> 0.0031896103 | O52: =F52/E52 -> 8385.2941 | P52: =B52/E52 -> 593.77713 | Q52: =B52/G52 -> 57.388548
A54: 12月 | B54: Cost 花费 | C54: IMP 展示 | D54: Click 点击 | E54: Order 订单 | F54: Sales 销量 | G54: ShoppingCart 加入购物车 | H54: Bookmark-Product 宝贝收藏 | I54: Bookmark-Store 店铺收藏 | J54: CTR 点击率 | K54: CPC 点击成本 | L54: CPM 千次展现成本 | M54: ROI 投资回报率 | N54: CVR 点击转化率 | O54: ASP 订单均价 | P54: Cporder 订单成本 | Q54: CPshopping cart 加购成本
A55: 明星店铺 | B55: =SUM(明星店铺!B614:B644) -> 3841.38 | C55: =SUM(明星店铺!C614:C644) -> 4328 | D55: =SUM(明星店铺!D614:D644) -> 1524 | E55: =SUM(明星店铺!E614:E644) -> 8 | F55: =SUM(明星店铺!F614:F644) -> 134928 | G55: =SUM(明星店铺!G614:G644) -> 340 | H55: =SUM(明星店铺!H614:H644) -> 67 | I55: =SUM(明星店铺!I614:I644) -> 113 | J55: =D55/C55 -> 0.35212569 | K55: =B55/D55 -> 2.5205906 | L55: =(B55/C55)*1000 -> 887.5647 | M55: =F55/B55 -> 35.124877 | N55: =E55/D55 -> 0.0052493438 | O55: =F55/E55 -> 16866 | P55: =B55/E55 -> 480.1725 | Q55: =B55/G55 -> 11.298176
A56: 直通车 | B56: =SUM(直通车!B614:B644) -> 121344.68 | C56: =SUM(直通车!C614:C644) -> 299486 | D56: =SUM(直通车!D614:D644) -> 21703 | E56: =SUM(直通车!E614:E644) -> 18 | F56: =SUM(直通车!F614:F644) -> 275328 | G56: =SUM(直通车!G614:G644) -> 891 | H56: =SUM(直通车!H614:H644) -> 353 | I56: =SUM(直通车!I614:I644) -> 219 | J56: =D56/C56 -> 0.072467494 | K56: =B56/D56 -> 5.591148 | L56: =(B56/C56)*1000 -> 405.17649 | M56: =F56/B56 -> 2.2689745 | N56: =E56/D56 -> 0.00082937843 | O56: =F56/E56 -> 15296 | P56: =B56/E56 -> 6741.3714 | Q56: =B56/G56 -> 136.18932
A57: 引力魔方 | B57: =SUM(引力魔方!B513:B543) -> 93923.95 | C57: =SUM(引力魔方!C513:C543) -> 5708966 | D57: =SUM(引力魔方!D513:D543) -> 120544 | E57: =SUM(引力魔方!E513:E543) -> 6 | F57: =SUM(引力魔方!F513:F543) -> 49886 | G57: =SUM(引力魔方!G513:G543) -> 429 | H57: =SUM(引力魔方!H513:H543) -> 546 | I57: =SUM(引力魔方!I513:I543) -> 66 | J57: =D57/C57 -> 0.021114857 | K57: =B57/D57 -> 0.77916736 | L57: =(B57/C57)*1000 -> 16.452007 | M57: =F57/B57 -> 0.53113184 | N57: =E57/D57 -> 4.9774356e-05 | O57: =F57/E57 -> 8314.3333 | P57: =B57/E57 -> 15653.992 | Q57: =B57/G57 -> 218.93695
A58: 万相台 | B58: =SUM(万相台!B102:B132) -> 12814.29 | C58: =SUM(万相台!C102:C132) -> 913809 | D58: =SUM(万相台!D102:D132) -> 13322 | E58: =SUM(万相台!E102:E132) -> 5 | F58: =SUM(万相台!F102:F132) -> 75770 | G58: =SUM(万相台!G102:G132) -> 242 | H58: =SUM(万相台!H102:H132) -> 83 | J58: =D58/C58 -> 0.014578539 | K58: =B58/D58 -> 0.96188936 | L58: =(B58/C58)*1000 -> 14.022941 | M58: =F58/B58 -> 5.91293 | N58: =E58/D58 -> 0.00037531902 | O58: =F58/E58 -> 15154 | P58: =B58/E58 -> 2562.858 | Q58: =B58/G58 -> 52.951612
A59: 总计 | B59: =SUM(B55:B58) -> 231924.3 | C59: =SUM(C55:C58) -> 6926589 | D59: =SUM(D55:D58) -> 157093 | E59: =SUM(E55:E58) -> 37 | F59: =SUM(F55:F58) -> 535912 | G59: =SUM(G55:G58) -> 1902 | H59: =SUM(H55:H58) -> 1049 | I59: =SUM(I55:I58) -> 398 | J59: =D59/C59 -> 0.022679706 | K59: =B59/D59 -> 1.4763503 | L59: =(B59/C59)*1000 -> 33.483191 | M59: =F59/B59 -> 2.3107194 | N59: =E59/D59 -> 0.00023552927 | O59: =F59/E59 -> 14484.108 | P59: =B59/E59 -> 6268.2245 | Q59: =B59/G59 -> 121.93707
A63: 2024年
A64: 1月 | B64: Cost 花费 | C64: IMP 展示 | D64: Click 点击 | E64: Order 订单 | F64: Sales 销量 | G64: ShoppingCart 加入购物车 | H64: Bookmark-Product 宝贝收藏 | I64: Bookmark-Store 店铺收藏 | J64: CTR 点击率 | K64: CPC 点击成本 | L64: CPM 千次展现成本 | M64: ROI 投资回报率 | N64: CVR 点击转化率 | O64: ASP 订单均价 | P64: Cporder 订单成本 | Q64: CPshopping cart 加购成本
A65: 明星店铺 | B65: =SUM(明星店铺!B645:B675) -> 4413.62 | C65: =SUM(明星店铺!C645:C675) -> 5217 | D65: =SUM(明星店铺!D645:D675) -> 1813 | E65: =SUM(明星店铺!E645:E675) -> 8 | F65: =SUM(明星店铺!F645:F675) -> 118804 | G65: =SUM(明星店铺!G645:G675) -> 442 | H65: =SUM(明星店铺!H645:H675) -> 43 | I65: =SUM(明星店铺!I645:I675) -> 117 | J65: =D65/C65 -> 0.34751773 | K65: =B65/D65 -> 2.4344291 | L65: =(B65/C65)*1000 -> 846.00728 | M65: =F65/B65 -> 26.917587 | N65: =E65/D65 -> 0.0044125758 | O65: =F65/E65 -> 14850.5 | P65: =B65/E65 -> 551.7025 | Q65: =B65/G65 -> 9.9855656
A66: 直通车 | B66: =SUM(直通车!B645:B675) -> 64544.95 | C66: =SUM(直通车!C645:C675) -> 163594 | D66: =SUM(直通车!D645:D675) -> 15532 | E66: =SUM(直通车!E645:E675) -> 5 | F66: =SUM(直通车!F645:F675) -> 54251 | G66: =SUM(直通车!G645:G675) -> 749 | H66: =SUM(直通车!H645:H675) -> 148 | I66: =SUM(直通车!I645:I675) -> 124 | J66: =D66/C66 -> 0.094942357 | K66: =B66/D66 -> 4.155611 | L66: =(B66/C66)*1000 -> 394.5435 | M66: =F66/B66 -> 0.84051502 | N66: =E66/D66 -> 0.00032191604 | O66: =F66/E66 -> 10850.2 | P66: =B66/E66 -> 12908.99 | Q66: =B66/G66 -> 86.174833
A67: 引力魔方 | B67: =SUM(引力魔方!B544:B574) -> 37588.65 | C67: =SUM(引力魔方!C544:C574) -> 31095835 | D67: =SUM(引力魔方!D544:D574) -> 188677 | E67: =SUM(引力魔方!E544:E574) -> 0 | F67: =SUM(引力魔方!F544:F574) -> 0 | G67: =SUM(引力魔方!G544:G574) -> 280 | H67: =SUM(引力魔方!H544:H574) -> 169 | I67: =SUM(引力魔方!I544:I574) -> 43 | J67: =D67/C67 -> 0.0060675972 | K67: =B67/D67 -> 0.19922222 | L67: =(B67/C67)*1000 -> 1.2088001 | M67: =F67/B67 -> 0 | N67: =E67/D67 -> 0 | O67: =F67/E67 -> #DIV/0! | P67: =B67/E67 -> #DIV/0! | Q67: =B67/G67 -> 134.24518
A68: 万相台 | B68: =SUM(万相台!B133:B163) -> 12333.92 | C68: =SUM(万相台!C133:C163) -> 843593 | D68: =SUM(万相台!D133:D163) -> 11679 | E68: =SUM(万相台!E133:E163) -> 11 | F68: =SUM(万相台!F133:F163) -> 155509 | G68: =SUM(万相台!G133:G163) -> 187 | H68: =SUM(万相台!H133:H163) -> 40 | J68: =D68/C68 -> 0.013844354 | K68: =B68/D68 -> 1.0560767 | L68: =(B68/C68)*1000 -> 14.6207 | M68: =(B68/C68)*1000 -> 14.6207 | N68: =E68/D68 -> 0.00094186146 | O68: =F68/E68 -> 14137.182 | P68: =B68/E68 -> 1121.2655 | Q68: =B68/G68 -> 65.956791
A69: 总计 | B69: =SUM(B65:B68) -> 118881.14 | C69: =SUM(C65:C68) -> 32108239 | D69: =SUM(D65:D68) -> 217701 | E69: =SUM(E65:E68) -> 24 | F69: =SUM(F65:F68) -> 328564 | G69: =SUM(G65:G68) -> 1658 | H69: =SUM(H65:H68) -> 400 | I69: =SUM(I65:I68) -> 284 | J69: =D69/C69 -> 0.0067802224 | K69: =B69/D69 -> 0.54607531 | L69: =(B69/C69)*1000 -> 3.702512 | M69: =F69/B69 -> 2.7638026 | N69: =E69/D69 -> 0.00011024295 | O69: =F69/E69 -> 13690.167 | P69: =B69/E69 -> 4953.3808 | Q69: =B69/G69 -> 71.701532
A71: 2月 | B71: Cost 花费 | C71: IMP 展示 | D71: Click 点击 | E71: Order 订单 | F71: Sales 销量 | G71: ShoppingCart 加入购物车 | H71: Bookmark-Product 宝贝收藏 | I71: Bookmark-Store 店铺收藏 | J71: CTR 点击率 | K71: CPC 点击成本 | L71: CPM 千次展现成本 | M71: ROI 投资回报率 | N71: CVR 点击转化率 | O71: ASP 订单均价 | P71: Cporder 订单成本 | Q71: CPshopping cart 加购成本
A72: 明星店铺 | B72: =SUM(明星店铺!B676:B704) -> 5341.79 | C72: =SUM(明星店铺!C676:C704) -> 7780 | D72: =SUM(明星店铺!D676:D704) -> 3160 | E72: =SUM(明星店铺!E676:E704) -> 22 | F72: =SUM(明星店铺!F676:F704) -> 336056 | G72: =SUM(明星店铺!G676:G704) -> 812 | H72: =SUM(明星店铺!H676:H704) -> 56 | I72: =SUM(明星店铺!I676:I704) -> 252 | J72: =D72/C72 -> 0.40616967 | K72: =B72/D72 -> 1.6904399 | L72: =(B72/C72)*1000 -> 686.6054 | M72: =F72/B72 -> 62.910747 | N72: =E72/D72 -> 0.0069620253 | O72: =F72/E72 -> 15275.273 | P72: =B72/E72 -> 242.80864 | Q72: =B72/G72 -> 6.5785591
A73: 直通车 | B73: =SUM(直通车!B676:B704) -> 41071.2 | C73: =SUM(直通车!C676:C704) -> 120151 | D73: =SUM(直通车!D676:D704) -> 9048 | E73: =SUM(直通车!E676:E704) -> 9 | F73: =SUM(直通车!F676:F704) -> 102983 | G73: =SUM(直通车!G676:G704) -> 590 | H73: =SUM(直通车!H676:H704) -> 79 | I73: =SUM(直通车!I676:I704) -> 115 | J73: =D73/C73 -> 0.075305241 | K73: =B73/D73 -> 4.5392573 | L73: =(B73/C73)*1000 -> 341.82986 | M73: =F73/B73 -> 2.5074261 | N73: =E73/D73 -> 0.00099469496 | O73: =F73/E73 -> 11442.556 | P73: =B73/E73 -> 4563.4667 | Q73: =B73/G73 -> 69.612203
A74: 引力魔方 | B74: =SUM(引力魔方!B575:B603) -> 14419.61 | C74: =SUM(引力魔方!C575:C603) -> 49785339 | D74: =SUM(引力魔方!D575:D603) -> 147329 | E74: =SUM(引力魔方!E575:E603) -> 0 | F74: =SUM(引力魔方!F575:F603) -> 0 | G74: =SUM(引力魔方!G575:G603) -> 85 | H74: =SUM(引力魔方!H575:H603) -> 82 | I74: =SUM(引力魔方!I575:I603) -> 36 | J74: =D74/C74 -> 0.0029592849 | K74: =B74/D74 -> 0.097873535 | L74: =(B74/C74)*1000 -> 0.28963567 | M74: =F74/B74 -> 0 | N74: =E74/D74 -> 0 | O74: =F74/E74 -> #DIV/0! | P74: =B74/E74 -> #DIV/0! | Q74: =B74/G74 -> 169.64247
A75: 万相台 | B75: =SUM(万相台!B164:B192) -> 5781.09 | C75: =SUM(万相台!C164:C192) -> 827507 | D75: =SUM(万相台!D164:D192) -> 16623 | E75: =SUM(万相台!E164:E192) -> 1 | F75: =SUM(万相台!F164:F192) -> 15880 | G75: =SUM(万相台!G164:G192) -> 123 | H75: =SUM(万相台!H164:H192) -> 67 | J75: =D75/C75 -> 0.020088048 | K75: =B75/D75 -> 0.34777657 | L75: =(B75/C75)*1000 -> 6.9861524 | M75: =(B75/C75)*1000 -> 6.9861524 | N75: =E75/D75 -> 6.0157613e-05 | O75: =F75/E75 -> 15880 | P75: =B75/E75 -> 5781.09 | Q75: =B75/G75 -> 47.000732
A76: 总计 | B76: =SUM(B72:B75) -> 66613.69 | C76: =SUM(C72:C75) -> 50740777 | D76: =SUM(D72:D75) -> 176160 | E76: =SUM(E72:E75) -> 32 | F76: =SUM(F72:F75) -> 454919 | G76: =SUM(G72:G75) -> 1610 | H76: =SUM(H72:H75) -> 284 | I76: =SUM(I72:I75) -> 403 | J76: =D76/C76 -> 0.0034717639 | K76: =B76/D76 -> 0.37814311 | L76: =(B76/C76)*1000 -> 1.3128236 | M76: =F76/B76 -> 6.8292118 | N76: =E76/D76 -> 0.00018165304 | O76: =F76/E76 -> 14216.219 | P76: =B76/E76 -> 2081.6778 | Q76: =B76/G76 -> 41.374963
A79: 3月 | B79: Cost 花费 | C79: IMP 展示 | D79: Click 点击 | E79: Order 订单 | F79: Sales 销量 | G79: ShoppingCart 加入购物车 | H79: Bookmark-Product 宝贝收藏 | I79: Bookmark-Store 店铺收藏 | J79: CTR 点击率 | K79: CPC 点击成本 | L79: CPM 千次展现成本 | M79: ROI 投资回报率 | N79: CVR 点击转化率 | O79: ASP 订单均价 | P79: Cporder 订单成本 | Q79: CPshopping cart 加购成本
A80: 明星店铺 | B80: =SUM(明星店铺!B710:B735) -> 6343.94 | C80: =SUM(明星店铺!C710:C735) -> 7790 | D80: =SUM(明星店铺!D710:D735) -> 3090 | E80: =SUM(明星店铺!E710:E735) -> 57 | F80: =SUM(明星店铺!F710:F735) -> 853525 | G80: =SUM(明星店铺!G710:G735) -> 864 | H80: =SUM(明星店铺!H710:H735) -> 65 | I80: =SUM(明星店铺!I710:I735) -> 205 | J80: =D80/C80 -> 0.39666239 | K80: =B80/D80 -> 2.053055 | L80: =(B80/C80)*1000 -> 814.3697 | M80: =F80/B80 -> 134.54178 | N80: =E80/D80 -> 0.018446602 | O80: =F80/E80 -> 14974.123 | P80: =B80/E80 -> 111.29719 | Q80: =B80/G80 -> 7.3425231 | S80: =D80/$D$84 -> 0.0059322685
A81: 直通车 | B81: =SUM(直通车!B710:B735) -> 75488.95 | C81: =SUM(直通车!C710:C735) -> 292874 | D81: =SUM(直通车!D710:D735) -> 15259 | E81: =SUM(直通车!E710:E735) -> 54 | F81: =SUM(直通车!F710:F735) -> 900873 | G81: =SUM(直通车!G710:G735) -> 1032 | H81: =SUM(直通车!H710:H735) -> 148 | I81: =SUM(直通车!I710:I735) -> 176 | J81: =D81/C81 -> 0.052100903 | K81: =B81/D81 -> 4.9471754 | L81: =(B81/C81)*1000 -> 257.75231 | M81: =F81/B81 -> 11.933839 | N81: =E81/D81 -> 0.0035388951 | O81: =F81/E81 -> 16682.833 | P81: =B81/E81 -> 1397.9435 | Q81: =B81/G81 -> 73.148207 | S81: =D81/$D$84 -> 0.029294655
A82: 引力魔方 | B82: =SUM(引力魔方!B609:B634) -> 42729.16 | C82: =SUM(引力魔方!C609:C634) -> 60695924 | D82: =SUM(引力魔方!D609:D634) -> 307564 | E82: =SUM(引力魔方!E609:E634) -> 3 | F82: =SUM(引力魔方!F609:F634) -> 61690 | G82: =SUM(引力魔方!G609:G634) -> 231 | H82: =SUM(引力魔方!H609:H634) -> 296 | I82: =SUM(引力魔方!I609:I634) -> 48 | J82: =D82/C82 -> 0.0050672925 | K82: =B82/D82 -> 0.1389277 | L82: =(B82/C82)*1000 -> 0.70398731 | M82: =F82/B82 -> 1.4437447 | N82: =E82/D82 -> 9.7540674e-06 | O82: =F82/E82 -> 20563.333 | P82: =B82/E82 -> 14243.053 | Q82: =B82/G82 -> 184.97472 | S82: =D82/$D$84 -> 0.59046997
A83: 万相台 | B83: =SUM(万相台!B198:B223) -> 72447.57 | C83: =SUM(万相台!C198:C223) -> 19289743 | D83: =SUM(万相台!D198:D223) -> 194967 | E83: =SUM(万相台!E198:E223) -> 40 | F83: =SUM(万相台!F198:F223) -> 673643 | G83: =SUM(万相台!G198:G223) -> 1444 | H83: =SUM(万相台!H198:H223) -> 3136 | I83: =SUM(万相台!J198:J223) -> 0.31336052 | J83: =D83/C83 -> 0.010107289 | K83: =B83/D83 -> 0.37158888 | L83: =(B83/C83)*1000 -> 3.7557561 | M83: =F83/B83 -> 9.2983519 | N83: =E83/D83 -> 0.00020516293 | O83: =F83/E83 -> 16841.075 | P83: =B83/E83 -> 1811.1892 | Q83: =B83/G83 -> 50.171447 | S83: =D83/$D$84 -> 0.3743031
A84: 总计 | B84: =SUM(B80:B83) -> 197009.62 | C84: =SUM(C80:C83) -> 80286331 | D84: =SUM(D80:D83) -> 520880 | E84: =SUM(E80:E83) -> 154 | F84: =SUM(F80:F83) -> 2489731 | G84: =SUM(G80:G83) -> 3571 | H84: =SUM(H80:H83) -> 3645 | I84: =SUM(I80:I83) -> 429.31336 | J84: =D84/C84 -> 0.0064877793 | K84: =B84/D84 -> 0.37822458 | L84: =(B84/C84)*1000 -> 2.4538376 | M84: =F84/B84 -> 12.637611 | N84: =E84/D84 -> 0.00029565351 | O84: =F84/E84 -> 16167.084 | P84: =B84/E84 -> 1279.2832 | Q84: =B84/G84 -> 55.169314
A87: 4月 | B87: Cost 花费 | C87: IMP 展示 | D87: Click 点击 | E87: Order 订单 | F87: Sales 销量 | G87: ShoppingCart 加入购物车 | H87: Bookmark-Product 宝贝收藏 | I87: Bookmark-Store 店铺收藏 | J87: CTR 点击率 | K87: CPC 点击成本 | L87: CPM 千次展现成本 | M87: ROI 投资回报率 | N87: CVR 点击转化率 | O87: ASP 订单均价 | P87: Cporder 订单成本 | Q87: CPshopping cart 加购成本
A88: 明星店铺 | B88: =SUM(明星店铺!B736:B765) -> 6488.18 | C88: =SUM(明星店铺!C736:C765) -> 7851 | D88: =SUM(明星店铺!D736:D765) -> 2955 | E88: =SUM(明星店铺!E736:E765) -> 18 | F88: =SUM(明星店铺!F736:F765) -> 276039 | G88: =SUM(明星店铺!G736:G765) -> 783 | H88: =SUM(明星店铺!H736:H756) -> 44 | I88: =SUM(明星店铺!I736:I765) -> 145 | J88: =D88/C88 -> 0.37638517 | K88: =B88/D88 -> 2.1956616 | L88: =(B88/C88)*1000 -> 826.41447 | M88: =F88/B88 -> 42.544905 | N88: =E88/D88 -> 0.0060913706 | O88: =IF(E88=0,"0",F88/E88) -> 15335.5 | P88: =IF(E88=0,"0",B88/E88) -> 360.45444 | Q88: =B88/G88 -> 8.2863091 | S88: =D88/$D$92 -> 0.0073047554
A89: 直通车 | B89: =SUM(直通车!B736:B765) -> 55187.14 | C89: =SUM(直通车!C736:C765) -> 217527 | D89: =SUM(直通车!D736:D765) -> 13706 | E89: =SUM(直通车!E736:E765) -> 9 | F89: =SUM(直通车!F736:F765) -> 196570 | G89: =SUM(直通车!G736:G765) -> 945 | H89: =SUM(直通车!H736:H765) -> 95 | I89: =SUM(直通车!I736:I765) -> 115 | J89: =D89/C89 -> 0.06300827 | K89: =B89/D89 -> 4.026495 | L89: =(B89/C89)*1000 -> 253.70248 | M89: =F89/B89 -> 3.5618805 | N89: =E89/D89 -> 0.00065664672 | O89: =IF(E89=0,"0",F89/E89) -> 21841.111 | P89: =IF(E89=0,"0",B89/E89) -> 6131.9044 | Q89: =B89/G89 -> 58.39909 | S89: =D89/$D$92 -> 0.033881211
A90: 引力魔方 | B90: =SUM(引力魔方!B635:B664) -> 37490.77 | C90: =SUM(引力魔方!C635:C664) -> 43486150 | D90: =SUM(引力魔方!D635:D664) -> 167971 | E90: =SUM(引力魔方!E635:E664) -> 2 | F90: =SUM(引力魔方!F635:F664) -> 20393.68 | G90: =SUM(引力魔方!G635:G664) -> 247 | H90: =SUM(引力魔方!H635:H664) -> 899 | I90: =SUM(引力魔方!I635:I664) -> 54 | J90: =D90/C90 -> 0.0038626321 | K90: =B90/D90 -> 0.22319787 | L90: =(B90/C90)*1000 -> 0.86213128 | M90: =F90/B90 -> 0.54396535 | N90: =E90/D90 -> 1.1906817e-05 | O90: =IF(E90=0,"0",F90/E90) -> 10196.84 | P90: =IF(E90=0,"0",B90/E90) -> 18745.385 | Q90: =B90/G90 -> 151.78449 | S90: =D90/$D$92 -> 0.41522405
A91: 万相台 | B91: =SUM(万相台!B224:B253) -> 61294.7 | C91: =SUM(万相台!C224:C253) -> 18951479 | D91: =SUM(万相台!D224:D253) -> 219899 | E91: =SUM(万相台!E224:E253) -> 31 | F91: =SUM(万相台!F224:F253) -> 464453.48 | G91: =SUM(万相台!G224:G253) -> 1037 | H91: =SUM(万相台!H224:H253) -> 3263 | I91: =SUM(万相台!J224:J253) -> 0.33683282 | J91: =D91/C91 -> 0.011603263 | K91: =B91/D91 -> 0.27874024 | L91: =(B91/C91)*1000 -> 3.2342964 | M91: =F91/B91 -> 7.577384 | N91: =E91/D91 -> 0.00014097381 | O91: =IF(E91=0,"0",F91/E91) -> 14982.37 | P91: =IF(E91=0,"0",B91/E91) -> 1977.2484 | Q91: =B91/G91 -> 59.107715 | S91: =D91/$D$92 -> 0.54358998
A92: 总计 | B92: =SUM(B88:B91) -> 160460.79 | C92: =SUM(C88:C91) -> 62663007 | D92: =SUM(D88:D91) -> 404531 | E92: =SUM(E88:E91) -> 60 | F92: =SUM(F88:F91) -> 957456.16 | G92: =SUM(G88:G91) -> 3012 | H92: =SUM(H88:H91) -> 4301 | I92: =SUM(I88:I91) -> 314.33683 | J92: =D92/C92 -> 0.0064556589 | K92: =B92/D92 -> 0.39665882 | L92: =(B92/C92)*1000 -> 2.5606941 | M92: =F92/B92 -> 5.9669167 | N92: =E92/D92 -> 0.00014831991 | O92: =F92/E92 -> 15957.603 | P92: =B92/E92 -> 2674.3465 | Q92: =B92/G92 -> 53.273835

Sheet 月数据汇总-
A2: 1月 | B2: Cost 花费 | C2: IMP 展示 | D2: Click 点击 | E2: Order 订单 | F2: Sales 销量 | G2: ShoppingCart 加入购物车 | H2: Bookmark-Product 宝贝收藏 | I2: Bookmark-Store 店铺收藏 | K2: CTR 点击率 | L2: CPC 点击成本 | M2: CPM 千次展现成本 | N2: ROI 投资回报率 | O2: CVR 点击转化率 | P2: ASP 订单均价 | Q2: Cporder 订单成本 | R2: CPshopping cart 加购成本
A3: 钻展 | B3: 6.05 | C3: 1427 | D3: 1 | E3: - | F3: - | G3: - | H3: - | I3: - | K3: - | L3: - | M3: - | N3: - | O3: - | P3: - | Q3: - | R3: -
A4: 明星店铺 | B4: 2731.45 | C4: 7691 | D4: 349 | E4: 0 | F4: 0 | G4: 2 | H4: 2 | I4: 11 | K4: =D4/C4 -> 0.045377714 | L4: =B4/D4 -> 7.8265043 | M4: =(B4/C4)*1000 -> 355.14888 | N4: =F4/B4 -> 0 | O4: =E4/D4 -> 0 | P4: =F4/E4 -> #DIV/0! | Q4: =B4/E4 -> #DIV/0! | R4: =B4/G4 -> 1365.725
A5: 直通车 | B5: 1952.96 | C5: 39544 | D5: 1253 | E5: 2 | F5: 198 | G5: 46 | H5: 4 | I5: 8 | K5: =D5/C5 -> 0.031686223 | L5: =B5/D5 -> 1.5586273 | M5: =(B5/C5)*1000 -> 49.387012 | N5: =F5/B5 -> 0.10138456 | O5: =E5/D5 -> 0.0015961692 | P5: =F5/E5 -> 99 | Q5: =B5/E5 -> 976.48 | R5: =B5/G5 -> 42.455652
A6: 引力魔方 | B6: - | C6: - | D6: - | E6: - | F6: - | G6: - | H6: - | I6: - | K6: - | L6: - | M6: - | N6: - | O6: - | P6: - | Q6: - | R6: -
A7: 总计 | B7: =SUM(B3:B6) -> 4690.46 | C7: =SUM(C3:C6) -> 48662 | D7: =SUM(D3:D6) -> 1603 | E7: =SUM(E3:E6) -> 2 | F7: =SUM(F3:F6) -> 198 | G7: =SUM(G3:G6) -> 48 | H7: =SUM(H3:H6) -> 6 | I7: =SUM(I3:I6) -> 19 | K7: =D7/C7 -> 0.032941515 | L7: =B7/D7 -> 2.9260512 | M7: =(B7/C7)*1000 -> 96.388558 | N7: =F7/B7 -> 0.042213344 | O7: =E7/D7 -> 0.0012476606 | P7: =F7/E7 -> 99 | Q7: =B7/E7 -> 2345.23 | R7: =B7/G7 -> 97.717917
A10: 2月 | B10: Cost 花费 | C10: IMP 展示 | D10: Click 点击 | E10: Order 订单 | F10: Sales 销量 | G10: ShoppingCart 加入购物车 | H10: Bookmark-Product 宝贝收藏 | I10: Bookmark-Store 店铺收藏 | K10: CTR 点击率 | L10: CPC 点击成本 | M10: CPM 千次展现成本 | N10: ROI 投资回报率 | O10: CVR 点击转化率 | P10: ASP 订单均价 | Q10: Cporder 订单成本 | R10: CPshopping cart 加购成本
A11: 明星店铺 | B11: 22646 | C11: 24719 | D11: 1047 | E11: 1 | F11: 99 | G11: 13 | H11: 3 | I11: 20 | K11: =D11/C11 -> 0.042356082 | L11: =B11/D11 -> 21.629417 | M11: =(B11/C11)*1000 -> 916.13738 | N11: =F11/B11 -> 0.004371633 | O11: =E11/D11 -> 0.00095510984 | P11: =F11/E11 -> 99 | Q11: =B11/E11 -> 22646 | R11: =B11/G11 -> 1742
A12: 直通车 | B12: 5688.53 | C12: 84202 | D12: 2773 | E12: 2 | F12: 198 | G12: 51 | H12: 14 | I12: 14 | K12: =D12/C12 -> 0.032932709 | L12: =B12/D12 -> 2.0513992 | M12: =(B12/C12)*1000 -> 67.558134 | N12: =F12/B12 -> 0.034806883 | O12: =E12/D12 -> 0.00072124053 | P12: =F12/E12 -> 99 | Q12: =B12/E12 -> 2844.265 | R12: =B12/G12 -> 111.5398
A13: 引力魔方 | B13: 1337.93 | C13: 197627 | D13: 1649 | E13: 0 | F13: 0 | G13: 8 | H13: 12 | I13: 2 | K13: =D13/C13 -> 0.0083440016 | L13: =B13/D13 -> 0.8113584 | M13: =(B13/C13)*1000 -> 6.7699758 | N13: =F13/B13 -> 0 | O13: =E13/D13 -> 0 | P13: =F13/E13 -> #DIV/0! | Q13: =B13/E13 -> #DIV/0! | R13: =B13/G13 -> 167.24125
A14: 总计 | B14: =SUM(B11:B13) -> 29672.46 | C14: =SUM(C11:C13) -> 306548 | D14: =SUM(D11:D13) -> 5469 | E14: =SUM(E11:E13) -> 3 | F14: =SUM(F11:F13) -> 297 | G14: =SUM(G11:G13) -> 72 | H14: =SUM(H11:H13) -> 29 | I14: =SUM(I11:I13) -> 36 | K14: =D14/C14 -> 0.017840599 | L14: =B14/D14 -> 5.4255732 | M14: =(B14/C14)*1000 -> 96.795477 | N14: =F14/B14 -> 0.010009281 | O14: =E14/D14 -> 0.00054854635 | P14: =F14/E14 -> 99 | Q14: =B14/E14 -> 9890.82 | R14: =B14/G14 -> 412.1175
A17: 3月 | B17: Cost 花费 | C17: IMP 展示 | D17: Click 点击 | E17: Order 订单 | F17: Sales 销量 | G17: ShoppingCart 加入购物车 | H17: Bookmark-Product 宝贝收藏 | I17: Bookmark-Store 店铺收藏 | K17: CTR 点击率 | L17: CPC 点击成本 | M17: CPM 千次展现成本 | N17: ROI 投资回报率 | O17: CVR 点击转化率 | P17: ASP 订单均价 | Q17: Cporder 订单成本 | R17: CPshopping cart 加购成本
A18: 明星店铺 | B18: 2866.29 | C18: 12670 | D18: 404 | E18: 3 | F18: 600 | G18: 2 | H18: 1 | I18: 12 | K18: =D18/C18 -> 0.031886346 | L18: =B18/D18 -> 7.0947772 | M18: =(B18/C18)*1000 -> 226.22652 | N18: =F18/B18 -> 0.20932983 | O18: =E18/D18 -> 0.0074257426 | P18: =F18/E18 -> 200 | Q18: =B18/E18 -> 955.43 | R18: =B18/G18 -> 1433.145
A19: 直通车 | B19: 3311.5 | C19: 120004 | D19: 2346 | E19: 0 | F19: 0 | G19: 1 | H19: 2 | I19: 8 | K19: =D19/C19 -> 0.019549348 | L19: =B19/D19 -> 1.4115516 | M19: =(B19/C19)*1000 -> 27.594914 | N19: =F19/B19 -> 0 | O19: =E19/D19 -> 0 | P19: =F19/E19 -> #DIV/0! | Q19: =B19/E19 -> #DIV/0! | R19: =B19/G19 -> 3311.5
A20: 引力魔方 | B20: 2031.5 | C20: 219571 | D20: 1511 | E20: 0 | F20: 0 | G20: 2 | H20: 14 | I20: 0 | K20: =D20/C20 -> 0.0068816009 | L20: =B20/D20 -> 1.3444739 | M20: =(B20/C20)*1000 -> 9.2521326 | N20: =F20/B20 -> 0 | O20: =E20/D20 -> 0 | P20: =F20/E20 -> #DIV/0! | Q20: =B20/E20 -> #DIV/0! | R20: =B20/G20 -> 1015.75
A21: 总计 | B21: =SUM(B18:B20) -> 8209.29 | C21: =SUM(C18:C20) -> 352245 | D21: =SUM(D18:D20) -> 4261 | E21: =SUM(E18:E20) -> 3 | F21: =SUM(F18:F20) -> 600 | G21: =SUM(G18:G20) -> 5 | H21: =SUM(H18:H20) -> 17 | I21: =SUM(I18:I20) -> 20 | K21: =D21/C21 -> 0.012096694 | L21: =B21/D21 -> 1.9266111 | M21: =(B21/C21)*1000 -> 23.305625 | N21: =F21/B21 -> 0.073087928 | O21: =E21/D21 -> 0.00070406008 | P21: =F21/E21 -> 200 | Q21: =B21/E21 -> 2736.43 | R21: =B21/G21 -> 1641.858
A25: 2023年
A26: 8月 | B26: Cost 花费 | C26: IMP 展示 | D26: Click 点击 | E26: Order 订单 | F26: Sales 销量 | G26: ShoppingCart 加入购物车 | H26: Bookmark-Product 宝贝收藏 | I26: Bookmark-Store 店铺收藏 | K26: CTR 点击率 | L26: CPC 点击成本 | M26: CPM 千次展现成本 | N26: ROI 投资回报率 | O26: CVR 点击转化率 | P26: ASP 订单均价 | Q26: Cporder 订单成本 | R26: CPshopping cart 加购成本
A27: 明星店铺 | B27: =SUM(明星店铺!B514:B522) -> 496.42 | C27: =SUM(明星店铺!C514:C522) -> 670 | D27: =SUM(明星店铺!D514:D522) -> 180 | E27: =SUM(明星店铺!E514:E522) -> 3 | F27: =SUM(明星店铺!F514:F522) -> 3 | G27: =SUM(明星店铺!G514:G522) -> 38 | H27: =SUM(明星店铺!H514:H522) -> 8 | I27: =SUM(明星店铺!I514:I522) -> 6 | K27: =D27/C27 -> 0.26865672 | L27: =B27/D27 -> 2.7578889 | M27: =(B27/C27)*1000 -> 740.92537 | N27: =F27/B27 -> 0.0060432698 | O27: =E27/D27 -> 0.016666667 | P27: =F27/E27 -> 1 | Q27: =B27/E27 -> 165.47333 | R27: =B27/G27 -> 13.063684
A28: 直通车 | B28: =SUM(直通车!B514:B522) -> 8646.78 | C28: =SUM(直通车!C514:C522) -> 32943 | D28: =SUM(直通车!D514:D522) -> 2523 | E28: =SUM(直通车!E514:E522) -> 1 | F28: =SUM(直通车!F514:F522) -> 1 | G28: =SUM(直通车!G514:G522) -> 62 | H28: =SUM(直通车!H514:H522) -> 37 | I28: =SUM(直通车!I514:I522) -> 12 | K28: =D28/C28 -> 0.076586832 | L28: =B28/D28 -> 3.4271819 | M28: =(B28/C28)*1000 -> 262.47701 | N28: =F28/B28 -> 0.00011564999 | O28: =E28/D28 -> 0.00039635355 | P28: =F28/E28 -> 1 | Q28: =B28/E28 -> 8646.78 | R28: =B28/G28 -> 139.46419
A29: 引力魔方 | B29: =SUM(引力魔方!B413:B421) -> 4176.9 | C29: =SUM(引力魔方!C413:C421) -> 444197 | D29: =SUM(引力魔方!D413:D421) -> 2732 | E29: =SUM(引力魔方!E413:E421) -> 0 | F29: =SUM(引力魔方!F413:F421) -> 0 | G29: =SUM(引力魔方!G413:G421) -> 25 | H29: =SUM(引力魔方!H413:H421) -> 14 | I29: =SUM(引力魔方!I413:I421) -> 2 | K29: =D29/C29 -> 0.0061504242 | L29: =B29/D29 -> 1.5288799 | M29: =(B29/C29)*1000 -> 9.4032603 | N29: =F29/B29 -> 0 | O29: =E29/D29 -> 0 | P29: =F29/E29 -> #DIV/0! | Q29: =B29/E29 -> #DIV/0! | R29: =B29/G29 -> 167.076
A30: 万相台 | B30: =SUM(万相台!B2:B10) -> 1014.03 | C30: =SUM(万相台!C2:C10) -> 96394 | D30: =SUM(万相台!D2:D10) -> 1126 | E30: =SUM(万相台!E2:E10) -> 0 | F30: =SUM(万相台!F2:F10) -> 0 | G30: =SUM(万相台!G2:G10) -> 22 | H30: =SUM(万相台!H2:H10) -> 12 | K30: =D30/C30 -> 0.011681225 | L30: =B30/D30 -> 0.9005595 | M30: =(B30/C30)*1000 -> 10.519638 | N30: =F30/B30 -> 0 | O30: =E30/D30 -> 0 | P30: =F30/E30 -> #DIV/0! | Q30: =B30/E30 -> #DIV/0! | R30: =B30/G30 -> 46.092273
A31: 总计 | B31: =SUM(B27:B30) -> 14334.13 | C31: =SUM(C27:C30) -> 574204 | D31: =SUM(D27:D30) -> 6561 | E31: =SUM(E27:E30) -> 4 | F31: =SUM(F27:F30) -> 4 | G31: =SUM(G27:G30) -> 147 | H31: =SUM(H27:H30) -> 71 | I31: =SUM(I27:I30) -> 20 | K31: =D31/C31 -> 0.011426253 | L31: =B31/D31 -> 2.1847478 | M31: =(B31/C31)*1000 -> 24.96348 | N31: =F31/B31 -> 0.00027905426 | O31: =E31/D31 -> 0.00060966316 | P31: =F31/E31 -> 1 | Q31: =B31/E31 -> 3583.5325 | R31: =B31/G31 -> 97.511088
A33: 9月 | B33: Cost 花费 | C33: IMP 展示 | D33: Click 点击 | E33: Order 订单 | F33: Sales 销量 | G33: ShoppingCart 加入购物车 | H33: Bookmark-Product 宝贝收藏 | I33: Bookmark-Store 店铺收藏 | J33: 总收藏数 | K33: CTR 点击率 | L33: CPC 点击成本 | M33: CPM 千次展现成本 | N33: ROI 投资回报率 | O33: CVR 点击转化率 | P33: ASP 订单均价 | Q33: Cporder 订单成本 | R33: CPshopping cart 加购成本
A34: 明星店铺 | B34: =SUM(明星店铺!B523:B552) -> 1129.72 | C34: =SUM(明星店铺!C523:C552) -> 1507 | D34: =SUM(明星店铺!D523:D552) -> 586 | E34: =SUM(明星店铺!E523:E552) -> 5 | F34: =SUM(明星店铺!F523:F552) -> 7282.8 | G34: =SUM(明星店铺!G523:G552) -> 84 | H34: =SUM(明星店铺!H523:H552) -> 17 | I34: =SUM(明星店铺!I523:I552) -> 26 | J34: =H34+I34 -> 43 | K34: =D34/C34 -> 0.38885202 | L34: =B34/D34 -> 1.9278498 | M34: =(B34/C34)*1000 -> 749.64831 | N34: =F34/B34 -> 6.4465531 | O34: =E34/D34 -> 0.0085324232 | P34: =F34/E34 -> 1456.56 | Q34: =B34/E34 -> 225.944 | R34: =B34/G34 -> 13.449048
A35: 直通车 | B35: =SUM(直通车!B523:B552) -> 38763.28 | C35: =SUM(直通车!C523:C552) -> 174099 | D35: =SUM(直通车!D523:D552) -> 10706 | E35: =SUM(直通车!E523:E552) -> 19 | F35: =SUM(直通车!F523:F552) -> 24965.1 | G35: =SUM(直通车!G523:G552) -> 252 | H35: =SUM(直通车!H523:H552) -> 177 | I35: =SUM(直通车!I523:I552) -> 88 | J35: =H35+I35 -> 265 | K35: =D35/C35 -> 0.061493748 | L35: =B35/D35 -> 3.6207061 | M35: =(B35/C35)*1000 -> 222.65079 | N35: =F35/B35 -> 0.64403993 | O35: =E35/D35 -> 0.0017747058 | P35: =F35/E35 -> 1313.9526 | Q35: =B35/E35 -> 2040.1726 | R35: =B35/G35 -> 153.82254
A36: 引力魔方 | B36: =SUM(引力魔方!B422:B451) -> 21321.69 | C36: =SUM(引力魔方!C422:C451) -> 1533981 | D36: =SUM(引力魔方!D422:D451) -> 11155 | E36: =SUM(引力魔方!E422:E451) -> 0 | F36: =SUM(引力魔方!F422:F451) -> 0 | G36: =SUM(引力魔方!G422:G451) -> 103 | H36: =SUM(引力魔方!H422:H451) -> 64 | I36: =SUM(引力魔方!I422:I451) -> 16 | J36: =H36+I36 -> 80 | K36: =D36/C36 -> 0.0072719284 | L36: =B36/D36 -> 1.9114021 | M36: =(B36/C36)*1000 -> 13.899579 | N36: =F36/B36 -> 0 | O36: =E36/D36 -> 0 | P36: =F36/E36 -> #DIV/0! | Q36: =B36/E36 -> #DIV/0! | R36: =B36/G36 -> 207.0067
A37: 万相台 | B37: =SUM(万相台!B11:B40) -> 6066.03 | C37: =SUM(万相台!C11:C40) -> 756412 | D37: =SUM(万相台!D11:D40) -> 9008 | E37: =SUM(万相台!E11:E40) -> 7 | F37: =SUM(万相台!F11:F40) -> 6379.9 | G37: =SUM(万相台!G11:G40) -> 115 | H37: =SUM(万相台!H11:H40) -> 96 | J37: =H37+I37 -> 96 | K37: =D37/C37 -> 0.011908854 | L37: =B37/D37 -> 0.67340475 | M37: =(B37/C37)*1000 -> 8.0194788 | N37: =F37/B37 -> 1.0517422 | O37: =E37/D37 -> 0.00077708703 | P37: =F37/E37 -> 911.41429 | Q37: =B37/E37 -> 866.57571 | R37: =B37/G37 -> 52.748087
A38: 总计 | B38: =SUM(B34:B37) -> 67280.72 | C38: =SUM(C34:C37) -> 2465999 | D38: =SUM(D34:D37) -> 31455 | E38: =SUM(E34:E37) -> 31 | F38: =SUM(F34:F37) -> 38627.8 | G38: =SUM(G34:G37) -> 554 | H38: =SUM(H34:H37) -> 354 | I38: =SUM(I34:I37) -> 130 | J38: =H38+I38 -> 484 | K38: =D38/C38 -> 0.01275548 | L38: =B38/D38 -> 2.1389515 | M38: =(B38/C38)*1000 -> 27.283353 | N38: =F38/B38 -> 0.57412881 | O38: =E38/D38 -> 0.00098553489 | P38: =F38/E38 -> 1246.0581 | Q38: =B38/E38 -> 2170.3458 | R38: =B38/G38 -> 121.44534
A40: 10月 | B40: Cost 花费 | C40: IMP 展示 | D40: Click 点击 | E40: Order 订单 | F40: Sales 销量 | G40: ShoppingCart 加入购物车 | H40: Bookmark-Product 宝贝收藏 | I40: Bookmark-Store 店铺收藏 | J40: 总收藏数 | K40: CTR 点击率 | L40: CPC 点击成本 | M40: CPM 千次展现成本 | N40: ROI 投资回报率 | O40: CVR 点击转化率 | P40: ASP 订单均价 | Q40: Cporder 订单成本 | R40: CPshopping cart 加购成本
A41: 明星店铺 | B41: =SUM(明星店铺!B553:B583) -> 8005.24 | C41: =SUM(明星店铺!C553:C583) -> 9248 | D41: =SUM(明星店铺!D553:D583) -> 3856 | E41: =SUM(明星店铺!E553:E583) -> 129 | F41: =SUM(明星店铺!F553:F583) -> 1401487.2 | G41: =SUM(明星店铺!G553:G583) -> 747 | H41: =SUM(明星店铺!H553:H583) -> 232 | I41: =SUM(明星店铺!I553:I583) -> 442 | J41: =H41+I41 -> 674 | K41: =D41/C41 -> 0.41695502 | L41: =B41/D41 -> 2.0760477 | M41: =(B41/C41)*1000 -> 865.61851 | N41: =F41/B41 -> 175.07123 | O41: =E41/D41 -> 0.033454357 | P41: =F41/E41 -> 10864.242 | Q41: =B41/E41 -> 62.056124 | R41: =B41/G41 -> 10.716519
A42: 直通车 | B42: =SUM(直通车!B553:B583) -> 57558.86 | C42: =SUM(直通车!C553:C583) -> 219210 | D42: =SUM(直通车!D553:D583) -> 18951 | E42: =SUM(直通车!E553:E583) -> 133 | F42: =SUM(直通车!F553:F583) -> 1640797.3 | G42: =SUM(直通车!G553:G583) -> 924 | H42: =SUM(直通车!H553:H583) -> 626 | I42: =SUM(直通车!I553:I583) -> 336 | J42: =H42+I42 -> 962 | K42: =D42/C42 -> 0.086451348 | L42: =B42/D42 -> 3.0372466 | M42: =(B42/C42)*1000 -> 262.57406 | N42: =F42/B42 -> 28.506425 | O42: =E42/D42 -> 0.0070180993 | P42: =F42/E42 -> 12336.822 | Q42: =B42/E42 -> 432.77338 | R42: =B42/G42 -> 62.293139
A43: 引力魔方 | B43: =SUM(引力魔方!B452:B482) -> 30457.64 | C43: =SUM(引力魔方!C452:C482) -> 806896 | D43: =SUM(引力魔方!D452:D482) -> 10898 | E43: =SUM(引力魔方!E452:E482) -> 64 | F43: =SUM(引力魔方!F452:F482) -> 665174.8 | G43: =SUM(引力魔方!G452:G482) -> 206 | H43: =SUM(引力魔方!H452:H482) -> 94 | I43: =SUM(引力魔方!I452:I482) -> 78 | J43: =H43+I43 -> 172 | K43: =D43/C43 -> 0.013506078 | L43: =B43/D43 -> 2.7947917 | M43: =(B43/C43)*1000 -> 37.746674 | N43: =F43/B43 -> 21.839341 | O43: =E43/D43 -> 0.0058726372 | P43: =F43/E43 -> 10393.356 | Q43: =B43/E43 -> 475.90062 | R43: =B43/G43 -> 147.85262
A44: 万相台 | B44: =SUM(万相台!B41:B71) -> 9480.74 | C44: =SUM(万相台!C41:C71) -> 91699 | D44: =SUM(万相台!D41:D71) -> 4467 | E44: =SUM(万相台!E41:E71) -> 12 | F44: =SUM(万相台!F41:F71) -> 67545.5 | G44: =SUM(万相台!G41:G71) -> 114 | H44: =SUM(万相台!H41:H71) -> 60 | J44: =H44+I44 -> 60 | K44: =D44/C44 -> 0.048713726 | L44: =B44/D44 -> 2.1223953 | M44: =(B44/C44)*1000 -> 103.38979 | N44: =F44/B44 -> 7.1244966 | O44: =E44/D44 -> 0.0026863667 | P44: =F44/E44 -> 5628.7917 | Q44: =B44/E44 -> 790.06167 | R44: =B44/G44 -> 83.164386
A45: 总计 | B45: =SUM(B41:B44) -> 105502.48 | C45: =SUM(C41:C44) -> 1127053 | D45: =SUM(D41:D44) -> 38172 | E45: =SUM(E41:E44) -> 338 | F45: =SUM(F41:F44) -> 3775004.8 | G45: =SUM(G41:G44) -> 1991 | H45: =SUM(H41:H44) -> 1012 | I45: =SUM(I41:I44) -> 856 | J45: =H45+I45 -> 1868 | K45: =D45/C45 -> 0.03386886 | L45: =B45/D45 -> 2.7638709 | M45: =(B45/C45)*1000 -> 93.609156 | N45: =F45/B45 -> 35.781195 | O45: =E45/D45 -> 0.0088546579 | P45: =F45/E45 -> 11168.653 | Q45: =B45/E45 -> 312.13751 | R45: =B45/G45 -> 52.989694
A47: 11月 | B47: Cost 花费 | C47: IMP 展示 | D47: Click 点击 | E47: Order 订单 | F47: Sales 销量 | G47: ShoppingCart 加入购物车 | H47: Bookmark-Product 宝贝收藏 | I47: Bookmark-Store 店铺收藏 | J47: 总收藏数 | K47: CTR 点击率 | L47: CPC 点击成本 | M47: CPM 千次展现成本 | N47: ROI 投资回报率 | O47: CVR 点击转化率 | P47: ASP 订单均价 | Q47: Cporder 订单成本 | R47: CPshopping cart 加购成本
A48: 明星店铺 | B48: =SUM(明星店铺!B584:B613) -> 6386.06 | C48: =SUM(明星店铺!C584:C613) -> 6596 | D48: =SUM(明星店铺!D584:D613) -> 2650 | E48: =SUM(明星店铺!E584:E613) -> 63 | F48: =SUM(明星店铺!F584:F613) -> 477277.22 | G48: =SUM(明星店铺!G584:G613) -> 661 | H48: =SUM(明星店铺!H584:H613) -> 121 | I48: =SUM(明星店铺!I584:I613) -> 280 | J48: =H48+I48 -> 401 | K48: =D48/C48 -> 0.40175864 | L48: =B48/D48 -> 2.409834 | M48: =(B48/C48)*1000 -> 968.17162 | N48: =F48/B48 -> 74.737353 | O48: =E48/D48 -> 0.023773585 | P48: =F48/E48 -> 7575.8289 | Q48: =B48/E48 -> 101.36603 | R48: =B48/G48 -> 9.6612103
A49: 直通车 | B49: =SUM(直通车!B584:B613) -> 85001.26 | C49: =SUM(直通车!C584:C613) -> 273932 | D49: =SUM(直通车!D584:D613) -> 22062 | E49: =SUM(直通车!E584:E613) -> 111 | F49: =SUM(直通车!F584:F613) -> 872404.39 | G49: =SUM(直通车!G584:G613) -> 1099 | H49: =SUM(直通车!H584:H613) -> 513 | I49: =SUM(直通车!I584:I613) -> 285 | J49: =H49+I49 -> 798 | K49: =D49/C49 -> 0.080538236 | L49: =B49/D49 -> 3.8528356 | M49: =(B49/C49)*1000 -> 310.30059 | N49: =F49/B49 -> 10.263429 | O49: =E49/D49 -> 0.0050312755 | P49: =F49/E49 -> 7859.499 | Q49: =B49/E49 -> 765.77712 | R49: =B49/G49 -> 77.344186
A50: 引力魔方 | B50: =SUM(引力魔方!B483:B512) -> 47468.12 | C50: =SUM(引力魔方!C483:C512) -> 3705258 | D50: =SUM(引力魔方!D483:D512) -> 43076 | E50: =SUM(引力魔方!E483:E512) -> 48 | F50: =SUM(引力魔方!F483:F512) -> 489457.12 | G50: =SUM(引力魔方!G483:G512) -> 606 | H50: =SUM(引力魔方!H483:H512) -> 175 | I50: =SUM(引力魔方!I483:I512) -> 79 | J50: =H50+I50 -> 254 | K50: =D50/C50 -> 0.011625641 | L50: =B50/D50 -> 1.1019621 | M50: =(B50/C50)*1000 -> 12.811016 | N50: =F50/B50 -> 10.311281 | O50: =E50/D50 -> 0.0011143096 | P50: =F50/E50 -> 10197.023 | Q50: =B50/E50 -> 988.91917 | R50: =B50/G50 -> 78.330231
A51: 万相台 | B51: =SUM(万相台!B72:B101) -> 10182.62 | C51: =SUM(万相台!C72:C101) -> 257113 | D51: =SUM(万相台!D72:D101) -> 10905 | E51: =SUM(万相台!E72:E101) -> 29 | F51: =SUM(万相台!F72:F101) -> 265570.08 | G51: =SUM(万相台!G72:G101) -> 231 | H51: =SUM(万相台!H72:H101) -> 56 | J51: =H51+I51 -> 56 | K51: =D51/C51 -> 0.042413258 | L51: =B51/D51 -> 0.93375699 | M51: =(B51/C51)*1000 -> 39.603676 | N51: =F51/B51 -> 26.080722 | O51: =E51/D51 -> 0.0026593306 | P51: =F51/E51 -> 9157.589 | Q51: =B51/E51 -> 351.12483 | R51: =B51/G51 -> 44.080606
A52: 总计 | B52: =SUM(B48:B51) -> 149038.06 | C52: =SUM(C48:C51) -> 4242899 | D52: =SUM(D48:D51) -> 78693 | E52: =SUM(E48:E51) -> 251 | F52: =SUM(F48:F51) -> 2104708.8 | G52: =SUM(G48:G51) -> 2597 | H52: =SUM(H48:H51) -> 865 | I52: =SUM(I48:I51) -> 644 | J52: =H52+I52 -> 1509 | K52: =D52/C52 -> 0.018546989 | L52: =B52/D52 -> 1.8939176 | M52: =(B52/C52)*1000 -> 35.126469 | N52: =F52/B52 -> 14.121955 | O52: =E52/D52 -> 0.0031896103 | P52: =F52/E52 -> 8385.2941 | Q52: =B52/E52 -> 593.77713 | R52: =B52/G52 -> 57.388548
A54: 12月 | B54: Cost 花费 | C54: IMP 展示 | D54: Click 点击 | E54: Order 订单 | F54: Sales 销量 | G54: ShoppingCart 加入购物车 | H54: Bookmark-Product 宝贝收藏 | I54: Bookmark-Store 店铺收藏 | J54: 总收藏数 | K54: CTR 点击率 | L54: CPC 点击成本 | M54: CPM 千次展现成本 | N54: ROI 投资回报率 | O54: CVR 点击转化率 | P54: ASP 订单均价 | Q54: Cporder 订单成本 | R54: CPshopping cart 加购成本
A55: 明星店铺 | B55: =SUM(明星店铺!B614:B644) -> 3841.38 | C55: =SUM(明星店铺!C614:C644) -> 4328 | D55: =SUM(明星店铺!D614:D644) -> 1524 | E55: =SUM(明星店铺!E614:E644) -> 8 | F55: =SUM(明星店铺!F614:F644) -> 134928 | G55: =SUM(明星店铺!G614:G644) -> 340 | H55: =SUM(明星店铺!H614:H644) -> 67 | I55: =SUM(明星店铺!I614:I644) -> 113 | J55: =H55+I55 -> 180 | K55: =D55/C55 -> 0.35212569 | L55: =B55/D55 -> 2.5205906 | M55: =(B55/C55)*1000 -> 887.5647 | N55: =F55/B55 -> 35.124877 | O55: =E55/D55 -> 0.0052493438 | P55: =F55/E55 -> 16866 | Q55: =B55/E55 -> 480.1725 | R55: =B55/G55 -> 11.298176
A56: 直通车 | B56: =SUM(直通车!B614:B644) -> 121344.68 | C56: =SUM(直通车!C614:C644) -> 299486 | D56: =SUM(直通车!D614:D644) -> 21703 | E56: =SUM(直通车!E614:E644) -> 18 | F56: =SUM(直通车!F614:F644) -> 275328 | G56: =SUM(直通车!G614:G644) -> 891 | H56: =SUM(直通车!H614:H644) -> 353 | I56: =SUM(直通车!I614:I644) -> 219 | J56: =H56+I56 -> 572 | K56: =D56/C56 -> 0.072467494 | L56: =B56/D56 -> 5.591148 | M56: =(B56/C56)*1000 -> 405.17649 | N56: =F56/B56 -> 2.2689745 | O56: =E56/D56 -> 0.00082937843 | P56: =F56/E56 -> 15296 | Q56: =B56/E56 -> 6741.3714 | R56: =B56/G56 -> 136.18932
A57: 引力魔方 | B57: =SUM(引力魔方!B513:B543) -> 93923.95 | C57: =SUM(引力魔方!C513:C543) -> 5708966 | D57: =SUM(引力魔方!D513:D543) -> 120544 | E57: =SUM(引力魔方!E513:E543) -> 6 | F57: =SUM(引力魔方!F513:F543) -> 49886 | G57: =SUM(引力魔方!G513:G543) -> 429 | H57: =SUM(引力魔方!H513:H543) -> 546 | I57: =SUM(引力魔方!I513:I543) -> 66 | J57: =H57+I57 -> 612 | K57: =D57/C57 -> 0.021114857 | L57: =B57/D57 -> 0.77916736 | M57: =(B57/C57)*1000 -> 16.452007 | N57: =F57/B57 -> 0.53113184 | O57: =E57/D57 -> 4.9774356e-05 | P57: =F57/E57 -> 8314.3333 | Q57: =B57/E57 -> 15653.992 | R57: =B57/G57 -> 218.93695
A58: 万相台 | B58: =SUM(万相台!B102:B132) -> 12814.29 | C58: =SUM(万相台!C102:C132) -> 913809 | D58: =SUM(万相台!D102:D132) -> 13322 | E58: =SUM(万相台!E102:E132) -> 5 | F58: =SUM(万相台!F102:F132) -> 75770 | G58: =SUM(万相台!G102:G132) -> 242 | H58: =SUM(万相台!H102:H132) -> 83 | J58: =H58+I58 -> 83 | K58: =D58/C58 -> 0.014578539 | L58: =B58/D58 -> 0.96188936 | M58: =(B58/C58)*1000 -> 14.022941 | N58: =F58/B58 -> 5.91293 | O58: =E58/D58 -> 0.00037531902 | P58: =F58/E58 -> 15154 | Q58: =B58/E58 -> 2562.858 | R58: =B58/G58 -> 52.951612
A59: 总计 | B59: =SUM(B55:B58) -> 231924.3 | C59: =SUM(C55:C58) -> 6926589 | D59: =SUM(D55:D58) -> 157093 | E59: =SUM(E55:E58) -> 37 | F59: =SUM(F55:F58) -> 535912 | G59: =SUM(G55:G58) -> 1902 | H59: =SUM(H55:H58) -> 1049 | I59: =SUM(I55:I58) -> 398 | J59: =H59+I59 -> 1447 | K59: =D59/C59 -> 0.022679706 | L59: =B59/D59 -> 1.4763503 | M59: =(B59/C59)*1000 -> 33.483191 | N59: =F59/B59 -> 2.3107194 | O59: =E59/D59 -> 0.00023552927 | P59: =F59/E59 -> 14484.108 | Q59: =B59/E59 -> 6268.2245 | R59: =B59/G59 -> 121.93707
A63: 2024年
A64: 1月 | B64: Cost 花费 | C64: IMP 展示 | D64: Click 点击 | E64: Order 订单 | F64: Sales 销量 | G64: ShoppingCart 加入购物车 | H64: Bookmark-Product 宝贝收藏 | I64: Bookmark-Store 店铺收藏 | J64: 总收藏数 | K64: CTR 点击率 | L64: CPC 点击成本 | M64: CPM 千次展现成本 | N64: ROI 投资回报率 | O64: CVR 点击转化率 | P64: ASP 订单均价 | Q64: Cporder 订单成本 | R64: CPshopping cart 加购成本
A65: 明星店铺 | B65: =SUM(明星店铺!B645:B675) -> 4413.62 | C65: =SUM(明星店铺!C645:C675) -> 5217 | D65: =SUM(明星店铺!D645:D675) -> 1813 | E65: =SUM(明星店铺!E645:E675) -> 8 | F65: =SUM(明星店铺!F645:F675) -> 118804 | G65: =SUM(明星店铺!G645:G675) -> 442 | H65: =SUM(明星店铺!H645:H675) -> 43 | I65: =SUM(明星店铺!I645:I675) -> 117 | J65: =H65+I65 -> 160 | K65: =D65/C65 -> 0.34751773 | L65: =B65/D65 -> 2.4344291 | M65: =(B65/C65)*1000 -> 846.00728 | N65: =F65/B65 -> 26.917587 | O65: =E65/D65 -> 0.0044125758 | P65: =F65/E65 -> 14850.5 | Q65: =B65/E65 -> 551.7025 | R65: =B65/G65 -> 9.9855656
A66: 直通车 | B66: =SUM(直通车!B645:B675) -> 64544.95 | C66: =SUM(直通车!C645:C675) -> 163594 | D66: =SUM(直通车!D645:D675) -> 15532 | E66: =SUM(直通车!E645:E675) -> 5 | F66: =SUM(直通车!F645:F675) -> 54251 | G66: =SUM(直通车!G645:G675) -> 749 | H66: =SUM(直通车!H645:H675) -> 148 | I66: =SUM(直通车!I645:I675) -> 124 | J66: =H66+I66 -> 272 | K66: =D66/C66 -> 0.094942357 | L66: =B66/D66 -> 4.155611 | M66: =(B66/C66)*1000 -> 394.5435 | N66: =F66/B66 -> 0.84051502 | O66: =E66/D66 -> 0.00032191604 | P66: =F66/E66 -> 10850.2 | Q66: =B66/E66 -> 12908.99 | R66: =B66/G66 -> 86.174833
A67: 引力魔方 | B67: =SUM(引力魔方!B544:B574) -> 37588.65 | C67: =SUM(引力魔方!C544:C574) -> 31095835 | D67: =SUM(引力魔方!D544:D574) -> 188677 | E67: =SUM(引力魔方!E544:E574) -> 0 | F67: =SUM(引力魔方!F544:F574) -> 0 | G67: =SUM(引力魔方!G544:G574) -> 280 | H67: =SUM(引力魔方!H544:H574) -> 169 | I67: =SUM(引力魔方!I544:I574) -> 43 | J67: =H67+I67 -> 212 | K67: =D67/C67 -> 0.0060675972 | L67: =B67/D67 -> 0.19922222 | M67: =(B67/C67)*1000 -> 1.2088001 | N67: =F67/B67 -> 0 | O67: =E67/D67 -> 0 | P67: =F67/E67 -> #DIV/0! | Q67: =B67/E67 -> #DIV/0! | R67: =B67/G67 -> 134.24518
A68: 万相台 | B68: =SUM(万相台!B133:B163) -> 12333.92 | C68: =SUM(万相台!C133:C163) -> 843593 | D68: =SUM(万相台!D133:D163) -> 11679 | E68: =SUM(万相台!E133:E163) -> 11 | F68: =SUM(万相台!F133:F163) -> 155509 | G68: =SUM(万相台!G133:G163) -> 187 | H68: =SUM(万相台!H133:H163) -> 40 | J68: =H68+I68 -> 40 | K68: =D68/C68 -> 0.013844354 | L68: =B68/D68 -> 1.0560767 | M68: =(B68/C68)*1000 -> 14.6207 | N68: =(B68/C68)*1000 -> 14.6207 | O68: =E68/D68 -> 0.00094186146 | P68: =F68/E68 -> 14137.182 | Q68: =B68/E68 -> 1121.2655 | R68: =B68/G68 -> 65.956791
A69: 总计 | B69: =SUM(B65:B68) -> 118881.14 | C69: =SUM(C65:C68) -> 32108239 | D69: =SUM(D65:D68) -> 217701 | E69: =SUM(E65:E68) -> 24 | F69: =SUM(F65:F68) -> 328564 | G69: =SUM(G65:G68) -> 1658 | H69: =SUM(H65:H68) -> 400 | I69: =SUM(I65:I68) -> 284 | J69: =H69+I69 -> 684 | K69: =D69/C69 -> 0.0067802224 | L69: =B69/D69 -> 0.54607531 | M69: =(B69/C69)*1000 -> 3.702512 | N69: =F69/B69 -> 2.7638026 | O69: =E69/D69 -> 0.00011024295 | P69: =F69/E69 -> 13690.167 | Q69: =B69/E69 -> 4953.3808 | R69: =B69/G69 -> 71.701532
A71: 2月 | B71: Cost 花费 | C71: IMP 展示 | D71: Click 点击 | E71: Order 订单 | F71: Sales 销量 | G71: ShoppingCart 加入购物车 | H71: Bookmark-Product 宝贝收藏 | I71: Bookmark-Store 店铺收藏 | J71: 总收藏数 | K71: CTR 点击率 | L71: CPC 点击成本 | M71: CPM 千次展现成本 | N71: ROI 投资回报率 | O71: CVR 点击转化率 | P71: ASP 订单均价 | Q71: Cporder 订单成本 | R71: CPshopping cart 加购成本 | S71: 收藏加购数 | U71: 收藏加购 成本
A72: 明星店铺 | B72: =SUM(明星店铺!B676:B704) -> 5341.79 | C72: =SUM(明星店铺!C676:C704) -> 7780 | D72: =SUM(明星店铺!D676:D704) -> 3160 | E72: =SUM(明星店铺!E676:E704) -> 22 | F72: =SUM(明星店铺!F676:F704) -> 336056 | G72: =SUM(明星店铺!G676:G704) -> 812 | H72: =SUM(明星店铺!H676:H704) -> 56 | I72: =SUM(明星店铺!I676:I704) -> 252 | J72: =H72+I72 -> 308 | K72: =D72/C72 -> 0.40616967 | L72: =B72/D72 -> 1.6904399 | M72: =(B72/C72)*1000 -> 686.6054 | N72: =F72/B72 -> 62.910747 | O72: =E72/D72 -> 0.0069620253 | P72: =F72/E72 -> 15275.273 | Q72: =B72/E72 -> 242.80864 | R72: =B72/G72 -> 6.5785591 | S72: =G72+J72 -> 1120 | U72: =B72/S72 -> 4.7694554
A73: 直通车 | B73: =SUM(直通车!B676:B704) -> 41071.2 | C73: =SUM(直通车!C676:C704) -> 120151 | D73: =SUM(直通车!D676:D704) -> 9048 | E73: =SUM(直通车!E676:E704) -> 9 | F73: =SUM(直通车!F676:F704) -> 102983 | G73: =SUM(直通车!G676:G704) -> 590 | H73: =SUM(直通车!H676:H704) -> 79 | I73: =SUM(直通车!I676:I704) -> 115 | J73: =H73+I73 -> 194 | K73: =D73/C73 -> 0.075305241 | L73: =B73/D73 -> 4.5392573 | M73: =(B73/C73)*1000 -> 341.82986 | N73: =F73/B73 -> 2.5074261 | O73: =E73/D73 -> 0.00099469496 | P73: =F73/E73 -> 11442.556 | Q73: =B73/E73 -> 4563.4667 | R73: =B73/G73 -> 69.612203 | S73: =G73+J73 -> 784 | U73: =B73/S73 -> 52.386735
A74: 引力魔方 | B74: =SUM(引力魔方!B575:B603) -> 14419.61 | C74: =SUM(引力魔方!C575:C603) -> 49785339 | D74: =SUM(引力魔方!D575:D603) -> 147329 | E74: =SUM(引力魔方!E575:E603) -> 0 | F74: =SUM(引力魔方!F575:F603) -> 0 | G74: =SUM(引力魔方!G575:G603) -> 85 | H74: =SUM(引力魔方!H575:H603) -> 82 | I74: =SUM(引力魔方!I575:I603) -> 36 | J74: =H74+I74 -> 118 | K74: =D74/C74 -> 0.0029592849 | L74: =B74/D74 -> 0.097873535 | M74: =(B74/C74)*1000 -> 0.28963567 | N74: =F74/B74 -> 0 | O74: =E74/D74 -> 0 | P74: =F74/E74 -> #DIV/0! | Q74: =B74/E74 -> #DIV/0! | R74: =B74/G74 -> 169.64247 | S74: =G74+J74 -> 203 | U74: =B74/S74 -> 71.032562
A75: 万相台 | B75: =SUM(万相台!B164:B192) -> 5781.09 | C75: =SUM(万相台!C164:C192) -> 827507 | D75: =SUM(万相台!D164:D192) -> 16623 | E75: =SUM(万相台!E164:E192) -> 1 | F75: =SUM(万相台!F164:F192) -> 15880 | G75: =SUM(万相台!G164:G192) -> 123 | H75: =SUM(万相台!H164:H192) -> 67 | J75: =H75+I75 -> 67 | K75: =D75/C75 -> 0.020088048 | L75: =B75/D75 -> 0.34777657 | M75: =(B75/C75)*1000 -> 6.9861524 | N75: =(B75/C75)*1000 -> 6.9861524 | O75: =E75/D75 -> 6.0157613e-05 | P75: =F75/E75 -> 15880 | Q75: =B75/E75 -> 5781.09 | R75: =B75/G75 -> 47.000732 | S75: =G75+J75 -> 190 | U75: =B75/S75 -> 30.426789
A76: 总计 | B76: =SUM(B72:B75) -> 66613.69 | C76: =SUM(C72:C75) -> 50740777 | D76: =SUM(D72:D75) -> 176160 | E76: =SUM(E72:E75) -> 32 | F76: =SUM(F72:F75) -> 454919 | G76: =SUM(G72:G75) -> 1610 | H76: =SUM(H72:H75) -> 284 | I76: =SUM(I72:I75) -> 403 | J76: =H76+I76 -> 687 | K76: =D76/C76 -> 0.0034717639 | L76: =B76/D76 -> 0.37814311 | M76: =(B76/C76)*1000 -> 1.3128236 | N76: =F76/B76 -> 6.8292118 | O76: =E76/D76 -> 0.00018165304 | P76: =F76/E76 -> 14216.219 | Q76: =B76/E76 -> 2081.6778 | R76: =B76/G76 -> 41.374963 | S76: =G76+J76 -> 2297 | U76: =B76/S76 -> 29.0003
A79: 3月 | B79: Cost 花费 | C79: IMP 展示 | D79: Click 点击 | E79: Order 订单 | F79: Sales 销量 | G79: ShoppingCart 加入购物车 | H79: Bookmark-Product 宝贝收藏 | I79: Bookmark-Store 店铺收藏 | J79: 总收藏数 | K79: CTR 点击率 | L79: CPC 点击成本 | M79: CPM 千次展现成本 | N79: ROI 投资回报率 | O79: CVR 点击转化率 | P79: ASP 订单均价 | Q79: Cporder 订单成本 | R79: CPshopping cart 加购成本 | S79: 收藏加购数 | T79: 收藏加购 环比 | U79: 收藏加购 成本 | V79: 花费环比 | W79: 点击占比 | X79: 加购环比 | Y79: 成交环比 | Z79: 加购成本 环比 | AA79: 收藏加购 成本环比 | AB79: 花费占比
A80: 明星店铺 | B80: =SUM(明星店铺!B705:B735) -> 7518.61 | C80: =SUM(明星店铺!C705:C735) -> 9372 | D80: =SUM(明星店铺!D705:D735) -> 3804 | E80: =SUM(明星店铺!E705:E735) -> 60 | F80: =SUM(明星店铺!F705:F735) -> 909870 | G80: =SUM(明星店铺!G705:G735) -> 1034 | H80: =SUM(明星店铺!H705:H735) -> 74 | I80: =SUM(明星店铺!I705:I735) -> 234 | J80: =H80+I80 -> 308 | K80: =D80/C80 -> 0.40588988 | L80: =B80/D80 -> 1.9765011 | M80: =(B80/C80)*1000 -> 802.24178 | N80: =F80/B80 -> 121.01572 | O80: =E80/D80 -> 0.015772871 | P80: =F80/E80 -> 15164.5 | Q80: =B80/E80 -> 125.31017 | R80: =B80/G80 -> 7.271383 | S80: =G80+J80 -> 1342 | T80: =(S80-S72)/S72 -> 0.19821429 | U80: =B80/S80 -> 5.602541 | V80: =(B80-B72)/B72 -> 0.4075076 | W80: =D80/$D$84 -> 0.0068744048 | X80: =(G80-G72)/G72 -> 0.27339901 | Y80: =(F80-F72)/F72 -> 1.7074952 | Z80: =(R80-R72)/R72 -> 0.10531544 | AA80: =(U80-U72)/U72 -> 0.17467102 | AB80: =B80/B84 -> 0.036186311
A81: 直通车 | B81: =SUM(直通车!B705:B735) -> 79734.93 | C81: =SUM(直通车!C705:C735) -> 305903 | D81: =SUM(直通车!D705:D735) -> 16284 | E81: =SUM(直通车!E705:E735) -> 57 | F81: =SUM(直通车!F705:F735) -> 945831 | G81: =SUM(直通车!G705:G735) -> 1117 | H81: =SUM(直通车!H705:H735) -> 161 | I81: =SUM(直通车!I705:I735) -> 188 | J81: =H81+I81 -> 349 | K81: =D81/C81 -> 0.053232561 | L81: =B81/D81 -> 4.8965199 | M81: =(B81/C81)*1000 -> 260.65429 | N81: =F81/B81 -> 11.862191 | O81: =E81/D81 -> 0.0035003685 | P81: =F81/E81 -> 16593.526 | Q81: =B81/E81 -> 1398.8584 | R81: =B81/G81 -> 71.383107 | S81: =G81+J81 -> 1466 | T81: =(S81-S73)/S73 -> 0.86989796 | U81: =B81/S81 -> 54.389447 | V81: =(B81-B73)/B73 -> 0.94138301 | W81: =D81/$D$84 -> 0.029427657 | X81: =(G81-G73)/G73 -> 0.89322034 | Y81: =(F81-F73)/F73 -> 8.1843411 | Z81: =(R81-R73)/R73 -> 0.02543955 | AA81: =(U81-U73)/U73 -> 0.038229388 | AB81: =B81/B84 -> 0.38375617
A82: 引力魔方 | B82: =SUM(引力魔方!B604:B634) -> 46814.25 | C82: =SUM(引力魔方!C604:C634) -> 66709402 | D82: =SUM(引力魔方!D604:D634) -> 335835 | E82: =SUM(引力魔方!E604:E634) -> 4 | F82: =SUM(引力魔方!F604:F634) -> 73400 | G82: =SUM(引力魔方!G604:G634) -> 250 | H82: =SUM(引力魔方!H604:H634) -> 320 | I82: =SUM(引力魔方!I604:I634) -> 52 | J82: =H82+I82 -> 372 | K82: =D82/C82 -> 0.0050342979 | L82: =B82/D82 -> 0.13939658 | M82: =(B82/C82)*1000 -> 0.7017639 | N82: =F82/B82 -> 1.5678987 | O82: =E82/D82 -> 1.1910611e-05 | P82: =F82/E82 -> 18350 | Q82: =B82/E82 -> 11703.562 | R82: =B82/G82 -> 187.257 | S82: =G82+J82 -> 622 | T82: =(S82-S74)/S74 -> 2.0640394 | U82: =B82/S82 -> 75.264068 | V82: =(B82-B74)/B74 -> 2.2465684 | W82: =D82/$D$84 -> 0.60690476 | X82: =(G82-G74)/G74 -> 1.9411765 | Y82: =IF(F74=0,100%,(F82-F74)/F74) -> 1 | Z82: =(R82-R74)/R74 -> 0.10383325 | AA82: =(U82-U74)/U74 -> 0.059571355 | AB82: =B82/B84 -> 0.22531226
A83: 万相台 | B83: =SUM(万相台!B193:B223) -> 73707.19 | C83: =SUM(万相台!C193:C223) -> 19398232 | D83: =SUM(万相台!D193:D223) -> 197434 | E83: =SUM(万相台!E193:E223) -> 42 | F83: =SUM(万相台!F193:F223) -> 703035 | G83: =SUM(万相台!G193:G223) -> 1507 | H83: =SUM(万相台!H193:H223) -> 3150 | I83: =SUM(万相台!J193:J223) -> 0.42727885 | J83: =H83+I83 -> 3150.4273 | K83: =D83/C83 -> 0.010177938 | L83: =B83/D83 -> 0.37332572 | M83: =(B83/C83)*1000 -> 3.799686 | N83: =F83/B83 -> 9.5382147 | O83: =E83/D83 -> 0.00021272932 | P83: =F83/E83 -> 16738.929 | Q83: =B83/E83 -> 1754.9331 | R83: =B83/G83 -> 48.909881 | S83: =G83+J83 -> 4657.4273 | T83: =(S83-S75)/S75 -> 23.512775 | U83: =B83/S83 -> 15.825731 | V83: =(B83-B75)/B75 -> 11.749705 | W83: =D83/$D$84 -> 0.35679317 | X83: =(G83-G75)/G75 -> 11.252033 | Y83: =(F83-F75)/F75 -> 43.271725 | Z83: =(R83-R75)/R75 -> 0.040619556 | AA83: =(U83-U75)/U75 -> -0.4798751 | AB83: =B83/B84 -> 0.35474526
A84: 总计 | B84: =SUM(B80:B83) -> 207774.98 | C84: =SUM(C80:C83) -> 86422909 | D84: =SUM(D80:D83) -> 553357 | E84: =SUM(E80:E83) -> 163 | F84: =SUM(F80:F83) -> 2632136 | G84: =SUM(G80:G83) -> 3908 | H84: =SUM(H80:H83) -> 3705 | I84: =SUM(I80:I83) -> 474.42728 | J84: =H84+I84 -> 4179.4273 | K84: =D84/C84 -> 0.0064028972 | L84: =B84/D84 -> 0.37548089 | M84: =(B84/C84)*1000 -> 2.4041655 | N84: =F84/B84 -> 12.668205 | O84: =E84/D84 -> 0.00029456571 | P84: =F84/E84 -> 16148.074 | Q84: =B84/E84 -> 1274.6931 | R84: =B84/G84 -> 53.166576 | S84: =G84+J84 -> 8087.4273 | T84: =(S84-S76)/S76 -> 2.5208652 | U84: =B84/S84 -> 25.69111 | V84: =(B84-B76)/B76 -> 2.1191033 | W84: =D84/$D$84 -> 1 | X84: =(G84-G76)/G76 -> 1.4273292 | Y84: =(F84-F76)/F76 -> 4.7859443 | Z84: =(R84-R76)/R76 -> 0.28499394 | AA84: =(U84-U76)/U76 -> -0.11410885 | AB84: =B84/B84 -> 1
A87: 4月 | B87: Cost 花费 | C87: IMP 展示 | D87: Click 点击 | E87: Order 订单 | F87: Sales 销量 | G87: ShoppingCart 加入购物车 | H87: Bookmark-Product 宝贝收藏 | I87: Bookmark-Store 店铺收藏 | J87: 总收藏数 | K87: CTR 点击率 | L87: CPC 点击成本 | M87: CPM 千次展现成本 | N87: ROI 投资回报率 | O87: CVR 点击转化率 | P87: ASP 订单均价 | Q87: Cporder 订单成本 | R87: CPshopping cart 加购成本 | S87: 收藏加购数 | T87: 收藏加购 环比 | U87: 收藏加购 成本 | V87: 花费环比 | W87: 点击占比 | X87: 加购环比 | Y87: 成交环比 | Z87: 加购成本 环比 | AA87: 收藏加购 成本环比 | AB87: 花费占比
A88: 明星店铺 | B88: =SUM(明星店铺!B736:B765) -> 6488.18 | C88: =SUM(明星店铺!C736:C765) -> 7851 | D88: =SUM(明星店铺!D736:D765) -> 2955 | E88: =SUM(明星店铺!E736:E765) -> 18 | F88: =SUM(明星店铺!F736:F765) -> 276039 | G88: =SUM(明星店铺!G736:G765) -> 783 | H88: =SUM(明星店铺!H736:H756) -> 44 | I88: =SUM(明星店铺!I736:I765) -> 145 | J88: =H88+I88 -> 189 | K88: =D88/C88 -> 0.37638517 | L88: =B88/D88 -> 2.1956616 | M88: =(B88/C88)*1000 -> 826.41447 | N88: =F88/B88 -> 42.544905 | O88: =E88/D88 -> 0.0060913706 | P88: =IF(E88=0,"0",F88/E88) -> 15335.5 | Q88: =IF(E88=0,"0",B88/E88) -> 360.45444 | R88: =B88/G88 -> 8.2863091 | S88: =G88+J88 -> 972 | T88: =(S88-S80)/S80 -> -0.2757079 | U88: =B88/S88 -> 6.6750823 | V88: =(B88-B80)/B80 -> -0.1370506 | W88: =D88/$D$92 -> 0.0073047554 | X88: =(G88-G80)/G80 -> -0.24274662 | Y88: =(F88-F80)/F80 -> -0.6966171 | Z88: =(R88-R80)/R80 -> 0.13957814 | AA88: =(U88-U80)/U80 -> 0.19143837 | AB88: =B88/B92 -> 0.040434676
A89: 直通车 | B89: =SUM(直通车!B736:B765) -> 55187.14 | C89: =SUM(直通车!C736:C765) -> 217527 | D89: =SUM(直通车!D736:D765) -> 13706 | E89: =SUM(直通车!E736:E765) -> 9 | F89: =SUM(直通车!F736:F765) -> 196570 | G89: =SUM(直通车!G736:G765) -> 945 | H89: =SUM(直通车!H736:H765) -> 95 | I89: =SUM(直通车!I736:I765) -> 115 | J89: =H89+I89 -> 210 | K89: =D89/C89 -> 0.06300827 | L89: =B89/D89 -> 4.026495 | M89: =(B89/C89)*1000 -> 253.70248 | N89: =F89/B89 -> 3.5618805 | O89: =E89/D89 -> 0.00065664672 | P89: =IF(E89=0,"0",F89/E89) -> 21841.111 | Q89: =IF(E89=0,"0",B89/E89) -> 6131.9044 | R89: =B89/G89 -> 58.39909 | S89: =G89+J89 -> 1155 | T89: =(S89-S81)/S81 -> -0.21214188 | U89: =B89/S89 -> 47.781074 | V89: =(B89-B81)/B81 -> -0.30786746 | W89: =D89/$D$92 -> 0.033881211 | X89: =(G89-G81)/G81 -> -0.15398389 | Y89: =(F89-F81)/F81 -> -0.79217217 | Z89: =(R89-R81)/R81 -> -0.18189201 | AA89: =(U89-U81)/U81 -> -0.12150103 | AB89: =B89/B92 -> 0.34392913
A90: 引力魔方 | B90: =SUM(引力魔方!B635:B664) -> 37490.77 | C90: =SUM(引力魔方!C635:C664) -> 43486150 | D90: =SUM(引力魔方!D635:D664) -> 167971 | E90: =SUM(引力魔方!E635:E664) -> 2 | F90: =SUM(引力魔方!F635:F664) -> 20393.68 | G90: =SUM(引力魔方!G635:G664) -> 247 | H90: =SUM(引力魔方!H635:H664) -> 899 | I90: =SUM(引力魔方!I635:I664) -> 54 | J90: =H90+I90 -> 953 | K90: =D90/C90 -> 0.0038626321 | L90: =B90/D90 -> 0.22319787 | M90: =(B90/C90)*1000 -> 0.86213128 | N90: =F90/B90 -> 0.54396535 | O90: =E90/D90 -> 1.1906817e-05 | P90: =IF(E90=0,"0",F90/E90) -> 10196.84 | Q90: =IF(E90=0,"0",B90/E90) -> 18745.385 | R90: =B90/G90 -> 151.78449 | S90: =G90+J90 -> 1200 | T90: =(S90-S82)/S82 -> 0.92926045 | U90: =B90/S90 -> 31.242308 | V90: =(B90-B82)/B82 -> -0.19915902 | W90: =D90/$D$92 -> 0.41522405 | X90: =(G90-G82)/G82 -> -0.012 | Y90: =(F90-F82)/F82 -> -0.72215695 | Z90: =(R90-R82)/R82 -> -0.1894322 | AA90: =(U90-U82)/U82 -> -0.58489742 | AB90: =B90/B92 -> 0.23364443
A91: 万相台 | B91: =SUM(万相台!B224:B253) -> 61294.7 | C91: =SUM(万相台!C224:C253) -> 18951479 | D91: =SUM(万相台!D224:D253) -> 219899 | E91: =SUM(万相台!E224:E253) -> 31 | F91: =SUM(万相台!F224:F253) -> 464453.48 | G91: =SUM(万相台!G224:G253) -> 1037 | H91: =SUM(万相台!H224:H253) -> 3263 | I91: =SUM(万相台!I224:I253) -> 394 | J91: =H91+I91 -> 3657 | K91: =D91/C91 -> 0.011603263 | L91: =B91/D91 -> 0.27874024 | M91: =(B91/C91)*1000 -> 3.2342964 | N91: =F91/B91 -> 7.577384 | O91: =E91/D91 -> 0.00014097381 | P91: =IF(E91=0,"0",F91/E91) -> 14982.37 | Q91: =IF(E91=0,"0",B91/E91) -> 1977.2484 | R91: =B91/G91 -> 59.107715 | S91: =G91+J91 -> 4694 | T91: =(S91-S83)/S83 -> 0.0078525587 | U91: =B91/S91 -> 13.058095 | V91: =(B91-B83)/B83 -> -0.1684027 | W91: =D91/$D$92 -> 0.54358998 | X91: =(G91-G83)/G83 -> -0.3118779 | Y91: =(F91-F83)/F83 -> -0.33935938 | Z91: =(R91-R83)/R83 -> 0.20850253 | AA91: =(U91-U83)/U83 -> -0.17488199 | AB91: =B91/B92 -> 0.38199176
A92: 总计 | B92: =SUM(B88:B91) -> 160460.79 | C92: =SUM(C88:C91) -> 62663007 | D92: =SUM(D88:D91) -> 404531 | E92: =SUM(E88:E91) -> 60 | F92: =SUM(F88:F91) -> 957456.16 | G92: =SUM(G88:G91) -> 3012 | H92: =SUM(H88:H91) -> 4301 | I92: =SUM(I88:I91) -> 708 | J92: =H92+I92 -> 5009 | K92: =D92/C92 -> 0.0064556589 | L92: =B92/D92 -> 0.39665882 | M92: =(B92/C92)*1000 -> 2.5606941 | N92: =F92/B92 -> 5.9669167 | O92: =E92/D92 -> 0.00014831991 | P92: =F92/E92 -> 15957.603 | Q92: =B92/E92 -> 2674.3465 | R92: =B92/G92 -> 53.273835 | S92: =G92+J92 -> 8021 | T92: =(S92-S84)/S84 -> -0.0082136477 | U92: =B92/S92 -> 20.005085 | V92: =(B92-B84)/B84 -> -0.22771842 | X92: =(G92-G84)/G84 -> -0.22927329 | Y92: =(F92-F84)/F84 -> -0.63624366 | Z92: =(R92-R84)/R84 -> 0.0020174029 | AA92: =(U92-U84)/U84 -> -0.22132264 | AB92: =B92/B92 -> 1
A93: 环比3月 | B93: =(B92-B84)/B84 -> -0.22771842 | C93: =(C92-C84)/C84 -> -0.27492597 | D93: =(D92-D84)/D84 -> -0.26895115 | E93: =(E92-E84)/E84 -> -0.63190184 | F93: =(F92-F84)/F84 -> -0.63624366 | G93: =(G92-G84)/G84 -> -0.22927329 | H93: =(H92-H84)/H84 -> 0.1608637 | I93: =(I92-I84)/I84 -> 0.49232566 | ... R93: =(R92-R84)/R84 -> 0.0020174029
A95: 5月 | B95: Cost 花费 | C95: IMP 展示 | D95: Click 点击 | E95: Order 订单 | F95: Sales 销量 | G95: ShoppingCart 加入购物车 | H95: Bookmark-Product 宝贝收藏 | I95: Bookmark-Store 店铺收藏 | J95: 总收藏数 | K95: CTR 点击率 | L95: CPC 点击成本 | M95: CPM 千次展现成本 | N95: ROI 投资回报率 | O95: CVR 点击转化率 | P95: ASP 订单均价 | Q95: Cporder 订单成本 | R95: CPshopping cart 加购成本 | S95: 收藏加购数 | T95: 收藏加购 环比 | U95: 收藏加购 成本 | V95: 花费环比 | W95: 点击占比 | X95: 加购环比 | Y95: 成交环比 | Z95: 加购成本 环比 | AA95: 收藏加购 成本环比 | AB95: 花费占比
A96: 明星店铺 | B96: =SUM(明星店铺!B766:B796) -> 11156.3 | C96: =SUM(明星店铺!C766:C796) -> 12760 | D96: =SUM(明星店铺!D766:D796) -> 6320 | E96: =SUM(明星店铺!E766:E796) -> 83 | F96: =SUM(明星店铺!F766:F796) -> 891276.81 | G96: =SUM(明星店铺!G766:G796) -> 1643 | H96: =SUM(明星店铺!H766:H796) -> 214 | I96: =SUM(明星店铺!I766:I796) -> 459 | J96: =H96+I96 -> 673 | K96: =D96/C96 -> 0.49529781 | L96: =B96/D96 -> 1.7652373 | M96: =(B96/C96)*1000 -> 874.31818 | N96: =F96/B96 -> 79.89 | O96: =E96/D96 -> 0.013132911 | P96: =IF(E96=0,"0",F96/E96) -> 10738.275 | Q96: =IF(E96=0,"0",B96/E96) -> 134.41325 | R96: =B96/G96 -> 6.7902009 | S96: =G96+J96 -> 2316 | T96: =(S96-S88)/S88 -> 1.382716 | U96: =B96/S96 -> 4.8170553 | V96: =(B96-B88)/B88 -> 0.71948066 | W96: =D96/$D$100 -> 0.019114618 | X96: =(G96-G88)/G88 -> 1.0983397 | Y96: =(F96-F88)/F88 -> 2.2288076 | Z96: =(R96-R88)/R88 -> -0.18055182 | AA96: =(U96-U88)/U88 -> -0.27835268 | AB96: =B96/B100 -> 0.060413856
A97: 直通车 | B97: =SUM(直通车!B766:B796) -> 66820.87 | C97: =SUM(直通车!C766:C796) -> 220604 | D97: =SUM(直通车!D766:D796) -> 16317 | E97: =SUM(直通车!E766:E796) -> 64 | F97: =SUM(直通车!F766:F796) -> 864387 | G97: =SUM(直通车!G766:G796) -> 1397 | H97: =SUM(直通车!H766:H796) -> 170 | I97: =SUM(直通车!I766:I796) -> 209 | J97: =H97+I97 -> 379 | K97: =D97/C97 -> 0.073965114 | L97: =B97/D97 -> 4.0951688 | M97: =(B97/C97)*1000 -> 302.89963 | N97: =F97/B97 -> 12.935884 | O97: =E97/D97 -> 0.0039222896 | P97: =IF(E97=0,"0",F97/E97) -> 13506.047 | Q97: =IF(E97=0,"0",B97/E97) -> 1044.0761 | R97: =B97/G97 -> 47.831689 | S97: =G97+J97 -> 1776 | T97: =(S97-S89)/S89 -> 0.53766234 | U97: =B97/S97 -> 37.624364 | V97: =(B97-B89)/B89 -> 0.21080509 | W97: =D97/$D$100 -> 0.049350194 | X97: =(G97-G89)/G89 -> 0.47830688 | Y97: =(F97-F89)/F89 -> 3.3973495 | Z97: =(R97-R89)/R89 -> -0.18095146 | AA97: =(U97-U89)/U89 -> -0.21256764 | AB97: =B97/B100 -> 0.36184994
A98: 引力魔方 | B98: =SUM(引力魔方!B665:B695) -> 31305.85 | C98: =SUM(引力魔方!C665:C695) -> 35598553 | D98: =SUM(引力魔方!D665:D695) -> 126129 | E98: =SUM(引力魔方!E665:E695) -> 14 | F98: =SUM(引力魔方!F665:F695) -> 151899 | G98: =SUM(引力魔方!G665:G695) -> 358 | H98: =SUM(引力魔方!H665:H695) -> 1315 | I98: =SUM(引力魔方!I665:I695) -> 46 | J98: =H98+I98 -> 1361 | K98: =D98/C98 -> 0.0035430935 | L98: =B98/D98 -> 0.24820501 | M98: =(B98/C98)*1000 -> 0.87941355 | N98: =F98/B98 -> 4.8520963 | O98: =E98/D98 -> 0.00011099747 | P98: =IF(E98=0,"0",F98/E98) -> 10849.929 | Q98: =IF(E98=0,"0",B98/E98) -> 2236.1321 | R98: =B98/G98 -> 87.446508 | S98: =G98+J98 -> 1719 | T98: =(S98-S90)/S90 -> 0.4325 | U98: =B98/S98 -> 18.211664 | V98: =(B98-B90)/B90 -> -0.16497181 | W98: =D98/$D$100 -> 0.38147273 | X98: =(G98-G90)/G90 -> 0.44939271 | Y98: =(F98-F90)/F90 -> 6.4483369 | Z98: =(R98-R90)/R90 -> -0.4238772 | AA98: =(U98-U90)/U90 -> -0.41708328 | AB98: =B98/B100 -> 0.16952817
A99: 万相台 | B99: =SUM(万相台!B254:B284) -> 75381.57 | C99: =SUM(万相台!C254:C284) -> 25259836 | D99: =SUM(万相台!D254:D284) -> 181871 | E99: =SUM(万相台!E254:E284) -> 103 | F99: =SUM(万相台!F254:F284) -> 1246048 | G99: =SUM(万相台!G254:G284) -> 1442 | H99: =SUM(万相台!H254:H284) -> 5099 | I99: =SUM(万相台!I254:I284) -> 390 | J99: =H99+I99 -> 5489 | K99: =D99/C99 -> 0.0072000072 | L99: =B99/D99 -> 0.41447823 | M99: =(B99/C99)*1000 -> 2.9842462 | N99: =F99/B99 -> 16.529876 | O99: =E99/D99 -> 0.00056633548 | P99: =IF(E99=0,"0",F99/E99) -> 12097.553 | Q99: =IF(E99=0,"0",B99/E99) -> 731.8599 | R99: =B99/G99 -> 52.275707 | S99: =G99+J99 -> 6931 | T99: =(S99-S91)/S91 -> 0.47656583 | U99: =B99/S99 -> 10.876002 | V99: =(B99-B91)/B91 -> 0.22982199 | W99: =D99/$D$100 -> 0.55006246 | X99: =(G99-G91)/G91 -> 0.39054966 | Y99: =(F99-F91)/F91 -> 1.6828263 | Z99: =(R99-R91)/R91 -> -0.11558571 | AA99: =(U99-U91)/U91 -> -0.16710656 | AB99: =B99/B100 -> 0.40820804
A100: 总计 | B100: =SUM(B96:B99) -> 184664.59 | C100: =SUM(C96:C99) -> 61091753 | D100: =SUM(D96:D99) -> 330637 | E100: =SUM(E96:E99) -> 264 | F100: =SUM(F96:F99) -> 3153610.8 | G100: =SUM(G96:G99) -> 4840 | H100: =SUM(H96:H99) -> 6798 | I100: =SUM(I96:I99) -> 1104 | J100: =H100+I100 -> 7902 | K100: =D100/C100 -> 0.005412138 | L100: =B100/D100 -> 0.55851157 | M100: =(B100/C100)*1000 -> 3.0227417 | N100: =F100/B100 -> 17.077507 | O100: =E100/D100 -> 0.00079845873 | P100: =F100/E100 -> 11945.495 | Q100: =B100/E100 -> 699.48708 | R100: =B100/G100 -> 38.153841 | S100: =G100+J100 -> 12742 | T100: =(S100-S92)/S92 -> 0.58857998 | U100: =B100/S100 -> 14.492591 | V100: =(B100-B92)/B92 -> 0.15083934 | W100: =D100/$D$100 -> 1 | X100: =(G100-G92)/G92 -> 0.60690571 | Y100: =(F100-F92)/F92 -> 2.2937391 | Z100: =(R100-R92)/R92 -> -0.28381651 | AA100: =(U100-U92)/U92 -> -0.27555467 | AB100: =B100/B100 -> 1
A101: 环比4月 | B101: =(B100-B92)/B92 -> 0.15083934 | C101: =(C100-C92)/C92 -> -0.025074666 | D101: =(D100-D92)/D92 -> -0.18266585 | E101: =(E100-E92)/E92 -> 3.4 | F101: =(F100-F92)/F92 -> 2.2937391 | G101: =(G100-G92)/G92 -> 0.60690571 | H101: =(H100-H92)/H92 -> 0.58056266 | I101: =(I100-I92)/I92 -> 0.55932203 | ... R101: =(R100-R92)/R92 -> -0.28381651
A103: 6月 | B103: Cost 花费 | C103: IMP 展示 | D103: Click 点击 | E103: Order 订单 | F103: Sales 销量 | G103: ShoppingCart 加入购物车 | H103: Bookmark-Product 宝贝收藏 | I103: Bookmark-Store 店铺收藏 | J103: 总收藏数 | K103: CTR 点击率 | L103: CPC 点击成本 | M103: CPM 千次展现成本 | N103: ROI 投资回报率 | O103: CVR 点击转化率 | P103: ASP 订单均价 | Q103: Cporder 订单成本 | R103: CPshopping cart 加购成本 | S103: 收藏加购数 | T103: 收藏加购 环比 | U103: 收藏加购 成本 | V103: 花费环比 | W103: 点击占比 | X103: 加购环比 | Y103: 成交环比 | Z103: 加购成本 环比 | AA103: 收藏加购 成本环比 | AB103: 花费占比 | AC103: 费率
A104: 明星店铺 | B104: =SUM(明星店铺!B797:B826) -> 11255.25 | C104: =SUM(明星店铺!C797:C826) -> 10443 | D104: =SUM(明星店铺!D797:D826) -> 4663 | E104: =SUM(明星店铺!E797:E826) -> 94 | F104: =SUM(明星店铺!F797:F826) -> 1413047 | G104: =SUM(明星店铺!G797:G826) -> 1201 | H104: =SUM(明星店铺!H797:H826) -> 110 | I104: =SUM(明星店铺!I797:I826) -> 282 | J104: =H104+I104 -> 392 | K104: =D104/C104 -> 0.4465192 | L104: =B104/D104 -> 2.4137358 | M104: =(B104/C104)*1000 -> 1077.7794 | N104: =F104/B104 -> 125.54559 | O104: =E104/D104 -> 0.020158696 | P104: =IF(E104=0,"0",F104/E104) -> 15032.415 | Q104: =IF(E104=0,"0",B104/E104) -> 119.7367 | R104: =B104/G104 -> 9.3715654 | S104: =G104+J104 -> 1593 | T104: =(S104-S96)/S96 -> -0.31217617 | U104: =B104/S104 -> 7.0654426 | V104: =(B104-B96)/B96 -> 0.008869428 | W104: =D104/$D$108 -> 0.018651776 | X104: =(G104-G96)/G96 -> -0.26902009 | Y104: =(F104-F96)/F96 -> 0.58541879 | Z104: =(R104-R96)/R96 -> 0.38016026 | AA104: =(U104-U96)/U96 -> 0.46675555 | AB104: =B104/B108 -> 0.046838649
A105: 直通车 | B105: =SUM(直通车!B797:B826) -> 88875.43 | C105: =SUM(直通车!C797:C826) -> 385955 | D105: =SUM(直通车!D797:D826) -> 20004 | E105: =SUM(直通车!E797:E826) -> 52 | F105: =SUM(直通车!F797:F826) -> 663374 | G105: =SUM(直通车!G797:G826) -> 1324 | H105: =SUM(直通车!H797:H826) -> 164 | I105: =SUM(直通车!I797:I826) -> 173 | J105: =H105+I105 -> 337 | K105: =D105/C105 -> 0.051829877 | L105: =B105/D105 -> 4.4428829 | M105: =(B105/C105)*1000 -> 230.27407 | N105: =F105/B105 -> 7.4640877 | O105: =E105/D105 -> 0.0025994801 | P105: =IF(E105=0,"0",F105/E105) -> 12757.192 | Q105: =IF(E105=0,"0",B105/E105) -> 1709.1429 | R105: =B105/G105 -> 67.126458 | S105: =G105+J105 -> 1661 | T105: =(S105-S97)/S97 -> -0.064752252 | U105: =B105/S105 -> 53.507182 | V105: =(B105-B97)/B97 -> 0.33005497 | W105: =D105/$D$108 -> 0.08001504 | X105: =(G105-G97)/G97 -> -0.052254832 | Y105: =(F105-F97)/F97 -> -0.23254977 | Z105: =(R105-R97)/R97 -> 0.40338881 | AA105: =(U105-U97)/U97 -> 0.42214185 | AB105: =B105/B108 -> 0.36985452
A106: 引力魔方 | B106: =SUM(引力魔方!B696:B725) -> 26455.84 | C106: =SUM(引力魔方!C696:C725) -> 24345333 | D106: =SUM(引力魔方!D696:D725) -> 84432 | E106: =SUM(引力魔方!E696:E725) -> 1 | F106: =SUM(引力魔方!F696:F725) -> 12960 | G106: =SUM(引力魔方!G696:G725) -> 291 | H106: =SUM(引力魔方!H696:H725) -> 2647 | I106: =SUM(引力魔方!I696:I725) -> 41 | J106: =H106+I106 -> 2688 | K106: =D106/C106 -> 0.003468098 | L106: =B106/D106 -> 0.31333902 | M106: =(B106/C106)*1000 -> 1.0866904 | N106: =F106/B106 -> 0.48987294 | O106: =E106/D106 -> 1.1843851e-05 | P106: =IF(E106=0,"0",F106/E106) -> 12960 | Q106: =IF(E106=0,"0",B106/E106) -> 26455.84 | R106: =B106/G106 -> 90.91354 | S106: =G106+J106 -> 2979 | T106: =(S106-S98)/S98 -> 0.73298429 | U106: =B106/S106 -> 8.8807788 | V106: =(B106-B98)/B98 -> -0.15492344 | W106: =D106/$D$108 -> 0.33772395 | X106: =(G106-G98)/G98 -> -0.18715084 | Y106: =(F106-F98)/F98 -> -0.91468015 | Z106: =(R106-R98)/R98 -> 0.039647451 | AA106: =(U106-U98)/U98 -> -0.51235764 | AB106: =B106/B108 -> 0.1100958
A107: 万相台 | B107: =SUM(万相台!B285:B314) -> 113711.83 | C107: =SUM(万相台!C285:C314) -> 27390605 | D107: =SUM(万相台!D285:D314) -> 140904 | E107: =SUM(万相台!E285:E314) -> 80 | F107: =SUM(万相台!F285:F314) -> 1004319 | G107: =SUM(万相台!G285:G314) -> 1573 | H107: =SUM(万相台!H285:H314) -> 7186 | I107: =SUM(万相台!I285:I314) -> 423 | J107: =H107+I107 -> 7609 | K107: =D107/C107 -> 0.0051442456 | L107: =B107/D107 -> 0.80701634 | M107: =(B107/C107)*1000 -> 4.1514903 | N107: =F107/B107 -> 8.8321417 | O107: =E107/D107 -> 0.00056776245 | P107: =IF(E107=0,"0",F107/E107) -> 12553.987 | Q107: =IF(E107=0,"0",B107/E107) -> 1421.3979 | R107: =B107/G107 -> 72.289784 | S107: =G107+J107 -> 9182 | T107: =(S107-S99)/S99 -> 0.32477276 | U107: =B107/S107 -> 12.384212 | V107: =(B107-B99)/B99 -> 0.50848317 | W107: =D107/$D$108 -> 0.56360924 | X107: =(G107-G99)/G99 -> 0.090846047 | Y107: =(F107-F99)/F99 -> -0.19399654 | Z107: =(R107-R99)/R99 -> 0.38285616 | AA107: =(U107-U99)/U99 -> 0.13867315 | AB107: =B107/B108 -> 0.47321103
A108: 总计 | B108: =SUM(B104:B107) -> 240298.35 | C108: =SUM(C104:C107) -> 52132336 | D108: =SUM(D104:D107) -> 250003 | E108: =SUM(E104:E107) -> 227 | F108: =SUM(F104:F107) -> 3093700 | G108: =SUM(G104:G107) -> 4389 | H108: =SUM(H104:H107) -> 10107 | I108: =SUM(I104:I107) -> 919 | J108: =SUM(J104:J107) -> 11026 | K108: =D108/C108 -> 0.0047955457 | L108: =B108/D108 -> 0.96118187 | M108: =(B108/C108)*1000 -> 4.6093916 | N108: =F108/B108 -> 12.874412 | O108: =E108/D108 -> 0.0009079891 | P108: =F108/E108 -> 13628.634 | Q108: =B108/E108 -> 1058.583 | R108: =B108/G108 -> 54.750137 | S108: =G108+J108 -> 15415 | T108: =(S108-S100)/S100 -> 0.20977868 | U108: =B108/S108 -> 15.588605 | V108: =(B108-B100)/B100 -> 0.30126924 | W108: =D108/$D$108 -> 1 | X108: =(G108-G100)/G100 -> -0.093181818 | Y108: =(F108-F100)/F100 -> -0.018997528 | Z108: =(R108-R100)/R100 -> 0.43498362 | AA108: =(U108-U100)/U100 -> 0.075625859 | AB108: =B108/B108 -> 1 | AC108: =B108/F108 -> 0.077673449
A109: 环比5月 | B109: =(B108-B100)/B100 -> 0.30126924 | C109: =(C108-C100)/C100 -> -0.1466551 | D109: =(D108-D100)/D100 -> -0.2438747 | E109: =(E108-E100)/E100 -> -0.14015152 | F109: =(F108-F100)/F100 -> -0.018997528 | G109: =(G108-G100)/G100 -> -0.093181818 | H109: =(H108-H100)/H100 -> 0.48676081 | I109: =(I108-I100)/I100 -> -0.16757246 | ... R109: =(R108-R100)/R100 -> 0.43498362
A111: 7月 | B111: Cost 花费 | C111: IMP 展示 | D111: Click 点击 | E111: Order 订单 | F111: Sales 销量 | G111: ShoppingCart 加入购物车 | H111: Bookmark-Product 宝贝收藏 | I111: Bookmark-Store 店铺收藏 | J111: 总收藏数 | K111: CTR 点击率 | L111: CPC 点击成本 | M111: CPM 千次展现成本 | N111: ROI 投资回报率 | O111: CVR 点击转化率 | P111: ASP 订单均价 | Q111: Cporder 订单成本 | R111: CPshopping cart 加购成本 | S111: 收藏加购数 | T111: 收藏加购 环比 | U111: 收藏加购 成本 | V111: 花费环比 | W111: 点击占比 | X111: 加购环比 | Y111: 成交环比 | Z111: 加购成本 环比 | AA111: 收藏加购 成本环比 | AB111: 花费占比 | AC111: 费率
A112: 明星店铺 | B112: =SUM(明星店铺!B827:B857) -> 13729.34 | C112: =SUM(明星店铺!C827:C857) -> 11854 | D112: =SUM(明星店铺!D827:D857) -> 4950 | E112: =SUM(明星店铺!E827:E857) -> 49 | F112: =SUM(明星店铺!F827:F857) -> 697698.8 | G112: =SUM(明星店铺!G827:G857) -> 929 | H112: =SUM(明星店铺!H827:H857) -> 103 | I112: =SUM(明星店铺!I827:I857) -> 246 | J112: =H112+I112 -> 349 | K112: =D112/C112 -> 0.41758056 | L112: =B112/D112 -> 2.773604 | M112: =(B112/C112)*1000 -> 1158.2031 | N112: =F112/B112 -> 50.818087 | O112: =E112/D112 -> 0.0098989899 | P112: =IF(E112=0,"0",F112/E112) -> 14238.751 | Q112: =IF(E112=0,"0",B112/E112) -> 280.19061 | R112: =B112/G112 -> 14.778622 | S112: =G112+J112 -> 1278 | T112: =(S112-S104)/S104 -> -0.19774011 | U112: =B112/S112 -> 10.742833 | V112: =(B112-B104)/B104 -> 0.21981653 | W112: =D112/$D$116 -> 0.024097324 | X112: =(G112-G104)/G104 -> -0.22647794 | Y112: =(F112-F104)/F104 -> -0.50624516 | Z112: =(R112-R104)/R104 -> 0.5769641 | AA112: =(U112-U104)/U104 -> 0.52047553 | AB112: =B112/B116 -> 0.07857492
A113: 直通车 | B113: =SUM(直通车!B827:B857) -> 70267.13 | C113: =SUM(直通车!C827:C857) -> 290559 | D113: =SUM(直通车!D827:D857) -> 18649 | E113: =SUM(直通车!E827:E857) -> 40 | F113: =SUM(直通车!F827:F857) -> 552984 | G113: =SUM(直通车!G827:G857) -> 1017 | H113: =SUM(直通车!H827:H857) -> 122 | I113: =SUM(直通车!I827:I857) -> 140 | J113: =H113+I113 -> 262 | K113: =D113/C113 -> 0.064183178 | L113: =B113/D113 -> 3.7678766 | M113: =(B113/C113)*1000 -> 241.83429 | N113: =F113/B113 -> 7.8697394 | O113: =E113/D113 -> 0.0021448871 | P113: =IF(E113=0,"0",F113/E113) -> 13824.6 | Q113: =IF(E113=0,"0",B113/E113) -> 1756.6782 | R113: =B113/G113 -> 69.092557 | S113: =G113+J113 -> 1279 | T113: =(S113-S105)/S105 -> -0.22998194 | U113: =B113/S113 -> 54.939116 | V113: =(B113-B105)/B105 -> -0.20937508 | W113: =D113/$D$116 -> 0.09078606 | X113: =(G113-G105)/G105 -> -0.23187311 | Y113: =(F113-F105)/F105 -> -0.16640688 | Z113: =(R113-R105)/R105 -> 0.029289477 | AA113: =(U113-U105)/U105 -> 0.02676153 | AB113: =B113/B116 -> 0.40214855
A114: 引力魔方 | B114: =SUM(引力魔方!B726:B756) -> 14555.63 | C114: =SUM(引力魔方!C726:C756) -> 15439831 | D114: =SUM(引力魔方!D726:D756) -> 59881 | E114: =SUM(引力魔方!E726:E756) -> 1 | F114: =SUM(引力魔方!F726:F756) -> 10442 | G114: =SUM(引力魔方!G726:G756) -> 417 | H114: =SUM(引力魔方!H726:H756) -> 1697 | I114: =SUM(引力魔方!I726:I756) -> 53 | J114: =H114+I114 -> 1750 | K114: =D114/C114 -> 0.0038783456 | L114: =B114/D114 -> 0.24307593 | M114: =(B114/C114)*1000 -> 0.94273247 | N114: =F114/B114 -> 0.71738564 | O114: =E114/D114 -> 1.6699788e-05 | P114: =IF(E114=0,"0",F114/E114) -> 10442 | Q114: =IF(E114=0,"0",B114/E114) -> 14555.63 | R114: =B114/G114 -> 34.905588 | S114: =G114+J114 -> 2167 | T114: =(S114-S106)/S106 -> -0.27257469 | U114: =B114/S114 -> 6.7169497 | V114: =(B114-B106)/B106 -> -0.44981411 | W114: =D114/$D$116 -> 0.29150947 | X114: =(G114-G106)/G106 -> 0.43298969 | Y114: =(F114-F106)/F106 -> -0.19429012 | Z114: =(R114-R106)/R106 -> -0.61605733 | AA114: =(U114-U106)/U106 -> -0.24365308 | AB114: =B114/B116 -> 0.083303893
A115: 万相台 | B115: =SUM(万相台!B315:B345) -> 76177.19 | C115: =SUM(万相台!C315:C345) -> 21177312 | D115: =SUM(万相台!D315:D345) -> 121937 | E115: =SUM(万相台!E315:E345) -> 61 | F115: =SUM(万相台!F315:F345) -> 748047 | G115: =SUM(万相台!G315:G345) -> 1707 | H115: =SUM(万相台!H315:H345) -> 8264 | I115: =SUM(万相台!I315:I345) -> 446 | J115: =H115+I115 -> 8710 | K115: =D115/C115 -> 0.0057579073 | L115: =B115/D115 -> 0.6247258 | M115: =(B115/C115)*1000 -> 3.5971133 | N115: =F115/B115 -> 9.8198293 | O115: =E115/D115 -> 0.00050025833 | P115: =IF(E115=0,"0",F115/E115) -> 12263.066 | Q115: =IF(E115=0,"0",B115/E115) -> 1248.8064 | R115: =B115/G115 -> 44.626356 | S115: =G115+J115 -> 10417 | T115: =(S115-S107)/S107 -> 0.13450229 | U115: =B115/S115 -> 7.3127762 | V115: =(B115-B107)/B107 -> -0.33008562 | W115: =D115/$D$116 -> 0.59360715 | X115: =(G115-G107)/G107 -> 0.08518754 | Y115: =(F115-F107)/F107 -> -0.25516992 | Z115: =(R115-R107)/R107 -> -0.3826741 | AA115: =(U115-U107)/U107 -> -0.40950813 | AB115: =B115/B116 -> 0.43597264
A116: 总计 | B116: =SUM(B112:B115) -> 174729.29 | C116: =SUM(C112:C115) -> 36919556 | D116: =SUM(D112:D115) -> 205417 | E116: =SUM(E112:E115) -> 151 | F116: =SUM(F112:F115) -> 2009171.8 | G116: =SUM(G112:G115) -> 4070 | H116: =SUM(H112:H115) -> 10186 | I116: =SUM(I112:I115) -> 885 | J116: =SUM(J112:J115) -> 11071 | K116: =D116/C116 -> 0.0055639076 | L116: =B116/D116 -> 0.85060774 | M116: =(B116/C116)*1000 -> 4.7327029 | N116: =F116/B116 -> 11.498769 | O116: =E116/D116 -> 0.00073509009 | P116: =F116/E116 -> 13305.774 | Q116: =B116/E116 -> 1157.1476 | R116: =B116/G116 -> 42.931029 | S116: =G116+J116 -> 15141 | T116: =(S116-S108)/S108 -> -0.017774895 | U116: =B116/S116 -> 11.540142 | V116: =(B116-B108)/B108 -> -0.27286521 | W116: =D116/$D$116 -> 1 | X116: =(G116-G108)/G108 -> -0.072681704 | Y116: =(F116-F108)/F108 -> -0.35056024 | Z116: =(R116-R108)/R108 -> -0.21587357 | AA116: =(U116-U108)/U108 -> -0.25970657 | AB116: =B116/B116 -> 1 | AC116: =B116/F116 -> 0.086965828
A117: 环比6月 | B117: =(B116-B108)/B108 -> -0.27286521 | C117: =(C116-C108)/C108 -> -0.29181083 | D117: =(D116-D108)/D108 -> -0.17834186 | E117: =(E116-E108)/E108 -> -0.33480176 | F117: =(F116-F108)/F108 -> -0.35056024 | G117: =(G116-G108)/G108 -> -0.072681704 | H117: =(H116-H108)/H108 -> 0.0078163649 | I117: =(I116-I108)/I108 -> -0.036996736 | ... R117: =(R116-R108)/R108 -> -0.21587357
A119: 8月 | B119: Cost 花费 | C119: IMP 展示 | D119: Click 点击 | E119: Order 订单 | F119: Sales 销量 | G119: ShoppingCart 加入购物车 | H119: Bookmark-Product 宝贝收藏 | I119: Bookmark-Store 店铺收藏 | J119: 总收藏数 | K119: CTR 点击率 | L119: CPC 点击成本 | M119: CPM 千次展现成本 | N119: ROI 投资回报率 | O119: CVR 点击转化率 | P119: ASP 订单均价 | Q119: Cporder 订单成本 | R119: CPshopping cart 加购成本 | S119: 收藏加购数 | T119: 收藏加购 环比 | U119: 收藏加购 成本 | V119: 花费环比 | W119: 点击占比 | X119: 加购环比 | Y119: 成交环比 | Z119: 加购成本 环比 | AA119: 收藏加购 成本环比 | AB119: 花费占比 | AC119: 费率
A120: 明星店铺 | B120: =SUM(明星店铺!B858:B888) -> 12102.66 | C120: =SUM(明星店铺!C858:C888) -> 10168 | D120: =SUM(明星店铺!D858:D888) -> 3824 | E120: =SUM(明星店铺!E858:E888) -> 33 | F120: =SUM(明星店铺!F858:F888) -> 419005.38 | G120: =SUM(明星店铺!G858:G888) -> 693 | H120: =SUM(明星店铺!H858:H888) -> 66 | I120: =SUM(明星店铺!I858:I888) -> 197 | J120: =H120+I120 -> 263 | K120: =D120/C120 -> 0.37608183 | L120: =B120/D120 -> 3.1649215 | M120: =(B120/C120)*1000 -> 1190.2695 | N120: =F120/B120 -> 34.620933 | O120: =E120/D120 -> 0.0086297071 | P120: =IF(E120=0,"0",F120/E120) -> 12697.133 | Q120: =IF(E120=0,"0",B120/E120) -> 366.74727 | R120: =B120/G120 -> 17.464156 | S120: =G120+J120 -> 956 | T120: =(S120-S112)/S112 -> -0.25195618 | U120: =B120/S120 -> 12.659686 | V120: =(B120-B112)/B112 -> -0.11848202 | W120: =D120/$D$124 -> 0.022037551 | X120: =(G120-G112)/G112 -> -0.2540366 | Y120: =(F120-F112)/F112 -> -0.39944661 | Z120: =(R120-R112)/R112 -> 0.18171746 | AA120: =(U120-U112)/U112 -> 0.17843093 | AB120: =B120/B124 -> 0.07901476
A121: 直通车 | B121: =SUM(直通车!B858:B888) -> 55551.38 | C121: =SUM(直通车!C858:C888) -> 197627 | D121: =SUM(直通车!D858:D888) -> 17351 | E121: =SUM(直通车!E858:E888) -> 29 | F121: =SUM(直通车!F858:F888) -> 394437.86 | G121: =SUM(直通车!G858:G888) -> 1012 | H121: =SUM(直通车!H858:H888) -> 118 | I121: =SUM(直通车!I858:I888) -> 114 | J121: =H121+I121 -> 232 | K121: =D121/C121 -> 0.087796708 | L121: =B121/D121 -> 3.2016241 | M121: =(B121/C121)*1000 -> 281.09206 | N121: =F121/B121 -> 7.1004151 | O121: =E121/D121 -> 0.0016713734 | P121: =IF(E121=0,"0",F121/E121) -> 13601.306 | Q121: =IF(E121=0,"0",B121/E121) -> 1915.5648 | R121: =B121/G121 -> 54.892668 | S121: =G121+J121 -> 1244 | T121: =(S121-S113)/S113 -> -0.027365129 | U121: =B121/S121 -> 44.65545 | V121: =(B121-B113)/B113 -> -0.2094258 | W121: =D121/$D$124 -> 0.099993084 | X121: =(G121-G113)/G113 -> -0.0049164208 | Y121: =(F121-F113)/F113 -> -0.28671018 | Z121: =(R121-R113)/R113 -> -0.2055198 | AA121: =(U121-U113)/U113 -> -0.18718296 | AB121: =B121/B124 -> 0.36267886
A122: 引力魔方 | B122: =SUM(引力魔方!B757:B787) -> 14483.02 | C122: =SUM(引力魔方!C757:C787) -> 18021162 | D122: =SUM(引力魔方!D757:D787) -> 68521 | E122: =SUM(引力魔方!E757:E787) -> 1 | F122: =SUM(引力魔方!F757:F787) -> 14487 | G122: =SUM(引力魔方!G757:G787) -> 499 | H122: =SUM(引力魔方!H757:H787) -> 1488 | I122: =SUM(引力魔方!I757:I787) -> 42 | J122: =H122+I122 -> 1530 | K122: =D122/C122 -> 0.003802252 | L122: =B122/D122 -> 0.21136615 | M122: =(B122/C122)*1000 -> 0.80366738 | N122: =F122/B122 -> 1.0002748 | O122: =E122/D122 -> 1.4594066e-05 | P122: =IF(E122=0,"0",F122/E122) -> 14487 | Q122: =IF(E122=0,"0",B122/E122) -> 14483.02 | R122: =B122/G122 -> 29.024088 | S122: =G122+J122 -> 2029 | T122: =(S122-S114)/S114 -> -0.06368251 | U122: =B122/S122 -> 7.1380089 | V122: =(B122-B114)/B114 -> -0.0049884478 | W122: =D122/$D$124 -> 0.39488365 | X122: =(G122-G114)/G114 -> 0.19664269 | Y122: =(F122-F114)/F114 -> 0.3873779 | Z122: =(R122-R114)/R114 -> -0.16849736 | AA122: =(U122-U114)/U114 -> 0.062686069 | AB122: =B122/B124 -> 0.094555441
A123: 万相台 | B123: =SUM(万相台!B346:B376) -> 71032.55 | C123: =SUM(万相台!C346:C376) -> 8804839 | D123: =SUM(万相台!D346:D376) -> 83826 | E123: =SUM(万相台!E346:E376) -> 43 | F123: =SUM(万相台!F346:F376) -> 462492.58 | G123: =SUM(万相台!G346:G376) -> 1600 | H123: =SUM(万相台!H346:H376) -> 6175 | I123: =SUM(万相台!I346:I376) -> 389 | J123: =H123+I123 -> 6564 | K123: =D123/C123 -> 0.0095204467 | L123: =B123/D123 -> 0.84738088 | M123: =(B123/C123)*1000 -> 8.0674445 | N123: =F123/B123 -> 6.510995 | O123: =E123/D123 -> 0.00051296734 | P123: =IF(E123=0,"0",F123/E123) -> 10755.641 | Q123: =IF(E123=0,"0",B123/E123) -> 1651.9198 | R123: =B123/G123 -> 44.395344 | S123: =G123+J123 -> 8164 | T123: =(S123-S115)/S115 -> -0.21628108 | U123: =B123/S123 -> 8.7007043 | V123: =(B123-B115)/B115 -> -0.067535177 | W123: =D123/$D$124 -> 0.48308572 | X123: =(G123-G115)/G115 -> -0.06268307 | Y123: =(F123-F115)/F115 -> -0.38173326 | Z123: =(R123-R115)/R115 -> -0.0051765918 | AA123: =(U123-U115)/U115 -> 0.18979496 | AB123: =B123/B124 -> 0.46375094
A124: 总计 | B124: =SUM(B120:B123) -> 153169.61 | C124: =SUM(C120:C123) -> 27033796 | D124: =SUM(D120:D123) -> 173522 | E124: =SUM(E120:E123) -> 106 | F124: =SUM(F120:F123) -> 1290422.8 | G124: =SUM(G120:G123) -> 3804 | H124: =SUM(H120:H123) -> 7847 | I124: =SUM(I120:I123) -> 742 | J124: =SUM(J120:J123) -> 8589 | K124: =D124/C124 -> 0.0064187064 | L124: =B124/D124 -> 0.88271003 | M124: =(B124/C124)*1000 -> 5.6658565 | N124: =F124/B124 -> 8.4247967 | O124: =E124/D124 -> 0.00061087355 | P124: =F124/E124 -> 12173.8 | Q124: =B124/E124 -> 1444.9963 | R124: =B124/G124 -> 40.265407 | S124: =G124+J124 -> 12393 | T124: =(S124-S116)/S116 -> -0.18149396 | U124: =B124/S124 -> 12.359365 | V124: =(B124-B116)/B116 -> -0.12338904 | W124: =D124/$D$124 -> 1 | X124: =(G124-G116)/G116 -> -0.065356265 | Y124: =(F124-F116)/F116 -> -0.35773396 | Z124: =(R124-R116)/R116 -> -0.062090801 | AA124: =(U124-U116)/U116 -> 0.070988985 | AB124: =B124/B124 -> 1 | AC124: =B124/F124 -> 0.11869723
...

Sheet 明星店铺
A1: Date 时间 | B1: Cost 花费 | C1: IMP 展示 | D1: Click 点击 | E1: Order 订单 | F1: Sales 销量 | G1: ShoppingCart 加入购物车 | H1: Bookmark-Product 宝贝收藏 | I1: Bookmark-Store 店铺收藏 | J1: CTR 点击率 | K1: CPC 点击成本 | L1: CPM 千次展现成本 | M1: ROI 投资回报率 | N1: CVR 点击转化率 | O1: ASP 订单均价 | P1: Cporder 订单成本 | Q1: CPshopping cart 加购成本 | R1: 加购率
A2: 44197 | B2: 56.54 | C2: 42 | D2: 18 | E2: 0 | F2: 0 | G2: 0 | H2: 0 | I2: 2 | J2: =D2/C2 -> 0.42857143 | K2: =B2/D2 -> 3.1411111 | L2: 1346.19 | M2: 0 | N2: 0 | O2: =F2/E2 -> #DIV/0! | P2: =B2/E2 -> #DIV/0! | Q2: =B2/G2 -> #DIV/0!
A3: 44198 | B3: 36.58 | C3: 26 | D3: 11 | E3: 0 | F3: 0 | G3: 0 | H3: 0 | I3: 2 | J3: =D3/C3 -> 0.42307692 | K3: =B3/D3 -> 3.3254545 | L3: 1406.92 | M3: 0 | N3: 0 | O3: =F3/E3 -> #DIV/0! | P3: =B3/E3 -> #DIV/0! | Q3: =B3/G3 -> #DIV/0!
A4: 44199 | B4: 49.47 | C4: 39 | D4: 11 | E4: 0 | F4: 0 | G4: 0 | H4: 0 | I4: 3 | J4: =D4/C4 -> 0.28205128 | K4: =B4/D4 -> 4.4972727 | L4: 1268.46 | M4: 0 | N4: 0 | O4: =F4/E4 -> #DIV/0! | P4: =B4/E4 -> #DIV/0! | Q4: =B4/G4 -> #DIV/0!
A5: 44200 | B5: 78.09 | C5: 62 | D5: 30 | E5: 0 | F5: 0 | G5: 1 | H5: 0 | I5: 0 | J5: =D5/C5 -> 0.48387097 | K5: =B5/D5 -> 2.603 | L5: 1259.52 | M5: 0 | N5: 0 | O5: =F5/E5 -> #DIV/0! | P5: =B5/E5 -> #DIV/0! | Q5: =B5/G5 -> 78.09
A6: 44201 | B6: 59.83 | C6: 50 | D6: 20 | E6: 0 | F6: 0 | G6: 1 | H6: 0 | I6: 2 | J6: =D6/C6 -> 0.4 | K6: =B6/D6 -> 2.9915 | L6: 1196.6 | M6: 0 | N6: 0 | O6: =F6/E6 -> #DIV/0! | P6: =B6/E6 -> #DIV/0! | Q6: =B6/G6 -> 59.83
A7: 44202 | B7: 78.24 | C7: 58 | D7: 31 | E7: 0 | F7: 0 | G7: 0 | H7: 0 | I7: 2 | J7: =D7/C7 -> 0.53448276 | K7: =B7/D7 -> 2.523871 | L7: 1348.97 | M7: 0 | N7: 0 | O7: =F7/E7 -> #DIV/0! | P7: =B7/E7 -> #DIV/0! | Q7: =B7/G7 -> #DIV/0!
A8: 44203 | B8: 72.5 | C8: 71 | D8: 23 | E8: 0 | F8: 0 | G8: 2 | H8: 0 | I8: 1 | J8: =D8/C8 -> 0.32394366 | K8: =B8/D8 -> 3.1521739 | L8: 1021.13 | M8: 0 | N8: 0 | O8: =F8/E8 -> #DIV/0! | P8: =B8/E8 -> #DIV/0! | Q8: =B8/G8 -> 36.25
A9: 44204 | B9: 72.51 | C9: 70 | D9: 22 | E9: 0 | F9: 0 | G9: 0 | H9: 0 | I9: 1 | J9: =D9/C9 -> 0.31428571 | K9: =B9/D9 -> 3.2959091 | L9: 1035.86 | M9: 0 | N9: 0 | O9: =F9/E9 -> #DIV/0! | P9: =B9/E9 -> #DIV/0! | Q9: =B9/G9 -> #DIV/0!
A10: 44205 | B10: 66.9 | C10: 81 | D10: 8 | E10: 0 | F10: 0 | G10: 0 | H10: 0 | I10: 0 | J10: =D10/C10 -> 0.098765432 | K10: =B10/D10 -> 8.3625 | L10: 825.93 | M10: 0 | N10: 0 | O10: =F10/E10 -> #DIV/0! | P10: =B10/E10 -> #DIV/0! | Q10: =B10/G10 -> #DIV/0!
A11: 44206 | B11: 41.51 | C11: 38 | D11: 9 | E11: 0 | F11: 0 | G11: 0 | H11: 0 | I11: 1 | J11: =D11/C11 -> 0.23684211 | K11: =B11/D11 -> 4.6122222 | L11: 1092.37 | M11: 0 | N11: 0 | O11: =F11/E11 -> #DIV/0! | P11: =B11/E11 -> #DIV/0! | Q11: =B11/G11 -> #DIV/0!
A12: 44207 | B12: 56.58 | C12: 51 | D12: 16 | E12: 0 | F12: 0 | G12: 2 | H12: 0 | I12: 0 | J12: =D12/C12 -> 0.31372549 | K12: =B12/D12 -> 3.53625 | L12: 1109.41 | M12: 0 | N12: 0 | O12: =F12/E12 -> #DIV/0! | P12: =B12/E12 -> #DIV/0! | Q12: =B12/G12 -> 28.29
A13: 44208 | B13: 56.94 | C13: 57 | D13: 13 | E13: 0 | F13: 0 | G13: 1 | H13: 1 | I13: 0 | J13: =D13/C13 -> 0.22807018 | K13: =B13/D13 -> 4.38 | L13: 998.95 | M13: 0 | N13: 0 | O13: =F13/E13 -> #DIV/0! | P13: =B13/E13 -> #DIV/0! | Q13: =B13/G13 -> 56.94
... A18: 44213 | B18: 49.73 | C18: 42 | D18: 11 | E18: 0 | F18: 0 | G18: 2 | H18: 2 | I18: 1 | J18: =D18/C18 -> 0.26190476 | K18: =B18/D18 -> 4.5209091 | L18: 1184.05 | M18: 0 | N18: 0 | O18: =F18/E18 -> #DIV/0! | P18: =B18/E18 -> #DIV/0! | Q18: =B18/G18 -> 24.865
A19: 44214 | B19: 50.64 | C19: 41 | D19: 18 | E19: 1 | F19: 0.01 | G19: 2 | H19: 0 | I19: 0 | J19: =D19/C19 -> 0.43902439 | K19: =B19/D19 -> 2.8133333 | L19: =B19/(C19/1000) -> 1235.122 | M19: 0 | N19: 0 | O19: =F19/E19 -> 0.01 | P19: =B19/E19 -> 50.64 | Q19: =B19/G19 -> 25.32
A20: 44215 | B20: 50.78 | C20: 39 | D20: 16 | E20: 0 | F20: 0 | G20: 0 | H20: 0 | I20: 1 | J20: =D20/C20 -> 0.41025641 | K20: =B20/D20 -> 3.17375 | L20: =B20/(C20/1000) -> 1302.0513 | M20: 0 | N20: 0 | O20: =F20/E20 -> #DIV/0! | P20: =B20/E20 -> #DIV/0! | Q20: =B20/G20 -> #DIV/0!
A21: 44216 | B21: 71.75 | C21: 58 | D21: 32 | E21: 1 | F21: 0.01 | G21: 0 | H21: 0 | I21: 2 | J21: =D21/C21 -> 0.55172414 | K21: =B21/D21 -> 2.2421875 | L21: =B21/(C21/1000) -> 1237.069 | M21: 0 | N21: 0 | O21: =F21/E21 -> 0.01 | P21: =B21/E21 -> 71.75 | Q21: =B21/G21 -> #DIV/0!
A22: 44217 | B22: 52.78 | C22: 38 | D22: 18 | E22: 1 | F22: 0.01 | G22: 0 | H22: 0 | I22: 0 | J22: =D22/C22 -> 0.47368421 | K22: =B22/D22 -> 2.9322222 | L22: =B22/(C22/1000) -> 1388.9474 | M22: 0 | N22: 0 | O22: =F22/E22 -> 0.01 | P22: =B22/E22 -> 52.78 | Q22: =B22/G22 -> #DIV/0!
A23: 44218 | B23: 49.79 | C23: 43 | D23: 14 | E23: 0 | F23: 0 | G23: 0 | H23: 0 | I23: 0 | J23: =D23/C23 -> 0.3255814 | K23: =B23/D23 -> 3.5564286 | L23: =B23/(C23/1000) -> 1157.907 | M23: 0 | N23: 0 | O23: =F23/E23 -> #DIV/0! | P23: =B23/E23 -> #DIV/0! | Q23: =B23/G23 -> #DIV/0!
A24: 44219 | B24: 60.91 | C24: 67 | D24: 13 | E24: 0 | F24: 0 | G24: 1 | H24: 0 | I24: 2 | J24: =D24/C24 -> 0.19402985 | K24: =B24/D24 -> 4.6853846 | L24: =B24/(C24/1000) -> 909.10448 | M24: 0 | N24: 0 | O24: =F24/E24 -> #DIV/0! | P24: =B24/E24 -> #DIV/0! | Q24: =B24/G24 -> 60.91
A25: 44220 | B25: 54.85 | C25: 50 | D25: 15 | E25: 0 | F25: 0 | G25: 1 | H25: 0 | I25: 1 | J25: =D25/C25 -> 0.3 | K25: =B25/D25 -> 3.6566667 | L25: =B25/(C25/1000) -> 1097 | M25: 0 | N25: 0 | O25: =F25/E25 -> #DIV/0! | P25: =B25/E25 -> #DIV/0! | Q25: =B25/G25 -> 54.85
A26: 44221 | B26: 35.77 | C26: 36 | D26: 10 | E26: 0 | F26: 0 | G26: 1 | H26: 0 | I26: 1 | J26: =D26/C26 -> 0.27777778 | K26: =B26/D26 -> 3.577 | L26: =B26/(C26/1000) -> 993.61111 | M26: 0 | N26: 0 | O26: =F26/E26 -> #DIV/0! | P26: =B26/E26 -> #DIV/0! | Q26: =B26/G26 -> 35.77
A27: 44222 | B27: 45.51 | C27: 40 | D27: 21 | E27: 0 | F27: 0 | G27: 0 | H27: 1 | I27: 1 | J27: =D27/C27 -> 0.525 | K27: =B27/D27 -> 2.1671429 | L27: =B27/(C27/1000) -> 1137.75 | M27: 0 | N27: 0 | O27: =F27/E27 -> #DIV/0! | P27: =B27/E27 -> #DIV/0! | Q27: =B27/G27 -> #DIV/0!
A28: 44223 | B28: 51.74 | C28: 39 | D28: 26 | E28: 0 | F28: 0 | G28: 1 | H28: 0 | I28: 0 | J28: =D28/C28 -> 0.66666667 | K28: =B28/D28 -> 1.99 | L28: =B28/(C28/1000) -> 1326.6667 | M28: 0 | N28: 0 | O28: =F28/E28 -> #DIV/0! | P28: =B28/E28 -> #DIV/0! | Q28: =B28/G28 -> 51.74
A29: 44224 | B29: 58.41 | C29: 41 | D29: 25 | E29: 0 | F29: 0 | G29: 2 | H29: 1 | I29: 2 | J29: =D29/C29 -> 0.6097561 | K29: =B29/D29 -> 2.3364 | L29: =B29/(C29/1000) -> 1424.6341 | M29: 0 | N29: 0 | O29: =F29/E29 -> #DIV/0! | P29: =B29/E29 -> #DIV/0! | Q29: =B29/G29 -> 29.205
A30: 44225 | B30: 41.08 | C30: 28 | D30: 10 | E30: 0 | F30: 0 | G30: 2 | H30: 0 | I30: 0 | J30: =D30/C30 -> 0.35714286 | K30: =B30/D30 -> 4.108 | L30: =B30/(C30/1000) -> 1467.1429 | M30: 0 | N30: 0 | O30: =F30/E30 -> #DIV/0! | P30: =B30/E30 -> #DIV/0! | Q30: =B30/G30 -> 20.54
... A32: 44227 | B32: 0 | C32: 0 | D32: 0 | E32: 0 | F32: 0 | G32: 0 | H32: 0 | I32: 0 | J32: =D32/C32 -> #DIV/0! | K32: =B32/D32 -> #DIV/0! | L32: =B32/(C32/1000) -> #DIV/0! | M32: 0 | N32: 0 | O32: =F32/E32 -> #DIV/0! | P32: =B32/E32 -> #DIV/0! | Q32: =B32/G32 -> #DIV/0!
A33: =A32+1 -> 44228 | B33: 0 | C33: 0 | D33: 0 | E33: 0 | F33: 0 | G33: 0 | H33: 0 | I33: 0 | J33: =D33/C33 -> #DIV/0! | K33: =B33/D33 -> #DIV/0! | L33: =B33/(C33/1000) -> #DIV/0! | M33: 0 | N33: 0 | O33: =F33/E33 -> #DIV/0! | P33: =B33/E33 -> #DIV/0! | Q33: =B33/G33 -> #DIV/0!
A34: =A33+1 -> 44229 | B34: 58.2 | C34: 54 | D34: 20 | E34: 0 | F34: 0 | G34: 1 | H34: 0 | I34: 1 | J34: =D34/C34 -> 0.37037037 | K34: =B34/D34 -> 2.91 | L34: =B34/(C34/1000) -> 1077.7778 | M34: 0 | N34: 0 | O34: =F34/E34 -> #DIV/0! | P34: =B34/E34 -> #DIV/0! | Q34: =B34/G34 -> 58.2
A35: =A34+1 -> 44230 | B35: 81.92 | C35: 71 | D35: 30 | E35: 0 | F35: 0 | G35: 4 | H35: 1 | I35: 1 | J35: =D35/C35 -> 0.42253521 | K35: =B35/D35 -> 2.7306667 | L35: =B35/(C35/1000) -> 1153.8028 | M35: 0 | N35: 0 | O35: =F35/E35 -> #DIV/0! | P35: =B35/E35 -> #DIV/0! | Q35: =B35/G35 -> 20.48
A36: =A35+1 -> 44231 | B36: 41.85 | C36: 35 | D36: 16 | E36: 0 | F36: 0 | G36: 1 | H36: 2 | I36: 0 | J36: =D36/C36 -> 0.45714286 | K36: =B36/D36 -> 2.615625 | L36: =B36/(C36/1000) -> 1195.7143 | M36: 0 | N36: 0 | O36: =F36/E36 -> #DIV/0! | P36: =B36/E36 -> #DIV/0! | Q36: =B36/G36 -> 41.85
A37: =A36+1 -> 44232 | B37: 72.21 | C37: 57 | D37: 11 | E37: 0 | F37: 0 | G37: 0 | H37: 0 | I37: 1 | J37: =D37/C37 -> 0.19298246 | K37: =B37/D37 -> 6.5645455 | L37: =B37/(C37/1000) -> 1266.8421 | M37: 0 | N37: 0 | O37: =F37/E37 -> #DIV/0! | P37: =B37/E37 -> #DIV/0! | Q37: =B37/G37 -> #DIV/0!
A38: =A37+1 -> 44233 | B38: 43.5 | C38: 52 | D38: 12 | E38: 0 | F38: 0 | G38: 0 | H38: 0 | I38: 0 | J38: =D38/C38 -> 0.23076923 | K38: =B38/D38 -> 3.625 | L38: =B38/(C38/1000) -> 836.53846 | M38: 0 | N38: 0 | O38: =F38/E38 -> #DIV/0! | P38: =B38/E38 -> #DIV/0! | Q38: =B38/G38 -> #DIV/0!
A39: =A38+1 -> 44234 | B39: 23.77 | C39: 25 | D39: 7 | E39: 0 | F39: 0 | G39: 0 | H39: 0 | I39: 1 | J39: =D39/C39 -> 0.28 | K39: =B39/D39 -> 3.3957143 | L39: =B39/(C39/1000) -> 950.8 | M39: 0 | N39: 0 | O39: =F39/E39 -> #DIV/0! | P39: =B39/E39 -> #DIV/0! | Q39: =B39/G39 -> #DIV/0!
A40: =A39+1 -> 44235 | B40: 33.8 | C40: 33 | D40: 11 | E40: 0 | F40: 0 | G40: 0 | H40: 0 | I40: 0 | J40: =D40/C40 -> 0.33333333 | K40: =B40/D40 -> 3.0727273 | L40: =B40/(C40/1000) -> 1024.2424 | M40: 0 | N40: 0 | O40: =F40/E40 -> #DIV/0! | P40: =B40/E40 -> #DIV/0! | Q40: =B40/G40 -> #DIV/0!
A41: =A40+1 -> 44236 | B41: 29.93 | C41: 35 | D41: 5 | E41: 0 | F41: 0 | G41: 0 | H41: 0 | I41: 0 | J41: =D41/C41 -> 0.14285714 | K41: =B41/D41 -> 5.986 | L41: =B41/(C41/1000) -> 855.14286 | M41: 0 | N41: 0 | O41: =F41/E41 -> #DIV/0! | P41: =B41/E41 -> #DIV/0! | Q41: =B41/G41 -> #DIV/0!
A42: =A41+1 -> 44237 | B42: 50.8 | C42: 71 | D42: 15 | E42: 0 | F42: 0 | G42: 3 | H42: 0 | I42: 0 | J42: =D42/C42 -> 0.21126761 | K42: =B42/D42 -> 3.3866667 | L42: =B42/(C42/1000) -> 715.49296 | M42: 0 | N42: 0 | O42: =F42/E42 -> #DIV/0! | P42: =B42/E42 -> #DIV/0! | Q42: =B42/G42 -> 16.933333
A43: =A42+1 -> 44238 | B43: 24.51 | C43: 35 | D43: 8 | E43: 0 | F43: 0 | G43: 1 | H43: 0 | I43: 0 | J43: =D43/C43 -> 0.22857143 | K43: =B43/D43 -> 3.06375 | L43: =B43/(C43/1000) -> 700.28571 | M43: 0 | N43: 0 | O43: =F43/E43 -> #DIV/0! | P43: =B43/E43 -> #DIV/0! | Q43: =B43/G43 -> 24.51
A44: =A43+1 -> 44239 | B44: 42.93 | C44: 46 | D44: 16 | E44: 0 | F44: 0 | G44: 1 | H44: 0 | I44: 0 | J44: =D44/C44 -> 0.34782609 | K44: =B44/D44 -> 2.683125 | L44: =B44/(C44/1000) -> 933.26087 | M44: 0 | N44: 0 | O44: =F44/E44 -> #DIV/0! | P44: =B44/E44 -> #DIV/0! | Q44: =B44/G44 -> 42.93
... A67: =A66+1 -> 44262 | B67: 152.95 | C67: 313 | D67: 18 | E67: 0 | F67: 0 | G67: 0 | H67: 1 | I67: 0 | J67: =D67/C67 -> 0.057507987 | K67: =B67/D67 -> 8.4972222 | L67: =B67/(C67/1000) -> 488.65815 | M67: 0 | N67: 0 | O67: =F67/E67 -> #DIV/0! | P67: =B67/E67 -> #DIV/0! | Q67: =B67/G67 -> #DIV/0!
A68: =A67+1 -> 44263 | B68: 135.08 | C68: 191 | D68: 17 | E68: 0 | F68: 0 | G68: 6 | H68: 2 | I68: 0 | J68: =D68/C68 -> 0.089005236 | K68: =B68/D68 -> 7.9458824 | L68: 707.23 | M68: 0 | N68: 0 | O68: =F68/E68 -> #DIV/0! | P68: =B68/E68 -> #DIV/0! | Q68: =B68/G68 -> 22.513333
A69: =A68+1 -> 44264 | B69: 137.37 | C69: 196 | D69: 18 | E69: 0 | F69: 0 | G69: 4 | H69: 1 | I69: 2 | J69: =D69/C69 -> 0.091836735 | K69: =B69/D69 -> 7.6316667 | L69: 700.87 | M69: 0 | N69: 0 | O69: =F69/E69 -> #DIV/0! | P69: =B69/E69 -> #DIV/0! | Q69: =B69/G69 -> 34.3425
A70: =A69+1 -> 44265 | B70: 94.71 | C70: 89 | D70: 25 | E70: 1 | F70: 0.01 | G70: 1 | H70: 2 | I70: 0 | J70: =D70/C70 -> 0.28089888 | K70: =B70/D70 -> 3.7884 | L70: 1064.16 | M70: 0 | N70: 0 | O70: =F70/E70 -> 0.01 | P70: =B70/E70 -> 94.71 | Q70: =B70/G70 -> 94.71
A71: =A70+1 -> 44266 | B71: 71.65 | C71: 70 | D71: 11 | E71: 1 | F71: 0.01 | G71: 2 | H71: 0 | I71: 0 | J71: =D71/C71 -> 0.15714286 | K71: =B71/D71 -> 6.5136364 | L71: 1023.57 | M71: 0 | N71: 0 | O71: =F71/E71 -> 0.01 | P71: =B71/E71 -> 71.65 | Q71: =B71/G71 -> 35.825
A72: =A71+1 -> 44267 | B72: 57.08 | C72: 60 | D72: 14 | E72: 0 | F72: 0 | G72: 2 | H72: 0 | I72: 0 | J72: =D72/C72 -> 0.23333333 | K72: =B72/D72 -> 4.0771429 | L72: 951.33 | M72: 0 | N72: 0 | O72: =F72/E72 -> #DIV/0! | P72: =B72/E72 -> #DIV/0! | Q72: =B72/G72 -> 28.54
A73: =A72+1 -> 44268 | B73: 53.24 | C73: 58 | D73: 12 | E73: 0 | F73: 0 | G73: 4 | H73: 0 | I73: 1 | J73: =D73/C73 -> 0.20689655 | K73: =B73/D73 -> 4.4366667 | L73: 917.93 | M73: 0 | N73: 0 | O73: =F73/E73 -> #DIV/0! | P73: =B73/E73 -> #DIV/0! | Q73: =B73/G73 -> 13.31
A74: =A73+1 -> 44269 | B74: 59.63 | C74: 67 | D74: 13 | E74: 0 | F74: 0 | G74: 1 | H74: 0 | I74: 0 | J74: =D74/C74 -> 0.19402985 | K74: =B74/D74 -> 4.5869231 | L74: 890 | M74: 0 | N74: 0 | O74: =F74/E74 -> #DIV/0! | P74: =B74/E74 -> #DIV/0! | Q74: =B74/G74 -> 59.63
A75: =A74+1 -> 44270 | B75: 71.4 | C75: 78 | D75: 17 | E75: 0 | F75: 0 | G75: 2 | H75: 0 | I75: 1 | J75: =D75/C75 -> 0.21794872 | K75: =B75/D75 -> 4.2 | L75: 915.38 | M75: 0 | N75: 0 | O75: =F75/E75 -> #DIV/0! | P75: =B75/E75 -> #DIV/0! | Q75: =B75/G75 -> 35.7
A76: =A75+1 -> 44271 | B76: 126.18 | C76: 140 | D76: 23 | E76: 0 | F76: 0 | G76: 6 | H76: 1 | I76: 0 | J76: =D76/C76 -> 0.16428571 | K76: =B76/D76 -> 5.486087 | L76: 901.29 | M76: 0 | N76: 0 | O76: =F76/E76 -> #DIV/0! | P76: =B76/E76 -> #DIV/0! | Q76: =B76/G76 -> 21.03
A77: =A76+1 -> 44272 | B77: 96.16 | C77: 94 | D77: 20 | E77: 0 | F77: 0 | G77: 4 | H77: 1 | I77: 0 | J77: =D77/C77 -> 0.21276596 | K77: =B77/D77 -> 4.808 | L77: 1022.98 | M77: 0 | N77: 0 | O77: =F77/E77 -> #DIV/0! | P77: =B77/E77 -> #DIV/0! | Q77: =B77/G77 -> 24.04
A78: =A77+1 -> 44273 | B78: 142.2 | C78: 147 | D78: 49 | E78: 0 | F78: 0 | G78: 4 | H78: 1 | I78: 1 | J78: =D78/C78 -> 0.33333333 | K78: =B78/D78 -> 2.9020408 | L78: 967.35 | M78: 0 | N78: 0 | O78: =F78/E78 -> #DIV/0! | P78: =B78/E78 -> #DIV/0! | Q78: =B78/G78 -> 35.55
A79: =A78+1 -> 44274 | B79: 101.1 | C79: 131 | D79: 18 | E79: 1 | F79: 1 | G79: 4 | H79: 0 | I79: 0 | J79: =D79/C79 -> 0.13740458 | K79: =B79/D79 -> 5.6166667 | L79: 771.76 | M79: 0 | N79: 0 | O79: =F79/E79 -> 1 | P79: =B79/E79 -> 101.1 | Q79: =B79/G79 -> 25.275
... A109: =A108+1 -> 44304 | B109: 192.51 | C109: 310 | D109: 21 | E109: 1 | F109: 0.01 | G109: 1 | H109: 4 | I109: 1 | J109: =D109/C109 -> 0.067741935 | K109: =B109/D109 -> 9.1671429 | L109: 621 | M109: 0 | N109: 0 | O109: =F109/E109 -> 0.01 | P109: =B109/E109 -> 192.51 | Q109: =B109/G109 -> 192.51
A110: =A109+1 -> 44305 | B110: 154.89 | C110: 189 | D110: 46 | E110: 0 | F110: 0 | G110: 5 | H110: 0 | I110: 5 | J110: =D110/C110 -> 0.24338624 | K110: =B110/D110 -> 3.3671739 | M110: 0 | N110: 0 | O110: =F110/E110 -> #DIV/0! | P110: =B110/E110 -> #DIV/0! | Q110: =B110/G110 -> 30.978
A111: =A110+1 -> 44306 | B111: 299.2 | C111: 289 | D111: 137 | E111: 12 | F111: 12478.99 | G111: 15 | H111: 4 | I111: 7 | J111: =D111/C111 -> 0.47404844 | K111: =B111/D111 -> 2.1839416 | M111: 0 | N111: 0 | O111: =F111/E111 -> 1039.9158 | P111: =B111/E111 -> 24.933333 | Q111: =B111/G111 -> 19.946667
A112: =A111+1 -> 44307 | B112: 265.19 | C112: 410 | D112: 78 | E112: 0 | F112: 0 | G112: 15 | H112: 1 | I112: 9 | J112: =D112/C112 -> 0.1902439 | K112: =B112/D112 -> 3.3998718 | M112: 0 | N112: 0 | O112: =F112/E112 -> #DIV/0! | P112: =B112/E112 -> #DIV/0! | Q112: =B112/G112 -> 17.679333
A113: =A112+1 -> 44308 | B113: 217.39 | C113: 314 | D113: 62 | E113: 1 | F113: 0.1 | G113: 10 | H113: 1 | I113: 2 | J113: =D113/C113 -> 0.19745223 | K113: =B113/D113 -> 3.5062903 | M113: 0 | N113: 0 | O113: =F113/E113 -> 0.1 | P113: =B113/E113 -> 217.39 | Q113: =B113/G113 -> 21.739
A114: =A113+1 -> 44309 | B114: 237.06 | C114: 361 | D114: 66 | E114: 3 | F114: 5800.1 | G114: 14 | H114: 0 | I114: 5 | J114: =D114/C114 -> 0.18282548 | K114: =B114/D114 -> 3.5918182 | M114: 0 | N114: 0 | O114: =F114/E114 -> 1933.3667 | P114: =B114/E114 -> 79.02 | Q114: =B114/G114 -> 16.932857
A115: =A114+1 -> 44310 | B115: 176.32 | C115: 210 | D115: 26 | E115: 0 | F115: 0 | G115: 3 | H115: 2 | I115: 2 | J115: =D115/C115 -> 0.12380952 | K115: =B115/D115 -> 6.7815385 | M115: 0 | N115: 0 | O115: =F115/E115 -> #DIV/0! | P115: =B115/E115 -> #DIV/0! | Q115: =B115/G115 -> 58.773333
A116: =A115+1 -> 44311 | B116: 202.63 | C116: 284 | D116: 41 | E116: 0 | F116: 0 | G116: 3 | H116: 0 | I116: 4 | J116: =D116/C116 -> 0.1443662 | K116: =B116/D116 -> 4.9421951 | M116: 0 | N116: 0 | O116: =F116/E116 -> #DIV/0! | P116: =B116/E116 -> #DIV/0! | Q116: =B116/G116 -> 67.543333
A117: =A116+1 -> 44312 | B117: 256.45 | C117: 435 | D117: 45 | E117: 0 | F117: 0 | G117: 6 | H117: 4 | I117: 5 | J117: =D117/C117 -> 0.10344828 | K117: =B117/D117 -> 5.6988889 | M117: 0 | N117: 0 | O117: =F117/E117 -> #DIV/0! | P117: =B117/E117 -> #DIV/0! | Q117: =B117/G117 -> 42.741667
A118: =A117+1 -> 44313 | B118: 208.37 | C118: 355 | D118: 43 | E118: 0 | F118: 0 | G118: 1 | H118: 0 | I118: 0 | J118: =D118/C118 -> 0.12112676 | K118: =B118/D118 -> 4.845814 | M118: 0 | N118: 0 | O118: =F118/E118 -> #DIV/0! | P118: =B118/E118 -> #DIV/0! | Q118: =B118/G118 -> 208.37
A119: =A118+1 -> 44314 | B119: 198.82 | C119: 323 | D119: 43 | E119: 0 | F119: 0 | G119: 6 | H119: 0 | I119: 2 | J119: =D119/C119 -> 0.13312693 | K119: =B119/D119 -> 4.6237209 | M119: 0 | N119: 0 | O119: =F119/E119 -> #DIV/0! | P119: =B119/E119 -> #DIV/0! | Q119: =B119/G119 -> 33.136667
A120: =A119+1 -> 44315 | B120: 184.05 | C120: 330 | D120: 22 | E120: 0 | F120: 0 | G120: 4 | H120: 0 | I120: 1 | J120: =D120/C120 -> 0.066666667 | K120: =B120/D120 -> 8.3659091 | M120: 0 | N120: 0 | O120: =F120/E120 -> #DIV/0! | P120: =B120/E120 -> #DIV/0! | Q120: =B120/G120 -> 46.0125
A121: =A120+1 -> 44316 | B121: 158.37 | C121: 300 | D121: 23 | E121: 1 | F121: 17068 | G121: 4 | H121: 0 | I121: 0 | J121: =D121/C121 -> 0.076666667 | K121: =B121/D121 -> 6.8856522 | M121: 0 | N121: 0 | O121: =F121/E121 -> 17068 | P121: =B121/E121 -> 158.37 | Q121: =B121/G121 -> 39.5925
... A123: =A122+1 -> 44318 | B123: 151.72 | C123: 284 | D123: 27 | E123: 0 | F123: 0 | G123: 3 | H123: 0 | I123: 0 | J123: =D123/C123 -> 0.095070423 | K123: =B123/D123 -> 5.6192593 | M123: 0 | N123: 0 | O123: =F123/E123 -> #DIV/0! | P123: =B123/E123 -> #DIV/0! | Q123: =B123/G123 -> 50.573333
A124: =A123+1 -> 44319 | B124: 195.65 | C124: 347 | D124: 31 | E124: 0 | F124: 0 | G124: 1 | H124: 0 | I124: 2 | J124: =D124/C124 -> 0.089337176 | K124: =B124/D124 -> 6.3112903 | L124: 563.83 | M124: 0 | N124: 0 | O124: =F124/E124 -> #DIV/0! | P124: =B124/E124 -> #DIV/0! | Q124: =B124/G124 -> 195.65
A125: =A124+1 -> 44320 | B125: 178.71 | C125: 308 | D125: 27 | E125: 0 | F125: 0 | G125: 1 | H125: 0 | I125: 1 | J125: =D125/C125 -> 0.087662338 | K125: =B125/D125 -> 6.6188889 | L125: 580.23 | M125: 0 | N125: 0 | O125: =F125/E125 -> #DIV/0! | P125: =B125/E125 -> #DIV/0! | Q125: =B125/G125 -> 178.71
A126: =A125+1 -> 44321 | B126: 198.25 | C126: 310 | D126: 35 | E126: 0 | F126: 0 | G126: 2 | H126: 0 | I126: 0 | J126: =D126/C126 -> 0.11290323 | K126: =B126/D126 -> 5.6642857 | L126: 639.52 | M126: 0 | N126: 0 | O126: =F126/E126 -> #DIV/0! | P126: =B126/E126 -> #DIV/0! | Q126: =B126/G126 -> 99.125
A127: =A126+1 -> 44322 | B127: 164.93 | C127: 208 | D127: 35 | E127: 1 | F127: 4000 | G127: 3 | H127: 0 | I127: 2 | J127: =D127/C127 -> 0.16826923 | K127: =B127/D127 -> 4.7122857 | L127: 792.93 | M127: 0 | N127: 0 | O127: =F127/E127 -> 4000 | P127: =B127/E127 -> 164.93 | Q127: =B127/G127 -> 54.976667
A128: =A127+1 -> 44323 | B128: 120.08 | C128: 139 | D128: 26 | E128: 0 | F128: 0 | G128: 3 | H128: 1 | I128: 3 | J128: =D128/C128 -> 0.18705036 | K128: =B128/D128 -> 4.6184615 | L128: 863.88 | M128: 0 | N128: 0 | O128: =F128/E128 -> #DIV/0! | P128: =B128/E128 -> #DIV/0! | Q128: =B128/G128 -> 40.026667
A129: =A128+1 -> 44324 | B129: 129.42 | C129: 155 | D129: 23 | E129: 0 | F129: 0 | G129: 3 | H129: 0 | I129: 1 | J129: =D129/C129 -> 0.1483871 | K129: =B129/D129 -> 5.6269565 | L129: 834.97 | M129: 0 | N129: 0 | O129: =F129/E129 -> #DIV/0! | P129: =B129/E129 -> #DIV/0! | Q129: =B129/G129 -> 43.14
A130: =A129+1 -> 44325 | B130: 32.57 | C130: 32 | D130: 5 | E130: 0 | F130: 0 | G130: 2 | H130: 0 | I130: 0 | J130: =D130/C130 -> 0.15625 | K130: =B130/D130 -> 6.514 | L130: 1017.81 | M130: 0 | N130: 0 | O130: =F130/E130 -> #DIV/0! | P130: =B130/E130 -> #DIV/0! | Q130: =B130/G130 -> 16.285
A131: =A130+1 -> 44326 | B131: 86.76 | C131: 91 | D131: 21 | E131: 0 | F131: 0 | G131: 2 | H131: 0 | I131: 1 | J131: =D131/C131 -> 0.23076923 | K131: =B131/D131 -> 4.1314286 | L131: 953.41 | M131: 0 | N131: 0 | O131: =F131/E131 -> #DIV/0! | P131: =B131/E131 -> #DIV/0! | Q131: =B131/G131 -> 43.38
A132: =A131+1 -> 44327 | B132: 77.14 | C132: 77 | D132: 13 | E132: 0 | F132: 0 | G132: 1 | H132: 0 | I132: 2 | J132: =D132/C132 -> 0.16883117 | K132: =B132/D132 -> 5.9338462 | L132: 1001.82 | M132: 0 | N132: 0 | O132: =F132/E132 -> #DIV/0! | P132: =B132/E132 -> #DIV/0! | Q132: =B132/G132 -> 77.14
A133: =A132+1 -> 44328 | B133: 146.82 | C133: 143 | D133: 67 | E133: 9 | F133: 0.45 | G133: 4 | H133: 1 | I133: 0 | J133: =D133/C133 -> 0.46853147 | K133: =B133/D133 -> 2.1913433 | L133: 1026.71 | M133: 0 | N133: 0 | O133: =F133/E133 -> 0.05 | P133: =B133/E133 -> 16.313333 | Q133: =B133/G133 -> 36.705
A134: =A133+1 -> 44329 | B134: 137.29 | C134: 158 | D134: 29 | E134: 0 | F134: 0 | G134: 2 | H134: 1 | I134: 1 | J134: =D134/C134 -> 0.1835443 | K134: =B134/D134 -> 4.7341379 | L134: 868.92 | M134: 0 | N134: 0 | O134: =F134/E134 -> #DIV/0! | P134: =B134/E134 -> #DIV/0! | Q134: =B134/G134 -> 68.645
A135: =A134+1 -> 44330 | B135: 89.65 | C135: 107 | D135: 13 | E135: 0 | F135: 0 | G135: 2 | H135: 2 | I135: 1 | J135: =D135/C135 -> 0.12149533 | K135: =B135/D135 -> 6.8961538 | L135: 837.85 | M135: 0 | N135: 0 | O135: =F135/E135 -> #DIV/0! | P135: =B135/E135 -> #DIV/0! | Q135: =B135/G135 -> 44.825
... A236: =A235+1 -> 44431 | B236: 279.8 | C236: 1009 | D236: 36 | E236: 0 | F236: 0 | G236: 1 | H236: 0 | I236: 0 | J236: =D236/C236 -> 0.03567889 | K236: =B236/D236 -> 7.7722222 | L236: 277.3 | M236: 0 | N236: 0 | O236: =F236/E236 -> #DIV/0! | P236: =B236/E236 -> #DIV/0! | Q236: =B236/G236 -> 279.8
A237: =A236+1 -> 44432 | B237: - | C237: - | D237: - | E237: - | F237: - | G237: - | H237: - | I237: - | J237: =D237/C237 -> #VALUE! | K237: =B237/D237 -> #VALUE! | L237: - | M237: 0 | N237: 0 | O237: =F237/E237 -> #VALUE! | P237: =B237/E237 -> #VALUE! | Q237: =B237/G237 -> #VALUE!
A238: =A237+1 -> 44433 | B238: 199.68 | C238: 769 | D238: 35 | E238: 0 | F238: 0 | G238: 1 | H238: 0 | I238: 1 | J238: =D238/C238 -> 0.045513654 | K238: =B238/D238 -> 5.7051429 | L238: 259.66 | M238: 0 | N238: 0 | O238: =F238/E238 -> #DIV/0! | P238: =B238/E238 -> #DIV/0! | Q238: =B238/G238 -> 199.68
A239: =A238+1 -> 44434 | B239: 288.21 | C239: 979 | D239: 37 | E239: 0 | F239: 0 | G239: 0 | H239: 0 | I239: 0 | J239: =D239/C239 -> 0.037793667 | K239: =B239/D239 -> 7.7894595 | L239: 294.39 | M239: 0 | N239: 0 | O239: =F239/E239 -> #DIV/0! | P239: =B239/E239 -> #DIV/0! | Q239: =B239/G239 -> #DIV/0!
A240: =A239+1 -> 44435 | B240: 284.79 | C240: 1053 | D240: 34 | E240: 0 | F240: 0 | G240: 1 | H240: 0 | I240: 0 | J240: =D240/C240 -> 0.032288699 | K240: =B240/D240 -> 8.3761765 | L240: 270.46 | M240: 0 | N240: 0 | O240: =F240/E240 -> #DIV/0! | P240: =B240/E240 -> #DIV/0! | Q240: =B240/G240 -> 284.79
A241: =A240+1 -> 44436 | B241: 272.49 | C241: 1047 | D241: 27 | E241: 0 | F241: 0 | G241: 3 | H241: 0 | I241: 0 | J241: =D241/C241 -> 0.025787966 | K241: =B241/D241 -> 10.092222 | L241: 272.49 | M241: 0 | N241: 0 | O241: =F241/E241 -> #DIV/0! | P241: =B241/E241 -> #DIV/0! | Q241: =B241/G241 -> 90.83
A242: =A241+1 -> 44437 | B242: 257.08 | C242: 1158 | D242: 49 | E242: 0 | F242: 0 | G242: 1 | H242: 0 | I242: 1 | J242: =D242/C242 -> 0.042314335 | K242: =B242/D242 -> 5.2465306 | L242: 222 | M242: 0 | N242: 0 | O242: =F242/E242 -> #DIV/0! | P242: =B242/E242 -> #DIV/0! | Q242: =B242/G242 -> 257.08
A243: =A242+1 -> 44438 | B243: 295.03 | C243: 1150 | D243: 35 | E243: 0 | F243: 0 | G243: 1 | H243: 0 | I243: 0 | J243: =D243/C243 -> 0.030434783 | K243: =B243/D243 -> 8.4294286 | L243: 256.55 | M243: 0 | N243: 0 | O243: =F243/E243 -> #DIV/0! | P243: =B243/E243 -> #DIV/0! | Q243: =B243/G243 -> 295.03
A244: =A243+1 -> 44439 | B244: 298.7 | C244: 1026 | D244: 34 | E244: 0 | F244: 0 | G244: 3 | H244: 1 | I244: 3 | J244: =D244/C244 -> 0.033138402 | K244: =B244/D244 -> 8.7852941 | L244: 298.7 | M244: 0 | N244: 0 | O244: =F244/E244 -> #DIV/0! | P244: =B244/E244 -> #DIV/0! | Q244: =B244/G244 -> 99.566667
A245: =A244+1 -> 44440 | B245: 355.12 | C245: 1348 | D245: 36 | E245: 0 | F245: 0 | G245: 0 | H245: 0 | I245: 0 | J245: =D245/C245 -> 0.026706231 | K245: =B245/D245 -> 9.8644444 | L245: 263.44 | M245: 0 | N245: 0 | O245: =F245/E245 -> #DIV/0! | P245: =B245/E245 -> #DIV/0! | Q245: =B245/G245 -> #DIV/0!
A246: =A245+1 -> 44441 | B246: 303.18 | C246: 1261 | D246: 36 | E246: 0 | F246: 0 | G246: 2 | H246: 0 | I246: 0 | J246: =D246/C246 -> 0.028548771 | K246: =B246/D246 -> 8.4216667 | L246: 240.43 | M246: 0 | N246: 0 | O246: =F246/E246 -> #DIV/0! | P246: =B246/E246 -> #DIV/0! | Q246: =B246/G246 -> 151.59
A247: =A246+1 -> 44442 | B247: 353.35 | C247: 1320 | D247: 24 | E247: 2 | F247: 0.02 | G247: 0 | H247: 0 | I247: 2 | J247: =D247/C247 -> 0.018181818 | K247: =B247/D247 -> 14.722917 | L247: 353.35 | M247: 0 | N247: 0 | O247: =F247/E247 -> 0.01 | P247: =B247/E247 -> 176.675 | Q247: =B247/G247 -> #DIV/0!
A248: =A247+1 -> 44443 | B248: - | C248: - | D248: - | E248: - | F248: - | G248: - | H248: - | I248: - | J248: =D248/C248 -> #VALUE! | K248: =B248/D248 -> #VALUE! | L248: - | M248: 0 | N248: 0 | O248: =F248/E248 -> #VALUE! | P248: =B248/E248 -> #VALUE! | Q248: =B248/G248 -> #VALUE!
A249: =A248+1 -> 44444 | B249: 298.2 | C249: 1201 | D249: 25 | E249: 0 | F249: 0 | G249: 0 | H249: 1 | I249: 1 | J249: =D249/C249 -> 0.020815987 | K249: =B249/D249 -> 11.928 | L249: 248.29 | M249: 0 | N249: 0 | O249: =F249/E249 -> #DIV/0! | P249: =B249/E249 -> #DIV/0! | Q249: =B249/G249 -> #DIV/0!
A250: =A249+1 -> 44445 | B250: 267.99 | C250: 1050 | D250: 26 | E250: 0 | F250: 0 | G250: 0 | H250: 0 | I250: 0 | J250: =D250/C250 -> 0.024761905 | K250: =B250/D250 -> 10.307308 | L250: 255.23 | M250: 0 | N250: 0 | O250: =F250/E250 -> #DIV/0! | P250: =B250/E250 -> #DIV/0! | Q250: =B250/G250 -> #DIV/0!
A251: =A250+1 -> 44446 | B251: - | C251: - | D251: - | E251: - | F251: - | G251: - | H251: - | I251: - | J251: =D251/C251 -> #VALUE! | K251: =B251/D251 -> #VALUE! | L251: - | M251: 0 | N251: 0 | O251: =F251/E251 -> #VALUE! | P251: =B251/E251 -> #VALUE! | Q251: =B251/G251 -> #VALUE!
A252: =A251+1 -> 44447 | B252: 294.57 | C252: 1059 | D252: 43 | E252: 0 | F252: 0 | G252: 1 | H252: 1 | I252: 1 | J252: =D252/C252 -> 0.040604344 | K252: =B252/D252 -> 6.8504651 | L252: 278.16 | M252: 0 | N252: 0 | O252: =F252/E252 -> #DIV/0! | P252: =B252/E252 -> #DIV/0! | Q252: =B252/G252 -> 294.57
A253: =A252+1 -> 44448 | B253: 276.23 | C253: 982 | D253: 38 | E253: 0 | F253: 0 | G253: 1 | H253: 0 | I253: 0 | J253: =D253/C253 -> 0.038696538 | K253: =B253/D253 -> 7.2692105 | L253: 281.29 | M253: 0 | N253: 0 | O253: =F253/E253 -> #DIV/0! | P253: =B253/E253 -> #DIV/0! | Q253: =B253/G253 -> 276.23
A254: =A253+1 -> 44449 | B254: 195.14 | C254: 814 | D254: 31 | E254: 0 | F254: 0 | G254: 0 | H254: 0 | I254: 0 | J254: =D254/C254 -> 0.038083538 | K254: =B254/D254 -> 6.2948387 | L254: 239.73 | M254: 0 | N254: 0 | O254: =F254/E254 -> #DIV/0! | P254: =B254/E254 -> #DIV/0! | Q254: =B254/G254 -> #DIV/0!
A255: =A254+1 -> 44450 | B255: - | C255: - | D255: - | E255: - | F255: - | G255: - | H255: - | I255: - | J255: =D255/C255 -> #VALUE! | K255: =B255/D255 -> #VALUE! | L255: - | M255: 0 | N255: 0 | O255: =F255/E255 -> #VALUE! | P255: =B255/E255 -> #VALUE! | Q255: =B255/G255 -> #VALUE!
A256: =A255+1 -> 44451 | B256: - | C256: - | D256: - | E256: - | F256: - | G256: - | H256: - | I256: - | J256: =D256/C256 -> #VALUE! | K256: =B256/D256 -> #VALUE! | L256: - | M256: 0 | N256: 0 | O256: =F256/E256 -> #VALUE! | P256: =B256/E256 -> #VALUE! | Q256: =B256/G256 -> #VALUE!
A257: =A256+1 -> 44452 | B257: 191.37 | C257: 883 | D257: 17 | E257: 0 | F257: 0 | G257: 0 | H257: 1 | I257: 0 | J257: =D257/C257 -> 0.019252548 | K257: =B257/D257 -> 11.257059 | L257: 216.73 | M257: 0 | N257: 0 | O257: =F257/E257 -> #DIV/0! | P257: =B257/E257 -> #DIV/0! | Q257: =B257/G257 -> #DIV/0!
...

Sheet 直通车
A1: Date 时间 | B1: Cost 花费 | C1: IMP 展示 | D1: Click 点击 | E1: Order 订单 | F1: Sales 销量GMV | G1: ShoppingCart 加入购物车 | H1: Bookmark-Product 宝贝收藏 | I1: Bookmark-Store 店铺收藏 | J1: CTR 点击率 | K1: CPC 点击成本 | L1: ROI 投资回报率 | M1: CVR 点击转化率 | N1: ASP 订单均价 | O1: Cporder 订单成本 | P1: CPshopping cart 加购成本 | Q1: 收藏加购成本 | R1: 收藏加购数 | S1: 收藏加购率
A2: 44197 | B2: 110.86 | C2: 5918 | D2: 80 | E2: 0 | F2: 0 | G2: 2 | H2: 0 | I2: 0 | J2: =D2/C2 -> 0.01351808 | K2: 1.39 | L2: =F2/B2 -> 0 | M2: 0 | N2: =F2/E2 -> #DIV/0! | O2: =B2/E2 -> #DIV/0! | P2: =B2/G2 -> 55.43
A3: 44198 | B3: 99.61 | C3: 6436 | D3: 77 | E3: 0 | F3: 0 | G3: 1 | H3: 3 | I3: 1 | J3: =D3/C3 -> 0.011963953 | K3: 1.29 | L3: 0 | M3: 0 | N3: =F3/E3 -> #DIV/0! | O3: =B3/E3 -> #DIV/0! | P3: =B3/G3 -> 99.61
A4: 44199 | B4: 130.39 | C4: 6733 | D4: 87 | E4: 0 | F4: 0 | G4: 1 | H4: 0 | I4: 2 | J4: =D4/C4 -> 0.012921432 | K4: 1.5 | L4: 0 | M4: 0 | N4: =F4/E4 -> #DIV/0! | O4: =B4/E4 -> #DIV/0! | P4: =B4/G4 -> 130.39
A5: 44200 | B5: 96.83 | C5: 6249 | D5: 72 | E5: 0 | F5: 0 | G5: 1 | H5: 0 | I5: 0 | J5: =D5/C5 -> 0.011521843 | K5: 1.34 | L5: 0 | M5: 0 | N5: =F5/E5 -> #DIV/0! | O5: =B5/E5 -> #DIV/0! | P5: =B5/G5 -> 96.83
A6: 44201 | B6: 123.41 | C6: 5251 | D6: 89 | E6: 0 | F6: 0 | G6: 1 | H6: 0 | I6: 0 | J6: =D6/C6 -> 0.016949153 | K6: 1.39 | L6: 0 | M6: 0 | N6: =F6/E6 -> #DIV/0! | O6: =B6/E6 -> #DIV/0! | P6: =B6/G6 -> 123.41
A7: 44202 | B7: 236.6 | C7: 3547 | D7: 132 | E7: 0 | F7: 0 | G7: 2 | H7: 1 | I7: 1 | J7: =D7/C7 -> 0.037214548 | K7: 1.79 | L7: 0 | M7: 0 | N7: =F7/E7 -> #DIV/0! | O7: =B7/E7 -> #DIV/0! | P7: =B7/G7 -> 118.3
A8: 44203 | B8: 300 | C8: 2606 | D8: 124 | E8: 0 | F8: 0 | G8: 1 | H8: 0 | I8: 0 | J8: =D8/C8 -> 0.047582502 | K8: 2.42 | L8: 0 | M8: 0 | N8: =F8/E8 -> #DIV/0! | O8: =B8/E8 -> #DIV/0! | P8: =B8/G8 -> 300
A9: 44204 | B9: 449.36 | C9: 6075 | D9: 195 | E9: 1 | F9: 200 | G9: 1 | H9: 0 | I9: 0 | J9: =D9/C9 -> 0.032098765 | K9: 2.3 | L9: 0.45 | M9: =E9/D9 -> 0.0051282051 | N9: =F9/E9 -> 200 | O9: =B9/E9 -> 449.36 | P9: =B9/G9 -> 449.36
A10: 44205 | B10: 415.34 | C10: 7328 | D10: 234 | E10: 0 | F10: 0 | G10: 5 | H10: 1 | I10: 0 | J10: =D10/C10 -> 0.031932314 | K10: 1.77 | L10: 0 | M10: =E10/D10 -> 0 | N10: =F10/E10 -> #DIV/0! | O10: =B10/E10 -> #DIV/0! | P10: =B10/G10 -> 83.068
A11: 44206 | B11: 450 | C11: 8236 | D11: 277 | E11: 0 | F11: 0 | G11: 2 | H11: 2 | I11: 0 | J11: =D11/C11 -> 0.033632831 | K11: 1.62 | L11: 0 | M11: =E11/D11 -> 0 | N11: =F11/E11 -> #DIV/0! | O11: =B11/E11 -> #DIV/0! | P11: =B11/G11 -> 225
A12: 44207 | B12: 436.22 | C12: 16851 | D12: 297 | E12: 0 | F12: 0 | G12: 5 | H12: 3 | I12: 1 | J12: =D12/C12 -> 0.017625067 | K12: 1.47 | L12: 0 | M12: =E12/D12 -> 0 | N12: =F12/E12 -> #DIV/0! | O12: =B12/E12 -> #DIV/0! | P12: =B12/G12 -> 87.244
A13: 44208 | B13: 333.5 | C13: 19534 | D13: 222 | E13: 0 | F13: 0 | G13: 2 | H13: 3 | I13: 1 | J13: =D13/C13 -> 0.0113648 | K13: 1.95 | L13: 0 | M13: =E13/D13 -> 0 | N13: =F13/E13 -> #DIV/0! | O13: =B13/E13 -> #DIV/0! | P13: =B13/G13 -> 166.75
A14: 44209 | B14: 150 | C14: 6603 | D14: 77 | E14: 0 | F14: 0 | G14: 1 | H14: 1 | I14: 0 | J14: =D14/C14 -> 0.011661366 | K14: 1.5 | L14: 0 | M14: =E14/D14 -> 0 | N14: =F14/E14 -> #DIV/0! | O14: =B14/E14 -> #DIV/0! | P14: =B14/G14 -> 150
A15: 44210 | B15: 150 | C15: 6592 | D15: 71 | E15: 0 | F15: 0 | G15: 1 | H15: 0 | I15: 1 | J15: =D15/C15 -> 0.010770631 | K15: 2.11 | L15: 0 | M15: =E15/D15 -> 0 | N15: =F15/E15 -> #DIV/0! | O15: =B15/E15 -> #DIV/0! | P15: =B15/G15 -> 150
A16: 44211 | B16: 300 | C16: 12239 | D16: 152 | E16: 0 | F16: 0 | G16: 1 | H16: 0 | I16: 0 | J16: =D16/C16 -> 0.012419315 | K16: 1.97 | L16: 0 | M16: 0 | N16: =F16/E16 -> #DIV/0! | O16: =B16/E16 -> #DIV/0! | P16: =B16/G16 -> 300
A17: 44212 | B17: 300 | C17: 8888 | D17: 159 | E17: 0 | F17: 0 | G17: 5 | H17: 0 | I17: 0 | J17: =D17/C17 -> 0.017889289 | K17: 1.89 | L17: 0 | M17: 0 | N17: =F17/E17 -> #DIV/0! | O17: =B17/E17 -> #DIV/0! | P17: =B17/G17 -> 60
A18: 44213 | B18: 300 | C18: 13642 | D18: 216 | E18: 0 | F18: 0 | G18: 3 | H18: 1 | I18: 0 | J18: =D18/C18 -> 0.015833456 | K18: 1.39 | L18: 0 | M18: 0 | N18: =F18/E18 -> #DIV/0! | O18: =B18/E18 -> #DIV/0! | P18: =B18/G18 -> 100
A19: 44214 | B19: 300 | C19: 15538 | D19: 203 | E19: 0 | F19: 0 | G19: 3 | H19: 0 | I19: 0 | J19: =D19/C19 -> 0.013064744 | K19: =B19/D19 -> 1.4778325 | L19: =F19/B19 -> 0 | M19: =E19/D19 -> 0 | N19: =F19/E19 -> #DIV/0! | O19: =B19/E19 -> #DIV/0! | P19: =B19/G19 -> 100
A20: 44215 | B20: 300 | C20: 16331 | D20: 141 | E20: 0 | F20: 0 | G20: 0 | H20: 2 | I20: 1 | J20: =D20/C20 -> 0.0086338865 | K20: =B20/D20 -> 2.1276596 | L20: =F20/B20 -> 0 | M20: =E20/D20 -> 0 | N20: =F20/E20 -> #DIV/0! | O20: =B20/E20 -> #DIV/0! | P20: =B20/G20 -> #DIV/0!
A21: 44216 | B21: 300 | C21: 16383 | D21: 155 | E21: 0 | F21: 0 | G21: 3 | H21: 1 | I21: 1 | J21: =D21/C21 -> 0.0094610267 | K21: =B21/D21 -> 1.9354839 | L21: =F21/B21 -> 0 | M21: =E21/D21 -> 0 | N21: =F21/E21 -> #DIV/0! | O21: =B21/E21 -> #DIV/0! | P21: =B21/G21 -> 100
A22: 44217 | B22: 296.95 | C22: 18441 | D22: 173 | E22: 0 | F22: 0 | G22: 0 | H22: 0 | I22: 0 | J22: =D22/C22 -> 0.00938127 | K22: =B22/D22 -> 1.716474 | L22: =F22/B22 -> 0 | M22: =E22/D22 -> 0 | N22: =F22/E22 -> #DIV/0! | O22: =B22/E22 -> #DIV/0! | P22: =B22/G22 -> #DIV/0!
A23: 44218 | B23: 257.3 | C23: 13320 | D23: 213 | E23: 0 | F23: 0 | G23: 4 | H23: 0 | I23: 0 | J23: =D23/C23 -> 0.015990991 | K23: =B23/D23 -> 1.2079812 | L23: =F23/B23 -> 0 | M23: =E23/D23 -> 0 | N23: =F23/E23 -> #DIV/0! | O23: =B23/E23 -> #DIV/0! | P23: =B23/G23 -> 64.325
A24: 44219 | B24: 271.28 | C24: 14263 | D24: 237 | E24: 0 | F24: 0 | G24: 3 | H24: 0 | I24: 0 | J24: =D24/C24 -> 0.01661642 | K24: =B24/D24 -> 1.1446414 | L24: =F24/B24 -> 0 | M24: =E24/D24 -> 0 | N24: =F24/E24 -> #DIV/0! | O24: =B24/E24 -> #DIV/0! | P24: =B24/G24 -> 90.426667
A25: 44220 | B25: 200.22 | C25: 8266 | D25: 167 | E25: 0 | F25: 0 | G25: 2 | H25: 0 | I25: 0 | J25: =D25/C25 -> 0.020203242 | K25: =B25/D25 -> 1.1989222 | L25: =F25/B25 -> 0 | M25: =E25/D25 -> 0 | N25: =F25/E25 -> #DIV/0! | O25: =B25/E25 -> #DIV/0! | P25: =B25/G25 -> 100.11
A26: 44221 | B26: 0 | C26: 2 | D26: 0 | E26: 0 | F26: 0 | G26: 0 | H26: 0 | I26: 0 | J26: =D26/C26 -> 0 | K26: 0 | L26: =F26/B26 -> #DIV/0! | M26: =E26/D26 -> #DIV/0! | N26: =F26/E26 -> #DIV/0! | O26: =B26/E26 -> #DIV/0! | P26: =B26/G26 -> #DIV/0!
A27: 44222 | B27: 0 | C27: 0 | D27: 0 | E27: 0 | F27: 0 | G27: 0 | H27: 0 | I27: 0 | J27: =D27/C27 -> #DIV/0! | K27: 0 | L27: =F27/B27 -> #DIV/0! | M27: =E27/D27 -> #DIV/0! | N27: =F27/E27 -> #DIV/0! | O27: =B27/E27 -> #DIV/0! | P27: =B27/G27 -> #DIV/0!
A28: 44223 | B28: 0 | C28: 0 | D28: 0 | E28: 0 | F28: 0 | G28: 0 | H28: 0 | I28: 0 | J28: =D28/C28 -> #DIV/0! | K28: 0 | L28: =F28/B28 -> #DIV/0! | M28: =E28/D28 -> #DIV/0! | N28: =F28/E28 -> #DIV/0! | O28: =B28/E28 -> #DIV/0! | P28: =B28/G28 -> #DIV/0!
A29: 44224 | B29: 276.73 | C29: 16117 | D29: 177 | E29: 0 | F29: 0 | G29: 0 | H29: 0 | I29: 0 | J29: =D29/C29 -> 0.010982193 | K29: =B29/D29 -> 1.5634463 | L29: =F29/B29 -> 0 | M29: =E29/D29 -> 0 | N29: =F29/E29 -> #DIV/0! | O29: =B29/E29 -> #DIV/0! | P29: =B29/G29 -> #DIV/0!
A30: 44225 | B30: 300 | C30: 15678 | D30: 129 | E30: 0 | F30: 0 | G30: 2 | H30: 0 | I30: 1 | J30: =D30/C30 -> 0.0082280903 | K30: =B30/D30 -> 2.3255814 | L30: =F30/B30 -> 0 | M30: =E30/D30 -> 0 | N30: =F30/E30 -> #DIV/0! | O30: =B30/E30 -> #DIV/0! | P30: =B30/G30 -> 150
A31: 44226 | B31: 94.91 | C31: 6764 | D31: 69 | E31: 0 | F31: 0 | G31: 0 | H31: 0 | I31: 0 | J31: =D31/C31 -> 0.010201064 | K31: =B31/D31 -> 1.3755072 | L31: =F31/B31 -> 0 | M31: =E31/D31 -> 0 | N31: =F31/E31 -> #DIV/0! | O31: =B31/E31 -> #DIV/0! | P31: =B31/G31 -> #DIV/0!
A32: 44227 | B32: 0 | C32: 0 | D32: 0 | E32: 0 | F32: 0 | G32: 0 | H32: 0 | I32: 0 | J32: =D32/C32 -> #DIV/0! | K32: 0 | L32: =F32/B32 -> #DIV/0! | M32: =E32/D32 -> #DIV/0! | N32: =F32/E32 -> #DIV/0! | O32: =B32/E32 -> #DIV/0! | P32: =B32/G32 -> #DIV/0!
A33: =A32+1 -> 44228 | B33: 188.02 | C33: 7543 | D33: 131 | E33: 0 | F33: 0 | G33: 2 | H33: 0 | I33: 0 | J33: =D33/C33 -> 0.017367095 | K33: =B33/D33 -> 1.4352672 | L33: =F33/B33 -> 0 | M33: =E33/D33 -> 0 | N33: =F33/E33 -> #DIV/0! | O33: =B33/E33 -> #DIV/0! | P33: =B33/G33 -> 94.01
A34: =A33+1 -> 44229 | B34: 300 | C34: 12623 | D34: 188 | E34: 0 | F34: 0 | G34: 3 | H34: 4 | I34: 1 | J34: =D34/C34 -> 0.014893448 | K34: =B34/D34 -> 1.5957447 | L34: =F34/B34 -> 0 | M34: =E34/D34 -> 0 | N34: =F34/E34 -> #DIV/0! | O34: =B34/E34 -> #DIV/0! | P34: =B34/G34 -> 100
A35: =A34+1 -> 44230 | B35: 300 | C35: 12677 | D35: 175 | E35: 0 | F35: 0 | G35: 1 | H35: 1 | I35: 1 | J35: =D35/C35 -> 0.013804528 | K35: =B35/D35 -> 1.7142857 | L35: =F35/B35 -> 0 | M35: =E35/D35 -> 0 | N35: =F35/E35 -> #DIV/0! | O35: =B35/E35 -> #DIV/0! | P35: =B35/G35 -> 300
A36: =A35+1 -> 44231 | B36: 300 | C36: 15785 | D36: 162 | E36: 0 | F36: 0 | G36: 2 | H36: 4 | I36: 1 | J36: =D36/C36 -> 0.010262908 | K36: =B36/D36 -> 1.8518519 | L36: =F36/B36 -> 0 | M36: =E36/D36 -> 0 | N36: =F36/E36 -> #DIV/0! | O36: =B36/E36 -> #DIV/0! | P36: =B36/G36 -> 150
A37: =A36+1 -> 44232 | B37: 300 | C37: 15287 | D37: 152 | E37: 1 | F37: 6000 | G37: 3 | H37: 2 | I37: 0 | J37: =D37/C37 -> 0.0099430889 | K37: =B37/D37 -> 1.9736842 | L37: =F37/B37 -> 20 | M37: =E37/D37 -> 0.0065789474 | N37: =F37/E37 -> 6000 | O37: =B37/E37 -> 300 | P37: =B37/G37 -> 100
A38: =A37+1 -> 44233 | B38: 291.1 | C38: 16307 | D38: 148 | E38: 0 | F38: 0 | G38: 1 | H38: 0 | I38: 0 | J38: =D38/C38 -> 0.009075857 | K38: =B38/D38 -> 1.9668919 | L38: =F38/B38 -> 0 | M38: =E38/D38 -> 0 | N38: =F38/E38 -> #DIV/0! | O38: =B38/E38 -> #DIV/0! | P38: =B38/G38 -> 291.1
A39: =A38+1 -> 44234 | B39: 295.57 | C39: 15673 | D39: 129 | E39: 0 | F39: 0 | G39: 4 | H39: 4 | I39: 0 | J39: =D39/C39 -> 0.0082307152 | K39: =B39/D39 -> 2.2912403 | L39: =F39/B39 -> 0 | M39: =E39/D39 -> 0 | N39: =F39/E39 -> #DIV/0! | O39: =B39/E39 -> #DIV/0! | P39: =B39/G39 -> 73.8925
A40: =A39+1 -> 44235 | B40: 293.48 | C40: 23805 | D40: 149 | E40: 0 | F40: 0 | G40: 2 | H40: 1 | I40: 0 | J40: =D40/C40 -> 0.0062591892 | K40: =B40/D40 -> 1.9696644 | L40: =F40/B40 -> 0 | M40: =E40/D40 -> 0 | N40: =F40/E40 -> #DIV/0! | O40: =B40/E40 -> #DIV/0! | P40: =B40/G40 -> 146.74
A41: =A40+1 -> 44236 | B41: 300 | C41: 22151 | D41: 157 | E41: 0 | F41: 0 | G41: 2 | H41: 3 | I41: 1 | J41: =D41/C41 -> 0.0070877161 | K41: =B41/D41 -> 1.910828 | L41: =F41/B41 -> 0 | M41: =E41/D41 -> 0 | N41: =F41/E41 -> #DIV/0! | O41: =B41/E41 -> #DIV/0! | P41: =B41/G41 -> 150
A42: =A41+1 -> 44237 | B42: 300 | C42: 13365 | D42: 131 | E42: 0 | F42: 0 | G42: 4 | H42: 4 | I42: 1 | J42: =D42/C42 -> 0.0098017209 | K42: =B42/D42 -> 2.2900763 | L42: =F42/B42 -> 0 | M42: =E42/D42 -> 0 | N42: =F42/E42 -> #DIV/0! | O42: =B42/E42 -> #DIV/0! | P42: =B42/G42 -> 75
A43: =A42+1 -> 44238 | B43: 18.65 | C43: 590 | D43: 7 | E43: 0 | F43: 0 | G43: 0 | H43: 0 | I43: 0 | J43: =D43/C43 -> 0.011864407 | K43: =B43/D43 -> 2.6642857 | L43: =F43/B43 -> 0 | M43: =E43/D43 -> 0 | N43: =F43/E43 -> #DIV/0! | O43: =B43/E43 -> #DIV/0! | P43: =B43/G43 -> #DIV/0!
A44: =A43+1 -> 44239 | B44: 0 | C44: 0 | D44: 0 | E44: 0 | F44: 0 | G44: 0 | H44: 0 | I44: 0 | J44: =D44/C44 -> #DIV/0! | K44: 0 | L44: =F44/B44 -> #DIV/0! | M44: =E44/D44 -> #DIV/0! | N44: =F44/E44 -> #DIV/0! | O44: =B44/E44 -> #DIV/0! | P44: =B44/G44 -> #DIV/0!
A45: =A44+1 -> 44240 | B45: 0 | C45: 0 | D45: 0 | E45: 0 | F45: 0 | G45: 0 | H45: 0 | I45: 0 | J45: =D45/C45 -> #DIV/0! | K45: 0 | L45: =F45/B45 -> #DIV/0! | M45: =E45/D45 -> #DIV/0! | N45: =F45/E45 -> #DIV/0! | O45: =B45/E45 -> #DIV/0! | P45: =B45/G45 -> #DIV/0!
A46: =A45+1 -> 44241 | B46: 0 | C46: 0 | D46: 0 | E46: 0 | F46: 0 | G46: 0 | H46: 0 | I46: 0 | J46: =D46/C46 -> #DIV/0! | K46: 0 | L46: =F46/B46 -> #DIV/0! | M46: =E46/D46 -> #DIV/0! | N46: =F46/E46 -> #DIV/0! | O46: =B46/E46 -> #DIV/0! | P46: =B46/G46 -> #DIV/0!
A47: =A46+1 -> 44242 | B47: 0 | C47: 0 | D47: 0 | E47: 0 | F47: 0 | G47: 0 | H47: 0 | I47: 0 | J47: =D47/C47 -> #DIV/0! | K47: 0 | L47: =F47/B47 -> #DIV/0! | M47: =E47/D47 -> #DIV/0! | N47: =F47/E47 -> #DIV/0! | O47: =B47/E47 -> #DIV/0! | P47: =B47/G47 -> #DIV/0!
A48: =A47+1 -> 44243 | B48: 0 | C48: 0 | D48: 0 | E48: 0 | F48: 0 | G48: 0 | H48: 0 | I48: 0 | J48: =D48/C48 -> #DIV/0! | K48: 0 | L48: =F48/B48 -> #DIV/0! | M48: =E48/D48 -> #DIV/0! | N48: =F48/E48 -> #DIV/0! | O48: =B48/E48 -> #DIV/0! | P48: =B48/G48 -> #DIV/0!
A49: =A48+1 -> 44244 | B49: 0 | C49: 0 | D49: 0 | E49: 0 | F49: 0 | G49: 0 | H49: 0 | I49: 0 | J49: =D49/C49 -> #DIV/0! | K49: 0 | L49: =F49/B49 -> #DIV/0! | M49: =E49/D49 -> #DIV/0! | N49: =F49/E49 -> #DIV/0! | O49: =B49/E49 -> #DIV/0! | P49: =B49/G49 -> #DIV/0!
A50: =A49+1 -> 44245 | B50: 298.9 | C50: 11984 | D50: 187 | E50: 0 | F50: 0 | G50: 9 | H50: 1 | I50: 0 | J50: =D50/C50 -> 0.015604139 | K50: =B50/D50 -> 1.5983957 | L50: =F50/B50 -> 0 | M50: =E50/D50 -> 0 | N50: =F50/E50 -> #DIV/0! | O50: =B50/E50 -> #DIV/0! | P50: =B50/G50 -> 33.211111
A51: =A50+1 -> 44246 | B51: 300 | C51: 18239 | D51: 176 | E51: 0 | F51: 0 | G51: 1 | H51: 2 | I51: 0 | J51: =D51/C51 -> 0.0096496518 | K51: =B51/D51 -> 1.7045455 | L51: =F51/B51 -> 0 | M51: =E51/D51 -> 0 | N51: =F51/E51 -> #DIV/0! | O51: =B51/E51 -> #DIV/0! | P51: =B51/G51 -> 300
A52: =A51+1 -> 44247 | B52: 300 | C52: 9241 | D52: 157 | E52: 0 | F52: 0 | G52: 3 | H52: 1 | I52: 0 | J52: =D52/C52 -> 0.016989503 | K52: =B52/D52 -> 1.910828 | L52: =F52/B52 -> 0 | M52: =E52/D52 -> 0 | N52: =F52/E52 -> #DIV/0! | O52: =B52/E52 -> #DIV/0! | P52: =B52/G52 -> 100
A53: =A52+1 -> 44248 | B53: 297.43 | C53: 12656 | D53: 146 | E53: 0 | F53: 0 | G53: 12 | H53: 0 | I53: 0 | J53: =D53/C53 -> 0.01153603 | K53: =B53/D53 -> 2.0371918 | L53: =F53/B53 -> 0 | M53: =E53/D53 -> 0 | N53: =F53/E53 -> #DIV/0! | O53: =B53/E53 -> #DIV/0! | P53: =B53/G53 -> 24.785833
A54: =A53+1 -> 44249 | B54: 300 | C54: 21201 | D54: 191 | E54: 0 | F54: 0 | G54: 5 | H54: 9 | I54: 2 | J54: =D54/C54 -> 0.009009009 | K54: =B54/D54 -> 1.5706806 | L54: =F54/B54 -> 0 | M54: =E54/D54 -> 0 | N54: =F54/E54 -> #DIV/0! | O54: =B54/E54 -> #DIV/0! | P54: =B54/G54 -> 60
A55: =A54+1 -> 44250 | B55: 279.38 | C55: 22519 | D55: 176 | E55: 0 | F55: 0 | G55: 1 | H55: 1 | I55: 0 | J55: =D55/C55 -> 0.0078156224 | K55: =B55/D55 -> 1.5873864 | L55: =F55/B55 -> 0 | M55: =E55/D55 -> 0 | N55: =F55/E55 -> #DIV/0! | O55: =B55/E55 -> #DIV/0! | P55: =B55/G55 -> 279.38
A56: =A55+1 -> 44251 | B56: 266.56 | C56: 22296 | D56: 209 | E56: 0 | F56: 0 | G56: 5 | H56: 0 | I56: 0 | J56: =D56/C56 -> 0.0093738787 | K56: =B56/D56 -> 1.2754067 | L56: =F56/B56 -> 0 | M56: =E56/D56 -> 0 | N56: =F56/E56 -> #DIV/0! | O56: =B56/E56 -> #DIV/0! | P56: =B56/G56 -> 53.312
A57: =A56+1 -> 44252 | B57: 285.34 | C57: 19618 | D57: 176 | E57: 0 | F57: 0 | G57: 4 | H57: 1 | I57: 0 | J57: =D57/C57 -> 0.0089713528 | K57: =B57/D57 -> 1.62125 | L57: =F57/B57 -> 0 | M57: =E57/D57 -> 0 | N57: =F57/E57 -> #DIV/0! | O57: =B57/E57 -> #DIV/0! | P57: =B57/G57 -> 71.335
A58: =A57+1 -> 44253 | B58: 253.63 | C58: 18313 | D58: 166 | E58: 0 | F58: 0 | G58: 1 | H58: 0 | I58: 0 | J58: =D58/C58 -> 0.0090645989 | K58: =B58/D58 -> 1.5278916 | L58: =F58/B58 -> 0 | M58: =E58/D58 -> 0 | N58: =F58/E58 -> #DIV/0! | O58: =B58/E58 -> #DIV/0! | P58: =B58/G58 -> 253.63
A59: =A58+1 -> 44254 | B59: 291.27 | C59: 18977 | D59: 190 | E59: 0 | F59: 0 | G59: 6 | H59: 1 | I59: 0 | J59: =D59/C59 -> 0.01001212 | K59: =B59/D59 -> 1.533 | L59: =F59/B59 -> 0 | M59: =E59/D59 -> 0 | N59: =F59/E59 -> #DIV/0! | O59: =B59/E59 -> #DIV/0! | P59: =B59/G59 -> 48.545
A60: =A59+1 -> 44255 | B60: 300 | C60: 15687 | D60: 143 | E60: 0 | F60: 0 | G60: 5 | H60: 0 | I60: 0 | J60: =D60/C60 -> 0.0091158284 | K60: =B60/D60 -> 2.0979021 | L60: =F60/B60 -> 0 | M60: =E60/D60 -> 0 | N60: =F60/E60 -> #DIV/0! | O60: =B60/E60 -> #DIV/0! | P60: =B60/G60 -> 60
A61: =A60+1 -> 44256 | B61: 281.95 | C61: 18716 | D61: 163 | E61: 0 | F61: 0 | G61: 1 | H61: 2 | I61: 0 | J61: =D61/C61 -> 0.0087091259 | K61: =B61/D61 -> 1.7297546 | L61: =F61/B61 -> 0 | M61: =E61/D61 -> 0 | N61: =F61/E61 -> #DIV/0! | O61: =B61/E61 -> #DIV/0! | P61: =B61/G61 -> 281.95
... A81: =A80+1 -> 44276 | B81: 443.92 | C81: 24657 | D81: 291 | E81: 0 | F81: 0 | G81: 7 | H81: 2 | I81: 0 | J81: =D81/C81 -> 0.011801922 | K81: =B81/D81 -> 1.5254983 | L81: =F81/B81 -> 0 | M81: =E81/D81 -> 0 | N81: =F81/E81 -> #DIV/0! | O81: =B81/E81 -> #DIV/0! | P81: =B81/G81 -> 63.417143
A82: =A81+1 -> 44277 | B82: 422.02 | C82: 29886 | D82: 265 | E82: 0 | F82: 0 | G82: 6 | H82: 3 | I82: 0 | J82: 0.0089 | K82: 1.59 | L82: =F82/B82 -> 0 | M82: =E82/D82 -> 0 | N82: =F82/E82 -> #DIV/0! | O82: =B82/E82 -> #DIV/0! | P82: =B82/G82 -> 70.336667
A83: =A82+1 -> 44278 | B83: 422.29 | C83: 32761 | D83: 282 | E83: 2 | F83: 10449 | G83: 9 | H83: 4 | I83: 1 | J83: 0.0154 | K83: 1.28 | L83: =F83/B83 -> 24.74366 | M83: =E83/D83 -> 0.0070921986 | N83: =F83/E83 -> 5224.5 | O83: =B83/E83 -> 211.145 | P83: =B83/G83 -> 46.921111
A84: =A83+1 -> 44279 | B84: 484.63 | C84: 24550 | D84: 321 | E84: 0 | F84: 0 | G84: 0 | H84: 4 | I84: 0 | J84: 0.0131 | K84: 1.51 | L84: =F84/B84 -> 0 | M84: =E84/D84 -> 0 | N84: =F84/E84 -> #DIV/0! | O84: =B84/E84 -> #DIV/0! | P84: =B84/G84 -> #DIV/0!
A85: =A84+1 -> 44280 | B85: 485.44 | C85: 25538 | D85: 361 | E85: 0 | F85: 0 | G85: 6 | H85: 7 | I85: 2 | J85: 0.0141 | K85: 1.34 | L85: =F85/B85 -> 0 | M85: =E85/D85 -> 0 | N85: =F85/E85 -> #DIV/0! | O85: =B85/E85 -> #DIV/0! | P85: =B85/G85 -> 80.906667
A86: =A85+1 -> 44281 | B86: 457.5 | C86: 34836 | D86: 356 | E86: 1 | F86: 1 | G86: 2 | H86: 3 | I86: 2 | J86: 0.0102 | K86: 1.29 | L86: =F86/B86 -> 0.0021857923 | M86: =E86/D86 -> 0.0028089888 | N86: =F86/E86 -> 1 | O86: =B86/E86 -> 457.5 | P86: =B86/G86 -> 228.75
A87: =A86+1 -> 44282 | B87: 474.78 | C87: 29830 | D87: 353 | E87: 0 | F87: 0 | G87: 9 | H87: 1 | I87: 1 | J87: 0.0118 | K87: 1.34 | L87: =F87/B87 -> 0 | M87: =E87/D87 -> 0 | N87: =F87/E87 -> #DIV/0! | O87: =B87/E87 -> #DIV/0! | P87: =B87/G87 -> 52.753333
A88: =A87+1 -> 44283 | B88: 493.28 | C88: 24937 | D88: 385 | E88: 0 | F88: 0 | G88: 11 | H88: 4 | I88: 1 | J88: 0.0154 | K88: 1.28 | L88: =F88/B88 -> 0 | M88: =E88/D88 -> 0 | N88: =F88/E88 -> #DIV/0! | O88: =B88/E88 -> #DIV/0! | P88: =B88/G88 -> 44.843636
A89: =A88+1 -> 44284 | B89: 500 | C89: 27841 | D89: 298 | E89: 0 | F89: 0 | G89: 2 | H89: 1 | I89: 0 | J89: 0.0107 | K89: 1.68 | L89: =F89/B89 -> 0 | M89: =E89/D89 -> 0 | N89: =F89/E89 -> #DIV/0! | O89: =B89/E89 -> #DIV/0! | P89: =B89/G89 -> 250
A90: =A89+1 -> 44285 | B90: 500 | C90: 21271 | D90: 251 | E90: 0 | F90: 0 | G90: 2 | H90: 2 | I90: 2 | J90: 0.0118 | K90: 1.99 | L90: =F90/B90 -> 0 | M90: =E90/D90 -> 0 | N90: =F90/E90 -> #DIV/0! | O90: =B90/E90 -> #DIV/0! | P90: =B90/G90 -> 250
A91: =A90+1 -> 44286 | B91: 470.72 | C91: 24105 | D91: 289 | E91: 0 | F91: 0 | G91: 13 | H91: 6 | I91: 2 | J91: 0.0146 | K91: 1.64 | L91: =F91/B91 -> 0 | M91: =E91/D91 -> 0 | N91: =F91/E91 -> #DIV/0! | O91: =B91/E91 -> #DIV/0! | P91: =B91/G91 -> 36.209231
A92: =A91+1 -> 44287 | B92: 550.73 | C92: 18435 | D92: 333 | E92: 0 | F92: 0 | G92: 9 | H92: 4 | I92: 2 | J92: 0.0181 | K92: 1.65 | L92: =F92/B92 -> 0 | M92: =E92/D92 -> 0 | N92: =F92/E92 -> #DIV/0! | O92: =B92/E92 -> #DIV/0! | P92: =B92/G92 -> 61.192222
A93: =A92+1 -> 44288 | B93: 546.65 | C93: 20623 | D93: 335 | E93: 0 | F93: 0 | G93: 6 | H93: 5 | I93: 0 | J93: 0.0162 | K93: 1.63 | L93: =F93/B93 -> 0 | M93: =E93/D93 -> 0 | N93: =F93/E93 -> #DIV/0! | O93: =B93/E93 -> #DIV/0! | P93: =B93/G93 -> 91.108333
... A166: =A165+1 -> 44361 | B166: 244.01 | C166: 7345 | D166: 152 | E166: 0 | F166: 0 | G166: 0 | H166: 0 | I166: 0 | J166: 0.0207 | K166: 1.61 | L166: =F166/B166 -> 0 | M166: =E166/D166 -> 0 | N166: =F166/E166 -> #DIV/0! | O166: =B166/E166 -> #DIV/0! | P166: =B166/G166 -> #DIV/0!
A167: =A166+1 -> 44362 | B167: - | C167: - | D167: - | E167: - | F167: - | G167: - | H167: - | I167: - | J167: - | K167: - | L167: =F167/B167 -> #VALUE! | M167: =E167/D167 -> #VALUE! | N167: =F167/E167 -> #VALUE! | O167: =B167/E167 -> #VALUE! | P167: =B167/G167 -> #VALUE!
A168: =A167+1 -> 44363 | B168: 357.53 | C168: 9556 | D168: 216 | E168: 0 | F168: 0 | G168: 4 | H168: 0 | I168: 1 | J168: 0.0226 | K168: 1.66 | L168: =F168/B168 -> 0 | M168: =E168/D168 -> 0 | N168: =F168/E168 -> #DIV/0! | O168: =B168/E168 -> #DIV/0! | P168: =B168/G168 -> 89.3825
A169: =A168+1 -> 44364 | B169: 501.6 | C169: 13608 | D169: 299 | E169: 0 | F169: 0 | G169: 7 | H169: 1 | I169: 2 | J169: 0.022 | K169: 1.68 | L169: =F169/B169 -> 0 | M169: =E169/D169 -> 0 | N169: =F169/E169 -> #DIV/0! | O169: =B169/E169 -> #DIV/0! | P169: =B169/G169 -> 71.657143
A170: =A169+1 -> 44365 | B170: 522.36 | C170: 10297 | D170: 258 | E170: 0 | F170: 0 | G170: 4 | H170: 3 | I170: 2 | J170: 0.0251 | K170: 2.02 | L170: =F170/B170 -> 0 | M170: =E170/D170 -> 0 | N170: =F170/E170 -> #DIV/0! | O170: =B170/E170 -> #DIV/0! | P170: =B170/G170 -> 130.59
A171: =A170+1 -> 44366 | B171: 459.7 | C171: 14195 | D171: 261 | E171: 0 | F171: 0 | G171: 1 | H171: 2 | I171: 1 | J171: 0.0184 | K171: 1.76 | L171: =F171/B171 -> 0 | M171: =E171/D171 -> 0 | N171: =F171/E171 -> #DIV/0! | O171: =B171/E171 -> #DIV/0! | P171: =B171/G171 -> 459.7
A172: =A171+1 -> 44367 | B172: 559.26 | C172: 14061 | D172: 280 | E172: 0 | F172: 0 | G172: 3 | H172: 3 | I172: 3 | J172: 0.0199 | K172: 2 | L172: =F172/B172 -> 0 | M172: =E172/D172 -> 0 | N172: =F172/E172 -> #DIV/0! | O172: =B172/E172 -> #DIV/0! | P172: =B172/G172 -> 186.42
A173: =A172+1 -> 44368 | B173: 492.33 | C173: 31387 | D173: 285 | E173: 0 | F173: 0 | G173: 5 | H173: 4 | I173: 2 | J173: 0.0091 | K173: 1.73 | L173: =F173/B173 -> 0 | M173: =E173/D173 -> 0 | N173: =F173/E173 -> #DIV/0! | O173: =B173/E173 -> #DIV/0! | P173: =B173/G173 -> 98.466
A174: =A173+1 -> 44369 | B174: 815.14 | C174: 36340 | D174: 376 | E174: 1 | F174: 4200 | G174: 9 | H174: 1 | I174: 2 | J174: 0.0103 | K174: 2.17 | L174: =F174/B174 -> 5.1524891 | M174: =E174/D174 -> 0.0026595745 | N174: =F174/E174 -> 4200 | O174: =B174/E174 -> 815.14 | P174: =B174/G174 -> 90.571111
A175: =A174+1 -> 44370 | B175: 797.4 | C175: 38216 | D175: 365 | E175: 0 | F175: 0 | G175: 10 | H175: 2 | I175: 1 | J175: 0.0096 | K175: 2.18 | L175: =F175/B175 -> 0 | M175: =E175/D175 -> 0 | N175: =F175/E175 -> #DIV/0! | O175: =B175/E175 -> #DIV/0! | P175: =B175/G175 -> 79.74
A176: =A175+1 -> 44371 | B176: 849.32 | C176: 37379 | D176: 394 | E176: 0 | F176: 0 | G176: 8 | H176: 4 | I176: 1 | J176: 0.0105 | K176: 2.16 | L176: =F176/B176 -> 0 | M176: =E176/D176 -> 0 | N176: =F176/E176 -> #DIV/0! | O176: =B176/E176 -> #DIV/0! | P176: =B176/G176 -> 106.165
A177: =A176+1 -> 44372 | B177: 895.74 | C177: 35425 | D177: 409 | E177: 0 | F177: 0 | G177: 5 | H177: 2 | I177: 0 | J177: 0.0115 | K177: 2.19 | L177: =F177/B177 -> 0 | M177: =E177/D177 -> 0 | N177: =F177/E177 -> #DIV/0! | O177: =B177/E177 -> #DIV/0! | P177: =B177/G177 -> 179.148
A178: =A177+1 -> 44373 | B178: 900 | C178: 26554 | D178: 383 | E178: 0 | F178: 0 | G178: 11 | H178: 3 | I178: 3 | J178: 0.0144 | K178: 2.35 | L178: =F178/B178 -> 0 | M178: =E178/D178 -> 0 | N178: =F178/E178 -> #DIV/0! | O178: =B178/E178 -> #DIV/0! | P178: =B178/G178 -> 81.818182
A179: =A178+1 -> 44374 | B179: 900 | C179: 32522 | D179: 394 | E179: 0 | F179: 0 | G179: 4 | H179: 4 | I179: 3 | J179: 0.0121 | K179: 2.28 | L179: =F179/B179 -> 0 | M179: =E179/D179 -> 0 | N179: =F179/E179 -> #DIV/0! | O179: =B179/E179 -> #DIV/0! | P179: =B179/G179 -> 225
... A251: =A250+1 -> 44446 | B251: 43.8 | C251: 1242 | D251: 29 | E251: 0 | F251: 0 | G251: 0 | H251: 0 | I251: 0 | J251: 0.0233 | K251: 1.51 | L251: =F251/B251 -> 0 | M251: =E251/D251 -> 0 | N251: =F251/E251 -> #DIV/0! | O251: =B251/E251 -> #DIV/0! | P251: =B251/G251 -> #DIV/0!
A252: =A251+1 -> 44447 | B252: - | C252: - | D252: - | E252: - | F252: - | G252: - | H252: - | I252: - | J252: - | K252: - | L252: =F252/B252 -> #VALUE! | M252: =E252/D252 -> #VALUE! | N252: =F252/E252 -> #VALUE! | O252: =B252/E252 -> #VALUE! | P252: =B252/G252 -> #VALUE!
A253: =A252+1 -> 44448 | B253: 299.88 | C253: 4340 | D253: 136 | E253: 1 | F253: 0.01 | G253: 3 | H253: 2 | I253: 1 | J253: 0.0313 | K253: 2.21 | L253: =F253/B253 -> 3.3346672e-05 | M253: =E253/D253 -> 0.0073529412 | N253: =F253/E253 -> 0.01 | O253: =B253/E253 -> 299.88 | P253: =B253/G253 -> 99.96
A254: =A253+1 -> 44449 | B254: 342.66 | C254: 3888 | D254: 188 | E254: 0 | F254: 0 | G254: 1 | H254: 2 | I254: 0 | J254: 0.0484 | K254: 1.82 | L254: =F254/B254 -> 0 | M254: =E254/D254 -> 0 | N254: =F254/E254 -> #DIV/0! | O254: =B254/E254 -> #DIV/0! | P254: =B254/G254 -> 342.66
A255: =A254+1 -> 44450 | B255: - | L255: =F255/B255 -> #VALUE! | M255: =E255/D255 -> #DIV/0! | N255: =F255/E255 -> #DIV/0! | O255: =B255/E255 -> #VALUE! | P255: =B255/G255 -> #VALUE!
A256: =A255+1 -> 44451 | B256: 292.34 | C256: 3886 | D256: 196 | E256: 0 | F256: 0 | G256: 3 | H256: 1 | I256: 0 | J256: 0.0504 | K256: 1.49 | L256: =F256/B256 -> 0 | M256: =E256/D256 -> 0 | N256: =F256/E256 -> #DIV/0! | O256: =B256/E256 -> #DIV/0! | P256: =B256/G256 -> 97.446667
A257: =A256+1 -> 44452 | B257: 300 | C257: 3456 | D257: 145 | E257: 0 | F257: 0 | G257: 1 | H257: 0 | I257: 0 | J257: 0.042 | K257: 2.07 | L257: =F257/B257 -> 0 | M257: =E257/D257 -> 0 | N257: =F257/E257 -> #DIV/0! | O257: =B257/E257 -> #DIV/0! | P257: =B257/G257 -> 300
A258: =A257+1 -> 44453 | B258: 291.21 | C258: 4642 | D258: 160 | E258: 0 | F258: 0 | G258: 3 | H258: 1 | I258: 3 | J258: 0.0345 | K258: 1.82 | L258: =F258/B258 -> 0 | M258: =E258/D258 -> 0 | N258: =F258/E258 -> #DIV/0! | O258: =B258/E258 -> #DIV/0! | P258: =B258/G258 -> 97.07
A259: =A258+1 -> 44454 | B259: 299.35 | C259: 6187 | D259: 149 | E259: 0 | F259: 0 | G259: 3 | H259: 0 | I259: 1 | J259: 0.0241 | K259: 2.01 | L259: =F259/B259 -> 0 | M259: =E259/D259 -> 0 | N259: =F259/E259 -> #DIV/0! | O259: =B259/E259 -> #DIV/0! | P259: =B259/G259 -> 99.783333
A260: =A259+1 -> 44455 | B260: 300 | C260: 5595 | D260: 115 | E260: 0 | F260: 0 | G260: 2 | H260: 0 | I260: 0 | J260: 0.0206 | K260: 2.61 | L260: =F260/B260 -> 0 | M260: =E260/D260 -> 0 | N260: =F260/E260 -> #DIV/0! | O260: =B260/E260 -> #DIV/0! | P260: =B260/G260 -> 150
A261: =A260+1 -> 44456 | B261: 293.98 | C261: 4144 | D261: 148 | E261: 0 | F261: 0 | G261: 2 | H261: 1 | I261: 1 | J261: 0.0357 | K261: 1.99 | L261: =F261/B261 -> 0 | M261: =E261/D261 -> 0 | N261: =F261/E261 -> #DIV/0! | O261: =B261/E261 -> #DIV/0! | P261: =B261/G261 -> 146.99
A262: =A261+1 -> 44457 | B262: 297.31 | C262: 4038 | D262: 148 | E262: 0 | F262: 0 | G262: 0 | H262: 1 | I262: 1 | J262: 0.0367 | K262: 2.01 | L262: =F262/B262 -> 0 | M262: =E262/D262 -> 0 | N262: =F262/E262 -> #DIV/0! | O262: =B262/E262 -> #DIV/0! | P262: =B262/G262 -> #DIV/0!
...

Sheet 对比超品日
A2: 1月 | B2: Cost 花费 | D2: IMP 展示 | E2: Click 点击 | F2: Order 订单 | G2: Sales 销量 | H2: ShoppingCart 加入购物车 | I2: Bookmark-Product 宝贝收藏 | J2: Bookmark-Store 店铺收藏 | L2: CTR 点击率 | M2: CPC 点击成本 | O2: CPM 千次展现成本 | P2: ROI 投资回报率 | R2: CVR 点击转化率 | T2: ASP 订单均价 | U2: Cporder 订单成本 | V2: CPshopping cart 加购成本
A3: 钻展 | B3: 6.05 | D3: 1427 | E3: 1 | F3: - | G3: - | H3: - | I3: - | J3: - | L3: - | M3: - | O3: - | P3: - | R3: - | T3: - | U3: - | V3: -
A4: 明星店铺 | B4: 2731.45 | D4: 7691 | E4: 349 | F4: 0 | G4: 0 | H4: 2 | I4: 2 | J4: 11 | L4: =E4/D4 -> 0.045377714 | M4: =B4/E4 -> 7.8265043 | O4: =(B4/D4)*1000 -> 355.14888 | P4: =G4/B4 -> 0 | R4: =F4/E4 -> 0 | T4: =G4/F4 -> #DIV/0! | U4: =B4/F4 -> #DIV/0! | V4: =B4/H4 -> 1365.725
A5: 直通车 | B5: 1952.96 | D5: 39544 | E5: 1253 | F5: 2 | G5: 198 | H5: 46 | I5: 4 | J5: 8 | L5: =E5/D5 -> 0.031686223 | M5: =B5/E5 -> 1.5586273 | O5: =(B5/D5)*1000 -> 49.387012 | P5: =G5/B5 -> 0.10138456 | R5: =F5/E5 -> 0.0015961692 | T5: =G5/F5 -> 99 | U5: =B5/F5 -> 976.48 | V5: =B5/H5 -> 42.455652
A6: 引力魔方 | B6: - | D6: - | E6: - | F6: - | G6: - | H6: - | I6: - | J6: - | L6: - | M6: - | O6: - | P6: - | R6: - | T6: - | U6: - | V6: -
A7: 总计 | B7: =SUM(B3:B6) -> 4690.46 | D7: =SUM(D3:D6) -> 48662 | E7: =SUM(E3:E6) -> 1603 | F7: =SUM(F3:F6) -> 2 | G7: =SUM(G3:G6) -> 198 | H7: =SUM(H3:H6) -> 48 | I7: =SUM(I3:I6) -> 6 | J7: =SUM(J3:J6) -> 19 | L7: =E7/D7 -> 0.032941515 | M7: =B7/E7 -> 2.9260512 | O7: =(B7/D7)*1000 -> 96.388558 | P7: =G7/B7 -> 0.042213344 | R7: =F7/E7 -> 0.0012476606 | T7: =G7/F7 -> 99 | U7: =B7/F7 -> 2345.23 | V7: =B7/H7 -> 97.717917
A10: 2月 | B10: Cost 花费 | D10: IMP 展示 | E10: Click 点击 | F10: Order 订单 | G10: Sales 销量 | H10: ShoppingCart 加入购物车 | I10: Bookmark-Product 宝贝收藏 | J10: Bookmark-Store 店铺收藏 | L10: CTR 点击率 | M10: CPC 点击成本 | O10: CPM 千次展现成本 | P10: ROI 投资回报率 | R10: CVR 点击转化率 | T10: ASP 订单均价 | U10: Cporder 订单成本 | V10: CPshopping cart 加购成本
A11: 明星店铺 | B11: 22646 | D11: 24719 | E11: 1047 | F11: 1 | G11: 99 | H11: 13 | I11: 3 | J11: 20 | L11: =E11/D11 -> 0.042356082 | M11: =B11/E11 -> 21.629417 | O11: =(B11/D11)*1000 -> 916.13738 | P11: =G11/B11 -> 0.004371633 | R11: =F11/E11 -> 0.00095510984 | T11: =G11/F11 -> 99 | U11: =B11/F11 -> 22646 | V11: =B11/H11 -> 1742
A12: 直通车 | B12: 5688.53 | D12: 84202 | E12: 2773 | F12: 2 | G12: 198 | H12: 51 | I12: 14 | J12: 14 | L12: =E12/D12 -> 0.032932709 | M12: =B12/E12 -> 2.0513992 | O12: =(B12/D12)*1000 -> 67.558134 | P12: =G12/B12 -> 0.034806883 | R12: =F12/E12 -> 0.00072124053 | T12: =G12/F12 -> 99 | U12: =B12/F12 -> 2844.265 | V12: =B12/H12 -> 111.5398
A13: 引力魔方 | B13: 1337.93 | D13: 197627 | E13: 1649 | F13: 0 | G13: 0 | H13: 8 | I13: 12 | J13: 2 | L13: =E13/D13 -> 0.0083440016 | M13: =B13/E13 -> 0.8113584 | O13: =(B13/D13)*1000 -> 6.7699758 | P13: =G13/B13 -> 0 | R13: =F13/E13 -> 0 | T13: =G13/F13 -> #DIV/0! | U13: =B13/F13 -> #DIV/0! | V13: =B13/H13 -> 167.24125
A14: 总计 | B14: =SUM(B11:B13) -> 29672.46 | D14: =SUM(D11:D13) -> 306548 | E14: =SUM(E11:E13) -> 5469 | F14: =SUM(F11:F13) -> 3 | G14: =SUM(G11:G13) -> 297 | H14: =SUM(H11:H13) -> 72 | I14: =SUM(I11:I13) -> 29 | J14: =SUM(J11:J13) -> 36 | L14: =E14/D14 -> 0.017840599 | M14: =B14/E14 -> 5.4255732 | O14: =(B14/D14)*1000 -> 96.795477 | P14: =G14/B14 -> 0.010009281 | R14: =F14/E14 -> 0.00054854635 | T14: =G14/F14 -> 99 | U14: =B14/F14 -> 9890.82 | V14: =B14/H14 -> 412.1175
A17: 3月 | B17: Cost 花费 | D17: IMP 展示 | E17: Click 点击 | F17: Order 订单 | G17: Sales 销量 | H17: ShoppingCart 加入购物车 | I17: Bookmark-Product 宝贝收藏 | J17: Bookmark-Store 店铺收藏 | L17: CTR 点击率 | M17: CPC 点击成本 | O17: CPM 千次展现成本 | P17: ROI 投资回报率 | R17: CVR 点击转化率 | T17: ASP 订单均价 | U17: Cporder 订单成本 | V17: CPshopping cart 加购成本
A18: 明星店铺 | B18: 2866.29 | D18: 12670 | E18: 404 | F18: 3 | G18: 600 | H18: 2 | I18: 1 | J18: 12 | L18: =E18/D18 -> 0.031886346 | M18: =B18/E18 -> 7.0947772 | O18: =(B18/D18)*1000 -> 226.22652 | P18: =G18/B18 -> 0.20932983 | R18: =F18/E18 -> 0.0074257426 | T18: =G18/F18 -> 200 | U18: =B18/F18 -> 955.43 | V18: =B18/H18 -> 1433.145
A19: 直通车 | B19: 3311.5 | D19: 120004 | E19: 2346 | F19: 0 | G19: 0 | H19: 1 | I19: 2 | J19: 8 | L19: =E19/D19 -> 0.019549348 | M19: =B19/E19 -> 1.4115516 | O19: =(B19/D19)*1000 -> 27.594914 | P19: =G19/B19 -> 0 | R19: =F19/E19 -> 0 | T19: =G19/F19 -> #DIV/0! | U19: =B19/F19 -> #DIV/0! | V19: =B19/H19 -> 3311.5
A20: 引力魔方 | B20: 2031.5 | D20: 219571 | E20: 1511 | F20: 0 | G20: 0 | H20: 2 | I20: 14 | J20: 0 | L20: =E20/D20 -> 0.0068816009 | M20: =B20/E20 -> 1.3444739 | O20: =(B20/D20)*1000 -> 9.2521326 | P20: =G20/B20 -> 0 | R20: =F20/E20 -> 0 | T20: =G20/F20 -> #DIV/0! | U20: =B20/F20 -> #DIV/0! | V20: =B20/H20 -> 1015.75
A21: 总计 | B21: =SUM(B18:B20) -> 8209.29 | D21: =SUM(D18:D20) -> 352245 | E21: =SUM(E18:E20) -> 4261 | F21: =SUM(F18:F20) -> 3 | G21: =SUM(G18:G20) -> 600 | H21: =SUM(H18:H20) -> 5 | I21: =SUM(I18:I20) -> 17 | J21: =SUM(J18:J20) -> 20 | L21: =E21/D21 -> 0.012096694 | M21: =B21/E21 -> 1.9266111 | O21: =(B21/D21)*1000 -> 23.305625 | P21: =G21/B21 -> 0.073087928 | R21: =F21/E21 -> 0.00070406008 | T21: =G21/F21 -> 200 | U21: =B21/F21 -> 2736.43 | V21: =B21/H21 -> 1641.858
A25: 2023年
A26: 8月 | B26: Cost 花费 | D26: IMP 展示 | E26: Click 点击 | F26: Order 订单 | G26: Sales 销量 | H26: ShoppingCart 加入购物车 | I26: Bookmark-Product 宝贝收藏 | J26: Bookmark-Store 店铺收藏 | L26: CTR 点击率 | M26: CPC 点击成本 | O26: CPM 千次展现成本 | P26: ROI 投资回报率 | R26: CVR 点击转化率 | T26: ASP 订单均价 | U26: Cporder 订单成本 | V26: CPshopping cart 加购成本
A27: 明星店铺 | B27: =SUM(明星店铺!B514:B522) -> 496.42 | D27: =SUM(明星店铺!C514:C522) -> 670 | E27: =SUM(明星店铺!D514:D522) -> 180 | F27: =SUM(明星店铺!E514:E522) -> 3 | G27: =SUM(明星店铺!F514:F522) -> 3 | H27: =SUM(明星店铺!G514:G522) -> 38 | I27: =SUM(明星店铺!H514:H522) -> 8 | J27: =SUM(明星店铺!I514:I522) -> 6 | L27: =E27/D27 -> 0.26865672 | M27: =B27/E27 -> 2.7578889 | O27: =(B27/D27)*1000 -> 740.92537 | P27: =G27/B27 -> 0.0060432698 | R27: =F27/E27 -> 0.016666667 | T27: =G27/F27 -> 1 | U27: =B27/F27 -> 165.47333 | V27: =B27/H27 -> 13.063684
A28: 直通车 | B28: =SUM(直通车!B514:B522) -> 8646.78 | D28: =SUM(直通车!C514:C522) -> 32943 | E28: =SUM(直通车!D514:D522) -> 2523 | F28: =SUM(直通车!E514:E522) -> 1 | G28: =SUM(直通车!F514:F522) -> 1 | H28: =SUM(直通车!G514:G522) -> 62 | I28: =SUM(直通车!H514:H522) -> 37 | J28: =SUM(直通车!I514:I522) -> 12 | L28: =E28/D28 -> 0.076586832 | M28: =B28/E28 -> 3.4271819 | O28: =(B28/D28)*1000 -> 262.47701 | P28: =G28/B28 -> 0.00011564999 | R28: =F28/E28 -> 0.00039635355 | T28: =G28/F28 -> 1 | U28: =B28/F28 -> 8646.78 | V28: =B28/H28 -> 139.46419
A29: 引力魔方 | B29: =SUM(引力魔方!B413:B421) -> 4176.9 | D29: =SUM(引力魔方!C413:C421) -> 444197 | E29: =SUM(引力魔方!D413:D421) -> 2732 | F29: =SUM(引力魔方!E413:E421) -> 0 | G29: =SUM(引力魔方!F413:F421) -> 0 | H29: =SUM(引力魔方!G413:G421) -> 25 | I29: =SUM(引力魔方!H413:H421) -> 14 | J29: =SUM(引力魔方!I413:I421) -> 2 | L29: =E29/D29 -> 0.0061504242 | M29: =B29/E29 -> 1.5288799 | O29: =(B29/D29)*1000 -> 9.4032603 | P29: =G29/B29 -> 0 | R29: =F29/E29 -> 0 | T29: =G29/F29 -> #DIV/0! | U29: =B29/F29 -> #DIV/0! | V29: =B29/H29 -> 167.076
A30: 万相台 | B30: =SUM(万相台!B2:B10) -> 1014.03 | D30: =SUM(万相台!C2:C10) -> 96394 | E30: =SUM(万相台!D2:D10) -> 1126 | F30: =SUM(万相台!E2:E10) -> 0 | G30: =SUM(万相台!F2:F10) -> 0 | H30: =SUM(万相台!G2:G10) -> 22 | I30: =SUM(万相台!H2:H10) -> 12 | L30: =E30/D30 -> 0.011681225 | M30: =B30/E30 -> 0.9005595 | O30: =(B30/D30)*1000 -> 10.519638 | P30: =G30/B30 -> 0 | R30: =F30/E30 -> 0 | T30: =G30/F30 -> #DIV/0! | U30: =B30/F30 -> #DIV/0! | V30: =B30/H30 -> 46.092273
A31: 总计 | B31: =SUM(B27:B30) -> 14334.13 | D31: =SUM(D27:D30) -> 574204 | E31: =SUM(E27:E30) -> 6561 | F31: =SUM(F27:F30) -> 4 | G31: =SUM(G27:G30) -> 4 | H31: =SUM(H27:H30) -> 147 | I31: =SUM(I27:I30) -> 71 | J31: =SUM(J27:J30) -> 20 | L31: =E31/D31 -> 0.011426253 | M31: =B31/E31 -> 2.1847478 | O31: =(B31/D31)*1000 -> 24.96348 | P31: =G31/B31 -> 0.00027905426 | R31: =F31/E31 -> 0.00060966316 | T31: =G31/F31 -> 1 | U31: =B31/F31 -> 3583.5325 | V31: =B31/H31 -> 97.511088
A33: 9月 | B33: Cost 花费 | D33: IMP 展示 | E33: Click 点击 | F33: Order 订单 | G33: Sales 销量 | H33: ShoppingCart 加入购物车 | I33: Bookmark-Product 宝贝收藏 | J33: Bookmark-Store 店铺收藏 | K33: 总收藏数 | L33: CTR 点击率 | M33: CPC 点击成本 | O33: CPM 千次展现成本 | P33: ROI 投资回报率 | R33: CVR 点击转化率 | T33: ASP 订单均价 | U33: Cporder 订单成本 | V33: CPshopping cart 加购成本
A34: 明星店铺 | B34: =SUM(明星店铺!B523:B552) -> 1129.72 | D34: =SUM(明星店铺!C523:C552) -> 1507 | E34: =SUM(明星店铺!D523:D552) -> 586 | F34: =SUM(明星店铺!E523:E552) -> 5 | G34: =SUM(明星店铺!F523:F552) -> 7282.8 | H34: =SUM(明星店铺!G523:G552) -> 84 | I34: =SUM(明星店铺!H523:H552) -> 17 | J34: =SUM(明星店铺!I523:I552) -> 26 | K34: =I34+J34 -> 43 | L34: =E34/D34 -> 0.38885202 | M34: =B34/E34 -> 1.9278498 | O34: =(B34/D34)*1000 -> 749.64831 | P34: =G34/B34 -> 6.4465531 | R34: =F34/E34 -> 0.0085324232 | T34: =G34/F34 -> 1456.56 | U34: =B34/F34 -> 225.944 | V34: =B34/H34 -> 13.449048
A35: 直通车 | B35: =SUM(直通车!B523:B552) -> 38763.28 | D35: =SUM(直通车!C523:C552) -> 174099 | E35: =SUM(直通车!D523:D552) -> 10706 | F35: =SUM(直通车!E523:E552) -> 19 | G35: =SUM(直通车!F523:F552) -> 24965.1 | H35: =SUM(直通车!G523:G552) -> 252 | I35: =SUM(直通车!H523:H552) -> 177 | J35: =SUM(直通车!I523:I552) -> 88 | K35: =I35+J35 -> 265 | L35: =E35/D35 -> 0.061493748 | M35: =B35/E35 -> 3.6207061 | O35: =(B35/D35)*1000 -> 222.65079 | P35: =G35/B35 -> 0.64403993 | R35: =F35/E35 -> 0.0017747058 | T35: =G35/F35 -> 1313.9526 | U35: =B35/F35 -> 2040.1726 | V35: =B35/H35 -> 153.82254
A36: 引力魔方 | B36: =SUM(引力魔方!B422:B451) -> 21321.69 | D36: =SUM(引力魔方!C422:C451) -> 1533981 | E36: =SUM(引力魔方!D422:D451) -> 11155 | F36: =SUM(引力魔方!E422:E451) -> 0 | G36: =SUM(引力魔方!F422:F451) -> 0 | H36: =SUM(引力魔方!G422:G451) -> 103 | I36: =SUM(引力魔方!H422:H451) -> 64 | J36: =SUM(引力魔方!I422:I451) -> 16 | K36: =I36+J36 -> 80 | L36: =E36/D36 -> 0.0072719284 | M36: =B36/E36 -> 1.9114021 | O36: =(B36/D36)*1000 -> 13.899579 | P36: =G36/B36 -> 0 | R36: =F36/E36 -> 0 | T36: =G36/F36 -> #DIV/0! | U36: =B36/F36 -> #DIV/0! | V36: =B36/H36 -> 207.0067
A37: 万相台 | B37: =SUM(万相台!B11:B40) -> 6066.03 | D37: =SUM(万相台!C11:C40) -> 756412 | E37: =SUM(万相台!D11:D40) -> 9008 | F37: =SUM(万相台!E11:E40) -> 7 | G37: =SUM(万相台!F11:F40) -> 6379.9 | H37: =SUM(万相台!G11:G40) -> 115 | I37: =SUM(万相台!H11:H40) -> 96 | K37: =I37+J37 -> 96 | L37: =E37/D37 -> 0.011908854 | M37: =B37/E37 -> 0.67340475 | O37: =(B37/D37)*1000 -> 8.0194788 | P37: =G37/B37 -> 1.0517422 | R37: =F37/E37 -> 0.00077708703 | T37: =G37/F37 -> 911.41429 | U37: =B37/F37 -> 866.57571 | V37: =B37/H37 -> 52.748087
A38: 总计 | B38: =SUM(B34:B37) -> 67280.72 | D38: =SUM(D34:D37) -> 2465999 | E38: =SUM(E34:E37) -> 31455 | F38: =SUM(F34:F37) -> 31 | G38: =SUM(G34:G37) -> 38627.8 | H38: =SUM(H34:H37) -> 554 | I38: =SUM(I34:I37) -> 354 | J38: =SUM(J34:J37) -> 130 | K38: =I38+J38 -> 484 | L38: =E38/D38 -> 0.01275548 | M38: =B38/E38 -> 2.1389515 | O38: =(B38/D38)*1000 -> 27.283353 | P38: =G38/B38 -> 0.57412881 | R38: =F38/E38 -> 0.00098553489 | T38: =G38/F38 -> 1246.0581 | U38: =B38/F38 -> 2170.3458 | V38: =B38/H38 -> 121.44534
A40: 10月 | B40: Cost 花费 | D40: IMP 展示 | E40: Click 点击 | F40: Order 订单 | G40: Sales 销量 | H40: ShoppingCart 加入购物车 | I40: Bookmark-Product 宝贝收藏 | J40: Bookmark-Store 店铺收藏 | K40: 总收藏数 | L40: CTR 点击率 | M40: CPC 点击成本 | O40: CPM 千次展现成本 | P40: ROI 投资回报率 | R40: CVR 点击转化率 | T40: ASP 订单均价 | U40: Cporder 订单成本 | V40: CPshopping cart 加购成本
A41: 明星店铺 | B41: =SUM(明星店铺!B553:B583) -> 8005.24 | D41: =SUM(明星店铺!C553:C583) -> 9248 | E41: =SUM(明星店铺!D553:D583) -> 3856 | F41: =SUM(明星店铺!E553:E583) -> 129 | G41: =SUM(明星店铺!F553:F583) -> 1401487.2 | H41: =SUM(明星店铺!G553:G583) -> 747 | I41: =SUM(明星店铺!H553:H583) -> 232 | J41: =SUM(明星店铺!I553:I583) -> 442 | K41: =I41+J41 -> 674 | L41: =E41/D41 -> 0.41695502 | M41: =B41/E41 -> 2.0760477 | O41: =(B41/D41)*1000 -> 865.61851 | P41: =G41/B41 -> 175.07123 | R41: =F41/E41 -> 0.033454357 | T41: =G41/F41 -> 10864.242 | U41: =B41/F41 -> 62.056124 | V41: =B41/H41 -> 10.716519
A42: 直通车 | B42: =SUM(直通车!B553:B583) -> 57558.86 | D42: =SUM(直通车!C553:C583) -> 219210 | E42: =SUM(直通车!D553:D583) -> 18951 | F42: =SUM(直通车!E553:E583) -> 133 | G42: =SUM(直通车!F553:F583) -> 1640797.3 | H42: =SUM(直通车!G553:G583) -> 924 | I42: =SUM(直通车!H553:H583) -> 626 | J42: =SUM(直通车!I553:I583) -> 336 | K42: =I42+J42 -> 962 | L42: =E42/D42 -> 0.086451348 | M42: =B42/E42 -> 3.0372466 | O42: =(B42/D42)*1000 -> 262.57406 | P42: =G42/B42 -> 28.506425 | R42: =F42/E42 -> 0.0070180993 | T42: =G42/F42 -> 12336.822 | U42: =B42/F42 -> 432.77338 | V42: =B42/H42 -> 62.293139
A43: 引力魔方 | B43: =SUM(引力魔方!B452:B482) -> 30457.64 | D43: =SUM(引力魔方!C452:C482) -> 806896 | E43: =SUM(引力魔方!D452:D482) -> 10898 | F43: =SUM(引力魔方!E452:E482) -> 64 | G43: =SUM(引力魔方!F452:F482) -> 665174.8 | H43: =SUM(引力魔方!G452:G482) -> 206 | I43: =SUM(引力魔方!H452:H482) -> 94 | J43: =SUM(引力魔方!I452:I482) -> 78 | K43: =I43+J43 -> 172 | L43: =E43/D43 -> 0.013506078 | M43: =B43/E43 -> 2.7947917 | O43: =(B43/D43)*1000 -> 37.746674 | P43: =G43/B43 -> 21.839341 | R43: =F43/E43 -> 0.0058726372 | T43: =G43/F43 -> 10393.356 | U43: =B43/F43 -> 475.90062 | V43: =B43/H43 -> 147.85262
A44: 万相台 | B44: =SUM(万相台!B41:B71) -> 9480.74 | D44: =SUM(万相台!C41:C71) -> 91699 | E44: =SUM(万相台!D41:D71) -> 4467 | F44: =SUM(万相台!E41:E71) -> 12 | G44: =SUM(万相台!F41:F71) -> 67545.5 | H44: =SUM(万相台!G41:G71) -> 114 | I44: =SUM(万相台!H41:H71) -> 60 | K44: =I44+J44 -> 60 | L44: =E44/D44 -> 0.048713726 | M44: =B44/E44 -> 2.1223953 | O44: =(B44/D44)*1000 -> 103.38979 | P44: =G44/B44 -> 7.1244966 | R44: =F44/E44 -> 0.0026863667 | T44: =G44/F44 -> 5628.7917 | U44: =B44/F44 -> 790.06167 | V44: =B44/H44 -> 83.164386
A45: 总计 | B45: =SUM(B41:B44) -> 105502.48 | D45: =SUM(D41:D44) -> 1127053 | E45: =SUM(E41:E44) -> 38172 | F45: =SUM(F41:F44) -> 338 | G45: =SUM(G41:G44) -> 3775004.8 | H45: =SUM(H41:H44) -> 1991 | I45: =SUM(I41:I44) -> 1012 | J45: =SUM(J41:J44) -> 856 | K45: =I45+J45 -> 1868 | L45: =E45/D45 -> 0.03386886 | M45: =B45/E45 -> 2.7638709 | O45: =(B45/D45)*1000 -> 93.609156 | P45: =G45/B45 -> 35.781195 | R45: =F45/E45 -> 0.0088546579 | T45: =G45/F45 -> 11168.653 | U45: =B45/F45 -> 312.13751 | V45: =B45/H45 -> 52.989694
A47: 11月 | B47: Cost 花费 | D47: IMP 展示 | E47: Click 点击 | F47: Order 订单 | G47: Sales 销量 | H47: ShoppingCart 加入购物车 | I47: Bookmark-Product 宝贝收藏 | J47: Bookmark-Store 店铺收藏 | K47: 总收藏数 | L47: CTR 点击率 | M47: CPC 点击成本 | O47: CPM 千次展现成本 | P47: ROI 投资回报率 | R47: CVR 点击转化率 | T47: ASP 订单均价 | U47: Cporder 订单成本 | V47: CPshopping cart 加购成本
A48: 明星店铺 | B48: =SUM(明星店铺!B584:B613) -> 6386.06 | D48: =SUM(明星店铺!C584:C613) -> 6596 | E48: =SUM(明星店铺!D584:D613) -> 2650 | F48: =SUM(明星店铺!E584:E613) -> 63 | G48: =SUM(明星店铺!F584:F613) -> 477277.22 | H48: =SUM(明星店铺!G584:G613) -> 661 | I48: =SUM(明星店铺!H584:H613) -> 121 | J48: =SUM(明星店铺!I584:I613) -> 280 | K48: =I48+J48 -> 401 | L48: =E48/D48 -> 0.40175864 | M48: =B48/E48 -> 2.409834 | O48: =(B48/D48)*1000 -> 968.17162 | P48: =G48/B48 -> 74.737353 | R48: =F48/E48 -> 0.023773585 | T48: =G48/F48 -> 7575.8289 | U48: =B48/F48 -> 101.36603 | V48: =B48/H48 -> 9.6612103
A49: 直通车 | B49: =SUM(直通车!B584:B613) -> 85001.26 | D49: =SUM(直通车!C584:C613) -> 273932 | E49: =SUM(直通车!D584:D613) -> 22062 | F49: =SUM(直通车!E584:E613) -> 111 | G49: =SUM(直通车!F584:F613) -> 872404.39 | H49: =SUM(直通车!G584:G613) -> 1099 | I49: =SUM(直通车!H584:H613) -> 513 | J49: =SUM(直通车!I584:I613) -> 285 | K49: =I49+J49 -> 798 | L49: =E49/D49 -> 0.080538236 | M49: =B49/E49 -> 3.8528356 | O49: =(B49/D49)*1000 -> 310.30059 | P49: =G49/B49 -> 10.263429 | R49: =F49/E49 -> 0.0050312755 | T49: =G49/F49 -> 7859.499 | U49: =B49/F49 -> 765.77712 | V49: =B49/H49 -> 77.344186
A50: 引力魔方 | B50: =SUM(引力魔方!B483:B512) -> 47468.12 | D50: =SUM(引力魔方!C483:C512) -> 3705258 | E50: =SUM(引力魔方!D483:D512) -> 43076 | F50: =SUM(引力魔方!E483:E512) -> 48 | G50: =SUM(引力魔方!F483:F512) -> 489457.12 | H50: =SUM(引力魔方!G483:G512) -> 606 | I50: =SUM(引力魔方!H483:H512) -> 175 | J50: =SUM(引力魔方!I483:I512) -> 79 | K50: =I50+J50 -> 254 | L50: =E50/D50 -> 0.011625641 | M50: =B50/E50 -> 1.1019621 | O50: =(B50/D50)*1000 -> 12.811016 | P50: =G50/B50 -> 10.311281 | R50: =F50/E50 -> 0.0011143096 | T50: =G50/F50 -> 10197.023 | U50: =B50/F50 -> 988.91917 | V50: =B50/H50 -> 78.330231
A51: 万相台 | B51: =SUM(万相台!B72:B101) -> 10182.62 | D51: =SUM(万相台!C72:C101) -> 257113 | E51: =SUM(万相台!D72:D101) -> 10905 | F51: =SUM(万相台!E72:E101) -> 29 | G51: =SUM(万相台!F72:F101) -> 265570.08 | H51: =SUM(万相台!G72:G101) -> 231 | I51: =SUM(万相台!H72:H101) -> 56 | K51: =I51+J51 -> 56 | L51: =E51/D51 -> 0.042413258 | M51: =B51/E51 -> 0.93375699 | O51: =(B51/D51)*1000 -> 39.603676 | P51: =G51/B51 -> 26.080722 | R51: =F51/E51 -> 0.0026593306 | T51: =G51/F51 -> 9157.589 | U51: =B51/F51 -> 351.12483 | V51: =B51/H51 -> 44.080606
A52: 总计 | B52: =SUM(B48:B51) -> 149038.06 | D52: =SUM(D48:D51) -> 4242899 | E52: =SUM(E48:E51) -> 78693 | F52: =SUM(F48:F51) -> 251 | G52: =SUM(G48:G51) -> 2104708.8 | H52: =SUM(H48:H51) -> 2597 | I52: =SUM(I48:I51) -> 865 | J52: =SUM(J48:J51) -> 644 | K52: =I52+J52 -> 1509 | L52: =E52/D52 -> 0.018546989 | M52: =B52/E52 -> 1.8939176 | O52: =(B52/D52)*1000 -> 35.126469 | P52: =G52/B52 -> 14.121955 | R52: =F52/E52 -> 0.0031896103 | T52: =G52/F52 -> 8385.2941 | U52: =B52/F52 -> 593.77713 | V52: =B52/H52 -> 57.388548
A54: 12月 | B54: Cost 花费 | D54: IMP 展示 | E54: Click 点击 | F54: Order 订单 | G54: Sales 销量 | H54: ShoppingCart 加入购物车 | I54: Bookmark-Product 宝贝收藏 | J54: Bookmark-Store 店铺收藏 | K54: 总收藏数 | L54: CTR 点击率 | M54: CPC 点击成本 | O54: CPM 千次展现成本 | P54: ROI 投资回报率 | R54: CVR 点击转化率 | T54: ASP 订单均价 | U54: Cporder 订单成本 | V54: CPshopping cart 加购成本
A55: 明星店铺 | B55: =SUM(明星店铺!B614:B644) -> 3841.38 | D55: =SUM(明星店铺!C614:C644) -> 4328 | E55: =SUM(明星店铺!D614:D644) -> 1524 | F55: =SUM(明星店铺!E614:E644) -> 8 | G55: =SUM(明星店铺!F614:F644) -> 134928 | H55: =SUM(明星店铺!G614:G644) -> 340 | I55: =SUM(明星店铺!H614:H644) -> 67 | J55: =SUM(明星店铺!I614:I644) -> 113 | K55: =I55+J55 -> 180 | L55: =E55/D55 -> 0.35212569 | M55: =B55/E55 -> 2.5205906 | O55: =(B55/D55)*1000 -> 887.5647 | P55: =G55/B55 -> 35.124877 | R55: =F55/E55 -> 0.0052493438 | T55: =G55/F55 -> 16866 | U55: =B55/F55 -> 480.1725 | V55: =B55/H55 -> 11.298176
A56: 直通车 | B56: =SUM(直通车!B614:B644) -> 121344.68 | D56: =SUM(直通车!C614:C644) -> 299486 | E56: =SUM(直通车!D614:D644) -> 21703 | F56: =SUM(直通车!E614:E644) -> 18 | G56: =SUM(直通车!F614:F644) -> 275328 | H56: =SUM(直通车!G614:G644) -> 891 | I56: =SUM(直通车!H614:H644) -> 353 | J56: =SUM(直通车!I614:I644) -> 219 | K56: =I56+J56 -> 572 | L56: =E56/D56 -> 0.072467494 | M56: =B56/E56 -> 5.591148 | O56: =(B56/D56)*1000 -> 405.17649 | P56: =G56/B56 -> 2.2689745 | R56: =F56/E56 -> 0.00082937843 | T56: =G56/F56 -> 15296 | U56: =B56/F56 -> 6741.3714 | V56: =B56/H56 -> 136.18932
A57: 引力魔方 | B57: =SUM(引力魔方!B513:B543) -> 93923.95 | D57: =SUM(引力魔方!C513:C543) -> 5708966 | E57: =SUM(引力魔方!D513:D543) -> 120544 | F57: =SUM(引力魔方!E513:E543) -> 6 | G57: =SUM(引力魔方!F513:F543) -> 49886 | H57: =SUM(引力魔方!G513:G543) -> 429 | I57: =SUM(引力魔方!H513:H543) -> 546 | J57: =SUM(引力魔方!I513:I543) -> 66 | K57: =I57+J57 -> 612 | L57: =E57/D57 -> 0.021114857 | M57: =B57/E57 -> 0.77916736 | O57: =(B57/D57)*1000 -> 16.452007 | P57: =G57/B57 -> 0.53113184 | R57: =F57/E57 -> 4.9774356e-05 | T57: =G57/F57 -> 8314.3333 | U57: =B57/F57 -> 15653.992 | V57: =B57/H57 -> 218.93695
A58: 万相台 | B58: =SUM(万相台!B102:B132) -> 12814.29 | D58: =SUM(万相台!C102:C132) -> 913809 | E58: =SUM(万相台!D102:D132) -> 13322 | F58: =SUM(万相台!E102:E132) -> 5 | G58: =SUM(万相台!F102:F132) -> 75770 | H58: =SUM(万相台!G102:G132) -> 242 | I58: =SUM(万相台!H102:H132) -> 83 | K58: =I58+J58 -> 83 | L58: =E58/D58 -> 0.014578539 | M58: =B58/E58 -> 0.96188936 | O58: =(B58/D58)*1000 -> 14.022941 | P58: =G58/B58 -> 5.91293 | R58: =F58/E58 -> 0.00037531902 | T58: =G58/F58 -> 15154 | U58: =B58/F58 -> 2562.858 | V58: =B58/H58 -> 52.951612
A59: 总计 | B59: =SUM(B55:B58) -> 231924.3 | D59: =SUM(D55:D58) -> 6926589 | E59: =SUM(E55:E58) -> 157093 | F59: =SUM(F55:F58) -> 37 | G59: =SUM(G55:G58) -> 535912 | H59: =SUM(H55:H58) -> 1902 | I59: =SUM(I55:I58) -> 1049 | J59: =SUM(J55:J58) -> 398 | K59: =I59+J59 -> 1447 | L59: =E59/D59 -> 0.022679706 | M59: =B59/E59 -> 1.4763503 | O59: =(B59/D59)*1000 -> 33.483191 | P59: =G59/B59 -> 2.3107194 | R59: =F59/E59 -> 0.00023552927 | T59: =G59/F59 -> 14484.108 | U59: =B59/F59 -> 6268.2245 | V59: =B59/H59 -> 121.93707
A63: 2024年
A64: 1月 | B64: Cost 花费 | D64: IMP 展示 | E64: Click 点击 | F64: Order 订单 | G64: Sales 销量 | H64: ShoppingCart 加入购物车 | I64: Bookmark-Product 宝贝收藏 | J64: Bookmark-Store 店铺收藏 | K64: 总收藏数 | L64: CTR 点击率 | M64: CPC 点击成本 | O64: CPM 千次展现成本 | P64: ROI 投资回报率 | R64: CVR 点击转化率 | T64: ASP 订单均价 | U64: Cporder 订单成本 | V64: CPshopping cart 加购成本
A65: 明星店铺 | B65: =SUM(明星店铺!B645:B675) -> 4413.62 | D65: =SUM(明星店铺!C645:C675) -> 5217 | E65: =SUM(明星店铺!D645:D675) -> 1813 | F65: =SUM(明星店铺!E645:E675) -> 8 | G65: =SUM(明星店铺!F645:F675) -> 118804 | H65: =SUM(明星店铺!G645:G675) -> 442 | I65: =SUM(明星店铺!H645:H675) -> 43 | J65: =SUM(明星店铺!I645:I675) -> 117 | K65: =I65+J65 -> 160 | L65: =E65/D65 -> 0.34751773 | M65: =B65/E65 -> 2.4344291 | O65: =(B65/D65)*1000 -> 846.00728 | P65: =G65/B65 -> 26.917587 | R65: =F65/E65 -> 0.0044125758 | T65: =G65/F65 -> 14850.5 | U65: =B65/F65 -> 551.7025 | V65: =B65/H65 -> 9.9855656
A66: 直通车 | B66: =SUM(直通车!B645:B675) -> 64544.95 | D66: =SUM(直通车!C645:C675) -> 163594 | E66: =SUM(直通车!D645:D675) -> 15532 | F66: =SUM(直通车!E645:E675) -> 5 | G66: =SUM(直通车!F645:F675) -> 54251 | H66: =SUM(直通车!G645:G675) -> 749 | I66: =SUM(直通车!H645:H675) -> 148 | J66: =SUM(直通车!I645:I675) -> 124 | K66: =I66+J66 -> 272 | L66: =E66/D66 -> 0.094942357 | M66: =B66/E66 -> 4.155611 | O66: =(B66/D66)*1000 -> 394.5435 | P66: =G66/B66 -> 0.84051502 | R66: =F66/E66 -> 0.00032191604 | T66: =G66/F66 -> 10850.2 | U66: =B66/F66 -> 12908.99 | V66: =B66/H66 -> 86.174833
A67: 引力魔方 | B67: =SUM(引力魔方!B544:B574) -> 37588.65 | D67: =SUM(引力魔方!C544:C574) -> 31095835 | E67: =SUM(引力魔方!D544:D574) -> 188677 | F67: =SUM(引力魔方!E544:E574) -> 0 | G67: =SUM(引力魔方!F544:F574) -> 0 | H67: =SUM(引力魔方!G544:G574) -> 280 | I67: =SUM(引力魔方!H544:H574) -> 169 | J67: =SUM(引力魔方!I544:I574) -> 43 | K67: =I67+J67 -> 212 | L67: =E67/D67 -> 0.0060675972 | M67: =B67/E67 -> 0.19922222 | O67: =(B67/D67)*1000 -> 1.2088001 | P67: =G67/B67 -> 0 | R67: =F67/E67 -> 0 | T67: =G67/F67 -> #DIV/0! | U67: =B67/F67 -> #DIV/0! | V67: =B67/H67 -> 134.24518
A68: 万相台 | B68: =SUM(万相台!B133:B163) -> 12333.92 | D68: =SUM(万相台!C133:C163) -> 843593 | E68: =SUM(万相台!D133:D163) -> 11679 | F68: =SUM(万相台!E133:E163) -> 11 | G68: =SUM(万相台!F133:F163) -> 155509 | H68: =SUM(万相台!G133:G163) -> 187 | I68: =SUM(万相台!H133:H163) -> 40 | K68: =I68+J68 -> 40 | L68: =E68/D68 -> 0.013844354 | M68: =B68/E68 -> 1.0560767 | O68: =(B68/D68)*1000 -> 14.6207 | P68: =(B68/D68)*1000 -> 14.6207 | R68: =F68/E68 -> 0.00094186146 | T68: =G68/F68 -> 14137.182 | U68: =B68/F68 -> 1121.2655 | V68: =B68/H68 -> 65.956791
A69: 总计 | B69: =SUM(B65:B68) -> 118881.14 | D69: =SUM(D65:D68) -> 32108239 | E69: =SUM(E65:E68) -> 217701 | F69: =SUM(F65:F68) -> 24 | G69: =SUM(G65:G68) -> 328564 | H69: =SUM(H65:H68) -> 1658 | I69: =SUM(I65:I68) -> 400 | J69: =SUM(J65:J68) -> 284 | K69: =I69+J69 -> 684 | L69: =E69/D69 -> 0.0067802224 | M69: =B69/E69 -> 0.54607531 | O69: =(B69/D69)*1000 -> 3.702512 | P69: =G69/B69 -> 2.7638026 | R69: =F69/E69 -> 0.00011024295 | T69: =G69/F69 -> 13690.167 | U69: =B69/F69 -> 4953.3808 | V69: =B69/H69 -> 71.701532
A71: 2月 | B71: Cost 花费 | D71: IMP 展示 | E71: Click 点击 | F71: Order 订单 | G71: Sales 销量 | H71: ShoppingCart 加入购物车 | I71: Bookmark-Product 宝贝收藏 | J71: Bookmark-Store 店铺收藏 | K71: 总收藏数 | L71: CTR 点击率 | M71: CPC 点击成本 | O71: CPM 千次展现成本 | P71: ROI 投资回报率 | R71: CVR 点击转化率 | T71: ASP 订单均价 | U71: Cporder 订单成本 | V71: CPshopping cart 加购成本
A72: 明星店铺 | B72: =SUM(明星店铺!B676:B704) -> 5341.79 | D72: =SUM(明星店铺!C676:C704) -> 7780 | E72: =SUM(明星店铺!D676:D704) -> 3160 | F72: =SUM(明星店铺!E676:E704) -> 22 | G72: =SUM(明星店铺!F676:F704) -> 336056 | H72: =SUM(明星店铺!G676:G704) -> 812 | I72: =SUM(明星店铺!H676:H704) -> 56 | J72: =SUM(明星店铺!I676:I704) -> 252 | K72: =I72+J72 -> 308 | L72: =E72/D72 -> 0.40616967 | M72: =B72/E72 -> 1.6904399 | O72: =(B72/D72)*1000 -> 686.6054 | P72: =G72/B72 -> 62.910747 | R72: =F72/E72 -> 0.0069620253 | T72: =G72/F72 -> 15275.273 | U72: =B72/F72 -> 242.80864 | V72: =B72/H72 -> 6.5785591
A73: 直通车 | B73: =SUM(直通车!B676:B704) -> 41071.2 | D73: =SUM(直通车!C676:C704) -> 120151 | E73: =SUM(直通车!D676:D704) -> 9048 | F73: =SUM(直通车!E676:E704) -> 9 | G73: =SUM(直通车!F676:F704) -> 102983 | H73: =SUM(直通车!G676:G704) -> 590 | I73: =SUM(直通车!H676:H704) -> 79 | J73: =SUM(直通车!I676:I704) -> 115 | K73: =I73+J73 -> 194 | L73: =E73/D73 -> 0.075305241 | M73: =B73/E73 -> 4.5392573 | O73: =(B73/D73)*1000 -> 341.82986 | P73: =G73/B73 -> 2.5074261 | R73: =F73/E73 -> 0.00099469496 | T73: =G73/F73 -> 11442.556 | U73: =B73/F73 -> 4563.4667 | V73: =B73/H73 -> 69.612203
A74: 引力魔方 | B74: =SUM(引力魔方!B575:B603) -> 14419.61 | D74: =SUM(引力魔方!C575:C603) -> 49785339 | E74: =SUM(引力魔方!D575:D603) -> 147329 | F74: =SUM(引力魔方!E575:E603) -> 0 | G74: =SUM(引力魔方!F575:F603) -> 0 | H74: =SUM(引力魔方!G575:G603) -> 85 | I74: =SUM(引力魔方!H575:H603) -> 82 | J74: =SUM(引力魔方!I575:I603) -> 36 | K74: =I74+J74 -> 118 | L74: =E74/D74 -> 0.0029592849 | M74: =B74/E74 -> 0.097873535 | O74: =(B74/D74)*1000 -> 0.28963567 | P74: =G74/B74 -> 0 | R74: =F74/E74 -> 0 | T74: =G74/F74 -> #DIV/0! | U74: =B74/F74 -> #DIV/0! | V74: =B74/H74 -> 169.64247
A75: 万相台 | B75: =SUM(万相台!B164:B192) -> 5781.09 | D75: =SUM(万相台!C164:C192) -> 827507 | E75: =SUM(万相台!D164:D192) -> 16623 | F75: =SUM(万相台!E164:E192) -> 1 | G75: =SUM(万相台!F164:F192) -> 15880 | H75: =SUM(万相台!G164:G192) -> 123 | I75: =SUM(万相台!H164:H192) -> 67 | K75: =I75+J75 -> 67 | L75: =E75/D75 -> 0.020088048 | M75: =B75/E75 -> 0.34777657 | O75: =(B75/D75)*1000 -> 6.9861524 | P75: =(B75/D75)*1000 -> 6.9861524 | R75: =F75/E75 -> 6.0157613e-05 | T75: =G75/F75 -> 15880 | U75: =B75/F75 -> 5781.09 | V75: =B75/H75 -> 47.000732
A76: 总计 | B76: =SUM(B72:B75) -> 66613.69 | D76: =SUM(D72:D75) -> 50740777 | E76: =SUM(E72:E75) -> 176160 | F76: =SUM(F72:F75) -> 32 | G76: =SUM(G72:G75) -> 454919 | H76: =SUM(H72:H75) -> 1610 | I76: =SUM(I72:I75) -> 284 | J76: =SUM(J72:J75) -> 403 | K76: =I76+J76 -> 687 | L76: =E76/D76 -> 0.0034717639 | M76: =B76/E76 -> 0.37814311 | O76: =(B76/D76)*1000 -> 1.3128236 | P76: =G76/B76 -> 6.8292118 | R76: =F76/E76 -> 0.00018165304 | T76: =G76/F76 -> 14216.219 | U76: =B76/F76 -> 2081.6778 | V76: =B76/H76 -> 41.374963
A79: 3月 | B79: Cost 花费 | D79: IMP 展示 | E79: Click 点击 | F79: Order 订单 | G79: Sales 销量 | H79: ShoppingCart 加入购物车 | I79: Bookmark-Product 宝贝收藏 | J79: Bookmark-Store 店铺收藏 | K79: 总收藏数 | L79: CTR 点击率 | M79: CPC 点击成本 | O79: CPM 千次展现成本 | P79: ROI 投资回报率 | R79: CVR 点击转化率 | T79: ASP 订单均价 | U79: Cporder 订单成本 | V79: CPshopping cart 加购成本 | W79: 收藏加购数 | X79: 收藏加购 成本 | Y79: 收藏加购率 | AA79: 花费环比 | AB79: 点击占比 | AC79: 加购环比 | AD79: 成交环比 | AE79: 加购成本 环比 | AF79: 收藏加购 成本环比
A80: 明星店铺 | B80: =SUM(明星店铺!B705:B735) -> 7518.61 | D80: =SUM(明星店铺!C705:C735) -> 9372 | E80: =SUM(明星店铺!D705:D735) -> 3804 | F80: =SUM(明星店铺!E705:E735) -> 60 | G80: =SUM(明星店铺!F705:F735) -> 909870 | H80: =SUM(明星店铺!G705:G735) -> 1034 | I80: =SUM(明星店铺!H705:H735) -> 74 | J80: =SUM(明星店铺!I705:I735) -> 234 | K80: =I80+J80 -> 308 | L80: =E80/D80 -> 0.40588988 | M80: =B80/E80 -> 1.9765011 | O80: =(B80/D80)*1000 -> 802.24178 | P80: =G80/B80 -> 121.01572 | R80: =F80/E80 -> 0.015772871 | T80: =G80/F80 -> 15164.5 | U80: =B80/F80 -> 125.31017 | V80: =B80/H80 -> 7.271383 | W80: =H80+K80 -> 1342 | X80: =B80/W80 -> 5.602541 | Y80: =W80/E80 -> 0.35278654 | AB80: =E80/$E$84 -> 0.0068744048
A81: 直通车 | B81: =SUM(直通车!B705:B735) -> 79734.93 | D81: =SUM(直通车!C705:C735) -> 305903 | E81: =SUM(直通车!D705:D735) -> 16284 | F81: =SUM(直通车!E705:E735) -> 57 | G81: =SUM(直通车!F705:F735) -> 945831 | H81: =SUM(直通车!G705:G735) -> 1117 | I81: =SUM(直通车!H705:H735) -> 161 | J81: =SUM(直通车!I705:I735) -> 188 | K81: =I81+J81 -> 349 | L81: =E81/D81 -> 0.053232561 | M81: =B81/E81 -> 4.8965199 | O81: =(B81/D81)*1000 -> 260.65429 | P81: =G81/B81 -> 11.862191 | R81: =F81/E81 -> 0.0035003685 | T81: =G81/F81 -> 16593.526 | U81: =B81/F81 -> 1398.8584 | V81: =B81/H81 -> 71.383107 | W81: =H81+K81 -> 1466 | X81: =B81/W81 -> 54.389447 | Y81: =W81/E81 -> 0.09002702 | AB81: =E81/$E$84 -> 0.029427657
A82: 引力魔方 | B82: =SUM(引力魔方!B604:B634) -> 46814.25 | D82: =SUM(引力魔方!C604:C634) -> 66709402 | E82: =SUM(引力魔方!D604:D634) -> 335835 | F82: =SUM(引力魔方!E604:E634) -> 4 | G82: =SUM(引力魔方!F604:F634) -> 73400 | H82: =SUM(引力魔方!G604:G634) -> 250 | I82: =SUM(引力魔方!H604:H634) -> 320 | J82: =SUM(引力魔方!I604:I634) -> 52 | K82: =I82+J82 -> 372 | L82: =E82/D82 -> 0.0050342979 | M82: =B82/E82 -> 0.13939658 | O82: =(B82/D82)*1000 -> 0.7017639 | P82: =G82/B82 -> 1.5678987 | R82: =F82/E82 -> 1.1910611e-05 | T82: =G82/F82 -> 18350 | U82: =B82/F82 -> 11703.562 | V82: =B82/H82 -> 187.257 | W82: =H82+K82 -> 622 | X82: =B82/W82 -> 75.264068 | Y82: =W82/E82 -> 0.0018521 | AB82: =E82/$E$84 -> 0.60690476
A83: 万相台 | B83: =SUM(万相台!B193:B223) -> 73707.19 | D83: =SUM(万相台!C193:C223) -> 19398232 | E83: =SUM(万相台!D193:D223) -> 197434 | F83: =SUM(万相台!E193:E223) -> 42 | G83: =SUM(万相台!F193:F223) -> 703035 | H83: =SUM(万相台!G193:G223) -> 1507 | I83: =SUM(万相台!H193:H223) -> 3150 | J83: =SUM(万相台!J193:J223) -> 0.42727885 | K83: =I83+J83 -> 3150.4273 | L83: =E83/D83 -> 0.010177938 | M83: =B83/E83 -> 0.37332572 | O83: =(B83/D83)*1000 -> 3.799686 | P83: =G83/B83 -> 9.5382147 | R83: =F83/E83 -> 0.00021272932 | T83: =G83/F83 -> 16738.929 | U83: =B83/F83 -> 1754.9331 | V83: =B83/H83 -> 48.909881 | W83: =H83+K83 -> 4657.4273 | X83: =B83/W83 -> 15.825731 | Y83: =W83/E83 -> 0.023589793 | AB83: =E83/$E$84 -> 0.35679317
A84: 总计 | B84: =SUM(B80:B83) -> 207774.98 | D84: =SUM(D80:D83) -> 86422909 | E84: =SUM(E80:E83) -> 553357 | F84: =SUM(F80:F83) -> 163 | G84: =SUM(G80:G83) -> 2632136 | H84: =SUM(H80:H83) -> 3908 | I84: =SUM(I80:I83) -> 3705 | J84: =SUM(J80:J83) -> 474.42728 | K84: =I84+J84 -> 4179.4273 | L84: =E84/D84 -> 0.0064028972 | M84: =B84/E84 -> 0.37548089 | O84: =(B84/D84)*1000 -> 2.4041655 | P84: =G84/B84 -> 12.668205 | R84: =F84/E84 -> 0.00029456571 | T84: =G84/F84 -> 16148.074 | U84: =B84/F84 -> 1274.6931 | V84: =B84/H84 -> 53.166576 | W84: =H84+K84 -> 8087.4273 | X84: =B84/W84 -> 25.69111 | Y84: =W84/E84 -> 0.014615207
A87: 4月 | B87: Cost 花费 | D87: IMP 展示 | E87: Click 点击 | F87: Order 订单 | G87: Sales 销量 | H87: ShoppingCart 加入购物车 | I87: Bookmark-Product 宝贝收藏 | J87: Bookmark-Store 店铺收藏 | K87: 总收藏数 | L87: CTR 点击率 | M87: CPC 点击成本 | O87: CPM 千次展现成本 | P87: ROI 投资回报率 | R87: CVR 点击转化率 | T87: ASP 订单均价 | U87: Cporder 订单成本 | V87: CPshopping cart 加购成本 | W87: 收藏加购数 | X87: 收藏加购 成本 | Y87: 收藏加购率 | AA87: 花费环比 | AB87: 点击占比 | AC87: 加购环比 | AD87: 成交环比 | AE87: 加购成本 环比 | AF87: 收藏加购 成本环比
A88: 明星店铺 | B88: =SUM(明星店铺!B736:B765) -> 6488.18 | D88: =SUM(明星店铺!C736:C765) -> 7851 | E88: =SUM(明星店铺!D736:D765) -> 2955 | F88: =SUM(明星店铺!E736:E765) -> 18 | G88: =SUM(明星店铺!F736:F765) -> 276039 | H88: =SUM(明星店铺!G736:G765) -> 783 | I88: =SUM(明星店铺!H736:H756) -> 44 | J88: =SUM(明星店铺!I736:I765) -> 145 | K88: =I88+J88 -> 189 | L88: =E88/D88 -> 0.37638517 | M88: =B88/E88 -> 2.1956616 | O88: =(B88/D88)*1000 -> 826.41447 | P88: =G88/B88 -> 42.544905 | R88: =F88/E88 -> 0.0060913706 | T88: =IF(F88=0,"0",G88/F88) -> 15335.5 | U88: =IF(F88=0,"0",B88/F88) -> 360.45444 | V88: =B88/H88 -> 8.2863091 | W88: =H88+K88 -> 972 | X88: =B88/W88 -> 6.6750823 | Y88: =W88/E88 -> 0.32893401 | AA88: =(B88-B80)/B80 -> -0.1370506 | AB88: =E88/$E$92 -> 0.0073047554 | AC88: =(H88-H80)/H80 -> -0.24274662 | AE88: =(V88-V80)/V80 -> 0.13957814 | AF88: =(X88-X80)/X80 -> 0.19143837
A89: 直通车 | B89: =SUM(直通车!B736:B765) -> 55187.14 | D89: =SUM(直通车!C736:C765) -> 217527 | E89: =SUM(直通车!D736:D765) -> 13706 | F89: =SUM(直通车!E736:E765) -> 9 | G89: =SUM(直通车!F736:F765) -> 196570 | H89: =SUM(直通车!G736:G765) -> 945 | I89: =SUM(直通车!H736:H765) -> 95 | J89: =SUM(直通车!I736:I765) -> 115 | K89: =I89+J89 -> 210 | L89: =E89/D89 -> 0.06300827 | M89: =B89/E89 -> 4.026495 | O89: =(B89/D89)*1000 -> 253.70248 | P89: =G89/B89 -> 3.5618805 | R89: =F89/E89 -> 0.00065664672 | T89: =IF(F89=0,"0",G89/F89) -> 21841.111 | U89: =IF(F89=0,"0",B89/F89) -> 6131.9044 | V89: =B89/H89 -> 58.39909 | W89: =H89+K89 -> 1155 | X89: =B89/W89 -> 47.781074 | Y89: =W89/E89 -> 0.084269663 | AA89: =(B89-B81)/B81 -> -0.30786746 | AB89: =E89/$E$92 -> 0.033881211 | AC89: =(H89-H81)/H81 -> -0.15398389 | AE89: =(V89-V81)/V81 -> -0.18189201 | AF89: =(X89-X81)/X81 -> -0.12150103
A90: 引力魔方 | B90: =SUM(引力魔方!B635:B664) -> 37490.77 | D90: =SUM(引力魔方!C635:C664) -> 43486150 | E90: =SUM(引力魔方!D635:D664) -> 167971 | F90: =SUM(引力魔方!E635:E664) -> 2 | G90: =SUM(引力魔方!F635:F664) -> 20393.68 | H90: =SUM(引力魔方!G635:G664) -> 247 | I90: =SUM(引力魔方!H635:H664) -> 899 | J90: =SUM(引力魔方!I635:I664) -> 54 | K90: =I90+J90 -> 953 | L90: =E90/D90 -> 0.0038626321 | M90: =B90/E90 -> 0.22319787 | O90: =(B90/D90)*1000 -> 0.86213128 | P90: =G90/B90 -> 0.54396535 | R90: =F90/E90 -> 1.1906817e-05 | T90: =IF(F90=0,"0",G90/F90) -> 10196.84 | U90: =IF(F90=0,"0",B90/F90) -> 18745.385 | V90: =B90/H90 -> 151.78449 | W90: =H90+K90 -> 1200 | X90: =B90/W90 -> 31.242308 | Y90: =W90/E90 -> 0.0071440903 | AA90: =(B90-B82)/B82 -> -0.19915902 | AB90: =E90/$E$92 -> 0.41522405 | AC90: =(H90-H82)/H82 -> -0.012 | AE90: =(V90-V82)/V82 -> -0.1894322 | AF90: =(X90-X82)/X82 -> -0.58489742
A91: 万相台 | B91: =SUM(万相台!B224:B253) -> 61294.7 | D91: =SUM(万相台!C224:C253) -> 18951479 | E91: =SUM(万相台!D224:D253) -> 219899 | F91: =SUM(万相台!E224:E253) -> 31 | G91: =SUM(万相台!F224:F253) -> 464453.48 | H91: =SUM(万相台!G224:G253) -> 1037 | I91: =SUM(万相台!H224:H253) -> 3263 | J91: =SUM(万相台!I224:I253) -> 394 | K91: =I91+J91 -> 3657 | L91: =E91/D91 -> 0.011603263 | M91: =B91/E91 -> 0.27874024 | O91: =(B91/D91)*1000 -> 3.2342964 | P91: =G91/B91 -> 7.577384 | R91: =F91/E91 -> 0.00014097381 | T91: =IF(F91=0,"0",G91/F91) -> 14982.37 | U91: =IF(F91=0,"0",B91/F91) -> 1977.2484 | V91: =B91/H91 -> 59.107715 | W91: =H91+K91 -> 4694 | X91: =B91/W91 -> 13.058095 | Y91: =W91/E91 -> 0.021346163 | AA91: =(B91-B83)/B83 -> -0.1684027 | AB91: =E91/$E$92 -> 0.54358998 | AC91: =(H91-H83)/H83 -> -0.3118779 | AE91: =(V91-V83)/V83 -> 0.20850253 | AF91: =(X91-X83)/X83 -> -0.17488199
A92: 总计 | B92: =SUM(B88:B91) -> 160460.79 | D92: =SUM(D88:D91) -> 62663007 | E92: =SUM(E88:E91) -> 404531 | F92: =SUM(F88:F91) -> 60 | G92: =SUM(G88:G91) -> 957456.16 | H92: =SUM(H88:H91) -> 3012 | I92: =SUM(I88:I91) -> 4301 | J92: =SUM(J88:J91) -> 708 | K92: =I92+J92 -> 5009 | L92: =E92/D92 -> 0.0064556589 | M92: =B92/E92 -> 0.39665882 | O92: =(B92/D92)*1000 -> 2.5606941 | P92: =G92/B92 -> 5.9669167 | R92: =F92/E92 -> 0.00014831991 | T92: =G92/F92 -> 15957.603 | U92: =B92/F92 -> 2674.3465 | V92: =B92/H92 -> 53.273835 | W92: =H92+K92 -> 8021 | X92: =B92/W92 -> 20.005085 | Y92: =W92/E92 -> 0.019827899 | AA92: =(B92-B84)/B84 -> -0.22771842 | AC92: =(H92-H84)/H84 -> -0.22927329 | AE92: =(V92-V84)/V84 -> 0.0020174029 | AF92: =(X92-X84)/X84 -> -0.22132264
A93: 环比3月 | B93: =(B92-B84)/B84 -> -0.22771842 | D93: =(D92-D84)/D84 -> -0.27492597 | E93: =(E92-E84)/E84 -> -0.26895115 | F93: =(F92-F84)/F84 -> -0.63190184 | G93: =(G92-G84)/G84 -> -0.63624366 | H93: =(H92-H84)/H84 -> -0.22927329 | I93: =(I92-I84)/I84 -> 0.1608637 | J93: =(J92-J84)/J84 -> 0.49232566 | K93: =(K92-K84)/K84 -> 0.19848957 | ... M93: =(M92-M84)/M84 -> 0.056402151 | O93: =(O92-O84)/O84 -> 0.065107214 | P93: =(P92-P84)/P84 -> -0.52898483 | R93: =(R92-R84)/R84 -> -0.4964794 | T93: =(T92-T84)/T84 -> -0.011795274 | U93: =(U92-U84)/U84 -> 1.0980316 | V93: =(V92-V84)/V84 -> 0.0020174029
A95: 618前30天 | B95: Cost 花费 | D95: IMP 展示 | E95: Click 点击 | F95: Order 订单 | G95: Sales 销量 | H95: ShoppingCart 加入购物车 | I95: Bookmark-Product 宝贝收藏 | J95: Bookmark-Store 店铺收藏 | K95: 总收藏数 | L95: CTR 点击率 | M95: CPC 点击成本 | O95: CPM 千次展现成本 | P95: ROI 投资回报率 | R95: CVR 点击转化率 | T95: ASP 订单均价 | U95: Cporder 订单成本 | V95: CPshopping cart 加购成本 | W95: 收藏加购数 | X95: 收藏加购 成本 | Y95: 收藏加购率 | AA95: 花费环比 | AB95: 点击占比 | AC95: 加购环比 | AD95: 成交环比 | AE95: 加购成本 环比 | AF95: 收藏加购 成本环比
A96: 明星店铺 | B96: =SUM(明星店铺!B754:B784) -> 10192.19 | D96: =SUM(明星店铺!C754:C784) -> 12523 | E96: =SUM(明星店铺!D754:D784) -> 5987 | F96: =SUM(明星店铺!E754:E784) -> 63 | G96: =SUM(明星店铺!F754:F784) -> 716985.81 | H96: =SUM(明星店铺!G754:G784) -> 1518 | I96: =SUM(明星店铺!H754:H784) -> 206 | J96: =SUM(明星店铺!I754:I784) -> 387 | K96: =I96+J96 -> 593 | L96: =E96/D96 -> 0.47808033 | M96: =B96/E96 -> 1.7023868 | O96: =(B96/D96)*1000 -> 813.87767 | P96: =G96/B96 -> 70.34659 | R96: =F96/E96 -> 0.010522799 | T96: =IF(F96=0,"0",G96/F96) -> 11380.727 | U96: =IF(F96=0,"0",B96/F96) -> 161.78079 | V96: =B96/H96 -> 6.7142227 | W96: =H96+K96 -> 2111 | X96: =B96/W96 -> 4.8281336 | Y96: =W96/E96 -> 0.35259729
A97: 直通车 | B97: =SUM(直通车!B754:B784) -> 62554.14 | D97: =SUM(直通车!C754:C784) -> 214054 | E97: =SUM(直通车!D754:D784) -> 16047 | F97: =SUM(直通车!E754:E784) -> 34 | G97: =SUM(直通车!F754:F784) -> 471115 | H97: =SUM(直通车!G754:G784) -> 1238 | I97: =SUM(直通车!H754:H784) -> 152 | J97: =SUM(直通车!I754:I784) -> 167 | K97: =I97+J97 -> 319 | L97: =E97/D97 -> 0.074967064 | M97: =B97/E97 -> 3.8981828 | O97: =(B97/D97)*1000 -> 292.23532 | P97: =G97/B97 -> 7.5313161 | R97: =F97/E97 -> 0.0021187761 | T97: =IF(F97=0,"0",G97/F97) -> 13856.324 | U97: =IF(F97=0,"0",B97/F97) -> 1839.8276 | V97: =B97/H97 -> 50.528384 | W97: =H97+K97 -> 1557 | X97: =B97/W97 -> 40.176069 | Y97: =W97/E97 -> 0.097027482
A98: 引力魔方 | B98: =SUM(引力魔方!B653:B683) -> 39045.92 | D98: =SUM(引力魔方!C653:C683) -> 42299840 | E98: =SUM(引力魔方!D653:D683) -> 165191 | F98: =SUM(引力魔方!E653:E683) -> 11 | G98: =SUM(引力魔方!F653:F683) -> 115697 | H98: =SUM(引力魔方!G653:G683) -> 395 | I98: =SUM(引力魔方!H653:H683) -> 1299 | J98: =SUM(引力魔方!I653:I683) -> 63 | K98: =I98+J98 -> 1362 | L98: =E98/D98 -> 0.0039052394 | M98: =B98/E98 -> 0.23636833 | O98: =(B98/D98)*1000 -> 0.92307489 | P98: =G98/B98 -> 2.9631009 | R98: =F98/E98 -> 6.6589584e-05 | T98: =IF(F98=0,"0",G98/F98) -> 10517.909 | U98: =IF(F98=0,"0",B98/F98) -> 3549.6291 | V98: =B98/H98 -> 98.85043 | W98: =H98+K98 -> 1757 | X98: =B98/W98 -> 22.223062 | Y98: =W98/E98 -> 0.010636173
A99: 万相台 | B99: =SUM(万相台!B242:B272) -> 71615.16 | D99: =SUM(万相台!C242:C272) -> 27107290 | E99: =SUM(万相台!D242:D272) -> 279410 | F99: =SUM(万相台!E242:E272) -> 50 | G99: =SUM(万相台!F242:F272) -> 693722 | H99: =SUM(万相台!G242:G272) -> 1349 | I99: =SUM(万相台!H242:H272) -> 4672 | J99: =SUM(万相台!I242:I272) -> 417 | K99: =I99+J99 -> 5089 | L99: =E99/D99 -> 0.010307559 | M99: =B99/E99 -> 0.25630851 | O99: =(B99/D99)*1000 -> 2.6419151 | P99: =G99/B99 -> 9.6868037 | R99: =F99/E99 -> 0.0001789485 | T99: =IF(F99=0,"0",G99/F99) -> 13874.44 | U99: =IF(F99=0,"0",B99/F99) -> 1432.3032 | V99: =B99/H99 -> 53.087591 | W99: =H99+K99 -> 6438 | X99: =B99/W99 -> 11.123821 | Y99: =W99/E99 -> 0.023041409
A100: 总计 | B100: =SUM(B96:B99) -> 183407.41 | D100: =SUM(D96:D99) -> 69633707 | E100: =SUM(E96:E99) -> 466635 | F100: =SUM(F96:F99) -> 158 | G100: =SUM(G96:G99) -> 1997519.8 | H100: =SUM(H96:H99) -> 4500 | I100: =SUM(I96:I99) -> 6329 | J100: =SUM(J96:J99) -> 1034 | K100: =I100+J100 -> 7363 | L100: =E100/D100 -> 0.0067012805 | M100: =B100/E100 -> 0.39304255 | O100: =(B100/D100)*1000 -> 2.6338884 | P100: =G100/B100 -> 10.891162 | R100: =F100/E100 -> 0.0003385944 | T100: =G100/F100 -> 12642.53 | U100: =B100/F100 -> 1160.8064 | V100: =B100/H100 -> 40.757202 | W100: =H100+K100 -> 11863 | X100: =B100/W100 -> 15.460458 | Y100: =W100/E100 -> 0.025422439
A101: 环比4月 | B101: =(B100-B92)/B92 -> 0.14300453 | D101: =(D100-D92)/D92 -> 0.11124107 | E101: =(E100-E92)/E92 -> 0.15352099 | F101: =(F100-F92)/F92 -> 1.6333333 | G101: =(G100-G92)/G92 -> 1.0862781 | H101: =(H100-H92)/H92 -> 0.4940239 | I101: =(I100-I92)/I92 -> 0.47151825 | J101: =(J100-J92)/J92 -> 0.46045198 | K101: =(K100-K92)/K92 -> 0.46995408 | ... M101: =(M100-M92)/M92 -> -0.0091168346 | O101: =(O100-O92)/O92 -> 0.028583771 | P101: =(P100-P92)/P92 -> 0.82525794 | R101: =(R100-R92)/R92 -> 1.2828656 | T101: =(T100-T92)/T92 -> -0.2077425 | U101: =(U100-U92)/U92 -> -0.56594765 | V101: =(V100-V92)/V92 -> -0.23494897
A103: 618活动 （5月18-6月20） | B103: Cost 花费 | C103: 对比超品 | D103: IMP 展示 | E103: Click 点击 | F103: Order 订单 | G103: Sales 销量 | H103: ShoppingCart 加入购物车 | I103: Bookmark-Product 宝贝收藏 | J103: Bookmark-Store 店铺收藏 | K103: 总收藏数 | L103: CTR 点击率 | M103: CPC 点击成本 | N103: 对比超品 | O103: CPM 千次展现成本 | P103: ROI 投资回报率 | Q103: 对比超品 | R103: CVR 点击转化率 | S103: 对比超品 | T103: ASP 订单均价 | U103: Cporder 订单成本 | V103: CPshopping cart 加购成本 | W103: 收藏加购数 | X103: 收藏加购 成本 | Y103: 收藏加购率 | Z103: 对比超品 | AA103: 花费环比 | AB103: 点击环比 | AC103: 加购环比 | AD103: 成交环比 | AE103: 加购成本 环比 | AF103: 收藏加购 成本环比 | AG103: 点击占比
A104: 明星店铺 | B104: =SUM(明星店铺!B783:B826) -> 15908.92 | C104: =(B104-B80)/B80 -> 1.115939 | D104: =SUM(明星店铺!C783:C826) -> 14995 | E104: =SUM(明星店铺!D783:D826) -> 6865 | F104: =SUM(明星店铺!E783:E826) -> 146 | G104: =SUM(明星店铺!F783:F826) -> 1981587 | H104: =SUM(明星店铺!G783:G826) -> 1850 | I104: =SUM(明星店铺!H783:H826) -> 173 | J104: =SUM(明星店铺!I783:I826) -> 460 | K104: =I104+J104 -> 633 | L104: =E104/D104 -> 0.45781927 | M104: =B104/E104 -> 2.3173955 | N104: =(M104-M80)/M80 -> 0.17247369 | O104: =(B104/D104)*1000 -> 1060.9483 | P104: =G104/B104 -> 124.55824 | Q104: =(P104-P80)/P80 -> 0.029273185 | R104: =F104/E104 -> 0.021267298 | S104: =(R104-R80)/R80 -> 0.34834669 | T104: =IF(F104=0,"0",G104/F104) -> 13572.514 | U104: =IF(F104=0,"0",B104/F104) -> 108.96521 | V104: =B104/H104 -> 8.5994162 | W104: =H104+I104 -> 2023 | X104: =B104/W104 -> 7.8640237 | Y104: =W104/E104 -> 0.29468318 | Z104: =(Y104-Y80)/Y80 -> -0.16469836 | AA104: =(B104-B80)/B80 -> 1.115939 | AB104: =(E104-E80)/E80 -> 0.80467928 | AC104: =(H104-H80)/H80 -> 0.78916828 | AD104: =(G104-G80)/G80 -> 1.1778793 | AE104: =(V104-V80)/V80 -> 0.18263833 | AF104: =(X104-X80)/X80 -> 0.40365305 | AG104: =E104/$E$108 -> 0.020148095
A105: 直通车 | B105: =SUM(直通车!B783:B826) -> 119719.46 | C105: =(B105-B81)/B81 -> 0.50146818 | D105: =SUM(直通车!C783:C826) -> 489505 | E105: =SUM(直通车!D783:D826) -> 26986 | F105: =SUM(直通车!E783:E826) -> 93 | G105: =SUM(直通车!F783:F826) -> 1191915 | H105: =SUM(直通车!G783:G826) -> 1961 | I105: =SUM(直通车!H783:H826) -> 233 | J105: =SUM(直通车!I783:I826) -> 285 | K105: =I105+J105 -> 518 | L105: =E105/D105 -> 0.055129161 | M105: =B105/E105 -> 4.4363544 | N105: =(M105-M81)/M81 -> -0.09397807 | O105: =(B105/D105)*1000 -> 244.5725 | P105: =G105/B105 -> 9.9559002 | Q105: =(P105-P81)/P81 -> -0.16070312 | R105: =F105/E105 -> 0.0034462314 | S105: =(R105-R81)/R81 -> -0.015466109 | T105: =IF(F105=0,"0",G105/F105) -> 12816.29 | U105: =IF(F105=0,"0",B105/F105) -> 1287.306 | V105: =B105/H105 -> 61.050209 | W105: =H105+I105 -> 2194 | X105: =B105/W105 -> 54.566755 | Y105: =W105/E105 -> 0.081301416 | Z105: =(Y105-Y81)/Y81 -> -0.096922066 | AA105: =(B105-B81)/B81 -> 0.50146818 | AB105: =(E105-E81)/E81 -> 0.65720953 | AC105: =(H105-H81)/H81 -> 0.75559534 | AD105: =(G105-G81)/G81 -> 0.26017756 | AE105: =(V105-V81)/V81 -> -0.1447527 | AF105: =(X105-X81)/X81 -> 0.0032599579 | AG105: =E105/$E$108 -> 0.079201237
A106: 引力魔方 | B106: =SUM(引力魔方!B682:B725) -> 38562.04 | C106: =(B106-B82)/B82 -> -0.1762756 | D106: =SUM(引力魔方!C682:C725) -> 36636527 | E106: =SUM(引力魔方!D682:D725) -> 122358 | F106: =SUM(引力魔方!E682:E725) -> 5 | G106: =SUM(引力魔方!F682:F725) -> 58960 | H106: =SUM(引力魔方!G682:G725) -> 399 | I106: =SUM(引力魔方!H682:H725) -> 3290 | J106: =SUM(引力魔方!I682:I725) -> 54 | K106: =I106+J106 -> 3344 | L106: =E106/D106 -> 0.0033397816 | M106: =B106/E106 -> 0.31515749 | N106: =(M106-M82)/M82 -> 1.2608696 | O106: =(B106/D106)*1000 -> 1.0525572 | P106: =G106/B106 -> 1.5289648 | Q106: =(P106-P82)/P82 -> -0.024831904 | R106: =F106/E106 -> 4.0863695e-05 | S106: =(R106-R82)/R82 -> 2.4308648 | T106: =IF(F106=0,"0",G106/F106) -> 11792 | U106: =IF(F106=0,"0",B106/F106) -> 7712.408 | V106: =B106/H106 -> 96.646717 | W106: =H106+I106 -> 3689 | X106: =B106/W106 -> 10.45325 | Y106: =W106/E106 -> 0.030149234 | Z106: =(Y106-Y82)/Y82 -> 15.278405 | AA106: =(B106-B82)/B82 -> -0.1762756 | AB106: =(E106-E82)/E82 -> -0.63566037 | AC106: =(H106-H82)/H82 -> 0.596 | AD106: =(G106-G82)/G82 -> -0.19673025 | AE106: =(V106-V82)/V82 -> -0.48388195 | AF106: =(X106-X82)/X82 -> -0.86111234 | AG106: =E106/$E$108 -> 0.35910861
A107: 万相台 | B107: =SUM(万相台!B271:B314) -> 151993.84 | C107: =(B107-B83)/B83 -> 1.0621304 | D107: =SUM(万相台!C271:C314) -> 36245970 | E107: =SUM(万相台!D271:D314) -> 184518 | F107: =SUM(万相台!E271:E314) -> 154 | G107: =SUM(万相台!F271:F314) -> 1851965 | H107: =SUM(万相台!G271:G314) -> 2256 | I107: =SUM(万相台!H271:H314) -> 9525 | J107: =SUM(万相台!I271:I314) -> 594 | K107: =I107+J107 -> 10119 | L107: =E107/D107 -> 0.0050907177 | M107: =B107/E107 -> 0.82373449 | N107: =(M107-M83)/M83 -> 1.2064767 | O107: =(B107/D107)*1000 -> 4.1933997 | P107: =G107/B107 -> 12.184474 | Q107: =(P107-P83)/P83 -> 0.2774376 | R107: =F107/E107 -> 0.00083460692 | S107: =(R107-R83)/R83 -> 2.9233282 | T107: =IF(F107=0,"0",G107/F107) -> 12025.747 | U107: =IF(F107=0,"0",B107/F107) -> 986.97299 | V107: =B107/H107 -> 67.373156 | W107: =H107+I107 -> 11781 | X107: =B107/W107 -> 12.901608 | Y107: =W107/E107 -> 0.06384743 | Z107: =(Y107-Y83)/Y83 -> 1.7065701 | AA107: =(B107-B83)/B83 -> 1.0621304 | AB107: =(E107-E83)/E83 -> -0.06541933 | AC107: =(H107-H83)/H83 -> 0.49701393 | AD107: =(G107-G83)/G83 -> 1.634243 | AE107: =(V107-V83)/V83 -> 0.37749582 | AF107: =(X107-X83)/X83 -> -0.18477018 | AG107: =E107/$E$108 -> 0.54154206
A108: 总计 | B108: =SUM(B104:B107) -> 326184.26 | D108: =SUM(D104:D107) -> 73386997 | E108: =SUM(E104:E107) -> 340727 | F108: =SUM(F104:F107) -> 398 | G108: =SUM(G104:G107) -> 5084427 | H108: =SUM(H104:H107) -> 6466 | I108: =SUM(I104:I107) -> 13221 | J108: =SUM(J104:J107) -> 1393 | K108: =SUM(K104:K107) -> 14614 | L108: =E108/D108 -> 0.0046428797 | M108: =B108/E108 -> 0.9573185 | O108: =(B108/D108)*1000 -> 4.4447146 | P108: =G108/B108 -> 15.587592 | R108: =F108/E108 -> 0.0011680906 | T108: =G108/F108 -> 12774.942 | U108: =B108/F108 -> 819.55844 | V108: =B108/H108 -> 50.446066 | W108: =H108+K108 -> 21080 | X108: =B108/W108 -> 15.473637 | Y108: =W108/E108 -> 0.061867712 | AA108: =(B108-B84)/B84 -> 0.56989191 | AB108: =(E108-E84)/E84 -> -0.38425465 | AC108: =(H108-H84)/H84 -> 0.65455476 | AD108: =(G108-G84)/G84 -> 0.93167336 | AE108: =(V108-V84)/V84 -> -0.051169567 | AF108: =(X108-X84)/X84 -> -0.39770462 | AG108: =E108/$E$108 -> 1
A109: 对比超品日 | B109: =(B108-B84)/B84 -> 0.56989191 | D109: =(D108-D84)/D84 -> -0.15083862 | E109: =(E108-E84)/E84 -> -0.38425465 | F109: =(F108-F84)/F84 -> 1.4417178 | G109: =(G108-G84)/G84 -> 0.93167336 | H109: =(H108-H84)/H84 -> 0.65455476 | I109: =(I108-I84)/I84 -> 2.5684211 | J109: =(J108-J84)/J84 -> 1.9361718 | K109: =(K108-K84)/K84 -> 2.4966513 | ... M109: =(M108-M84)/M84 -> 1.5495798 | O109: =(O108-O84)/O84 -> 0.84875565 | P109: =(P108-P84)/P84 -> 0.23044991 | R109: =(R108-R84)/R84 -> 2.9654669 | T109: =(T108-T84)/T84 -> -0.20888754 | U109: =(U108-U84)/U84 -> -0.35705432 | V109: =(V108-V84)/V84 -> -0.051169567 | W109: =(W108-W84)/W84 -> 1.6065149 | X109: =(X108-X84)/X84 -> -0.39770462 | Y109: =(Y108-Y84)/Y84 -> 3.2331053
D111: =D104/D80-1 -> 0.59997866

Sheet 对比前30天
A2: 1月 | B2: Cost 花费 | C2: IMP 展示 | D2: Click 点击 | E2: Order 订单 | F2: Sales 销量 | G2: ShoppingCart 加入购物车 | H2: Bookmark-Product 宝贝收藏 | I2: Bookmark-Store 店铺收藏 | K2: CTR 点击率 | L2: CPC 点击成本 | M2: CPM 千次展现成本 | N2: ROI 投资回报率 | O2: CVR 点击转化率 | P2: ASP 订单均价 | Q2: Cporder 订单成本 | R2: CPshopping cart 加购成本
A3: 钻展 | B3: 6.05 | C3: 1427 | D3: 1 | E3: - | F3: - | G3: - | H3: - | I3: - | K3: - | L3: - | M3: - | N3: - | O3: - | P3: - | Q3: - | R3: -
A4: 明星店铺 | B4: 2731.45 | C4: 7691 | D4: 349 | E4: 0 | F4: 0 | G4: 2 | H4: 2 | I4: 11 | K4: =D4/C4 -> 0.045377714 | L4: =B4/D4 -> 7.8265043 | M4: =(B4/C4)*1000 -> 355.14888 | N4: =F4/B4 -> 0 | O4: =E4/D4 -> 0 | P4: =F4/E4 -> #DIV/0! | Q4: =B4/E4 -> #DIV/0! | R4: =B4/G4 -> 1365.725
A5: 直通车 | B5: 1952.96 | C5: 39544 | D5: 1253 | E5: 2 | F5: 198 | G5: 46 | H5: 4 | I5: 8 | K5: =D5/C5 -> 0.031686223 | L5: =B5/D5 -> 1.5586273 | M5: =(B5/C5)*1000 -> 49.387012 | N5: =F5/B5 -> 0.10138456 | O5: =E5/D5 -> 0.0015961692 | P5: =F5/E5 -> 99 | Q5: =B5/E5 -> 976.48 | R5: =B5/G5 -> 42.455652
A6: 引力魔方 | B6: - | C6: - | D6: - | E6: - | F6: - | G6: - | H6: - | I6: - | K6: - | L6: - | M6: - | N6: - | O6: - | P6: - | Q6: - | R6: -
A7: 总计 | B7: =SUM(B3:B6) -> 4690.46 | C7: =SUM(C3:C6) -> 48662 | D7: =SUM(D3:D6) -> 1603 | E7: =SUM(E3:E6) -> 2 | F7: =SUM(F3:F6) -> 198 | G7: =SUM(G3:G6) -> 48 | H7: =SUM(H3:H6) -> 6 | I7: =SUM(I3:I6) -> 19 | K7: =D7/C7 -> 0.032941515 | L7: =B7/D7 -> 2.9260512 | M7: =(B7/C7)*1000 -> 96.388558 | N7: =F7/B7 -> 0.042213344 | O7: =E7/D7 -> 0.0012476606 | P7: =F7/E7 -> 99 | Q7: =B7/E7 -> 2345.23 | R7: =B7/G7 -> 97.717917
A10: 2月 | B10: Cost 花费 | C10: IMP 展示 | D10: Click 点击 | E10: Order 订单 | F10: Sales 销量 | G10: ShoppingCart 加入购物车 | H10: Bookmark-Product 宝贝收藏 | I10: Bookmark-Store 店铺收藏 | K10: CTR 点击率 | L10: CPC 点击成本 | M10: CPM 千次展现成本 | N10: ROI 投资回报率 | O10: CVR 点击转化率 | P10: ASP 订单均价 | Q10: Cporder 订单成本 | R10: CPshopping cart 加购成本
A11: 明星店铺 | B11: 22646 | C11: 24719 | D11: 1047 | E11: 1 | F11: 99 | G11: 13 | H11: 3 | I11: 20 | K11: =D11/C11 -> 0.042356082 | L11: =B11/D11 -> 21.629417 | M11: =(B11/C11)*1000 -> 916.13738 | N11: =F11/B11 -> 0.004371633 | O11: =E11/D11 -> 0.00095510984 | P11: =F11/E11 -> 99 | Q11: =B11/E11 -> 22646 | R11: =B11/G11 -> 1742
A12: 直通车 | B12: 5688.53 | C12: 84202 | D12: 2773 | E12: 2 | F12: 198 | G12: 51 | H12: 14 | I12: 14 | K12: =D12/C12 -> 0.032932709 | L12: =B12/D12 -> 2.0513992 | M12: =(B12/C12)*1000 -> 67.558134 | N12: =F12/B12 -> 0.034806883 | O12: =E12/D12 -> 0.00072124053 | P12: =F12/E12 -> 99 | Q12: =B12/E12 -> 2844.265 | R12: =B12/G12 -> 111.5398
A13: 引力魔方 | B13: 1337.93 | C13: 197627 | D13: 1649 | E13: 0 | F13: 0 | G13: 8 | H13: 12 | I13: 2 | K13: =D13/C13 -> 0.0083440016 | L13: =B13/D13 -> 0.8113584 | M13: =(B13/C13)*1000 -> 6.7699758 | N13: =F13/B13 -> 0 | O13: =E13/D13 -> 0 | P13: =F13/E13 -> #DIV/0! | Q13: =B13/E13 -> #DIV/0! | R13: =B13/G13 -> 167.24125
A14: 总计 | B14: =SUM(B11:B13) -> 29672.46 | C14: =SUM(C11:C13) -> 306548 | D14: =SUM(D11:D13) -> 5469 | E14: =SUM(E11:E13) -> 3 | F14: =SUM(F11:F13) -> 297 | G14: =SUM(G11:G13) -> 72 | H14: =SUM(H11:H13) -> 29 | I14: =SUM(I11:I13) -> 36 | K14: =D14/C14 -> 0.017840599 | L14: =B14/D14 -> 5.4255732 | M14: =(B14/C14)*1000 -> 96.795477 | N14: =F14/B14 -> 0.010009281 | O14: =E14/D14 -> 0.00054854635 | P14: =F14/E14 -> 99 | Q14: =B14/E14 -> 9890.82 | R14: =B14/G14 -> 412.1175
A17: 3月 | B17: Cost 花费 | C17: IMP 展示 | D17: Click 点击 | E17: Order 订单 | F17: Sales 销量 | G17: ShoppingCart 加入购物车 | H17: Bookmark-Product 宝贝收藏 | I17: Bookmark-Store 店铺收藏 | K17: CTR 点击率 | L17: CPC 点击成本 | M17: CPM 千次展现成本 | N17: ROI 投资回报率 | O17: CVR 点击转化率 | P17: ASP 订单均价 | Q17: Cporder 订单成本 | R17: CPshopping cart 加购成本
A18: 明星店铺 | B18: 2866.29 | C18: 12670 | D18: 404 | E18: 3 | F18: 600 | G18: 2 | H18: 1 | I18: 12 | K18: =D18/C18 -> 0.031886346 | L18: =B18/D18 -> 7.0947772 | M18: =(B18/C18)*1000 -> 226.22652 | N18: =F18/B18 -> 0.20932983 | O18: =E18/D18 -> 0.0074257426 | P18: =F18/E18 -> 200 | Q18: =B18/E18 -> 955.43 | R18: =B18/G18 -> 1433.145
A19: 直通车 | B19: 3311.5 | C19: 120004 | D19: 2346 | E19: 0 | F19: 0 | G19: 1 | H19: 2 | I19: 8 | K19: =D19/C19 -> 0.019549348 | L19: =B19/D19 -> 1.4115516 | M19: =(B19/C19)*1000 -> 27.594914 | N19: =F19/B19 -> 0 | O19: =E19/D19 -> 0 | P19: =F19/E19 -> #DIV/0! | Q19: =B19/E19 -> #DIV/0! | R19: =B19/G19 -> 3311.5
A20: 引力魔方 | B20: 2031.5 | C20: 219571 | D20: 1511 | E20: 0 | F20: 0 | G20: 2 | H20: 14 | I20: 0 | K20: =D20/C20 -> 0.0068816009 | L20: =B20/D20 -> 1.3444739 | M20: =(B20/C20)*1000 -> 9.2521326 | N20: =F20/B20 -> 0 | O20: =E20/D20 -> 0 | P20: =F20/E20 -> #DIV/0! | Q20: =B20/E20 -> #DIV/0! | R20: =B20/G20 -> 1015.75
A21: 总计 | B21: =SUM(B18:B20) -> 8209.29 | C21: =SUM(C18:C20) -> 352245 | D21: =SUM(D18:D20) -> 4261 | E21: =SUM(E18:E20) -> 3 | F21: =SUM(F18:F20) -> 600 | G21: =SUM(G18:G20) -> 5 | H21: =SUM(H18:H20) -> 17 | I21: =SUM(I18:I20) -> 20 | K21: =D21/C21 -> 0.012096694 | L21: =B21/D21 -> 1.9266111 | M21: =(B21/C21)*1000 -> 23.305625 | N21: =F21/B21 -> 0.073087928 | O21: =E21/D21 -> 0.00070406008 | P21: =F21/E21 -> 200 | Q21: =B21/E21 -> 2736.43 | R21: =B21/G21 -> 1641.858
A25: 2023年
A26: 8月 | B26: Cost 花费 | C26: IMP 展示 | D26: Click 点击 | E26: Order 订单 | F26: Sales 销量 | G26: ShoppingCart 加入购物车 | H26: Bookmark-Product 宝贝收藏 | I26: Bookmark-Store 店铺收藏 | K26: CTR 点击率 | L26: CPC 点击成本 | M26: CPM 千次展现成本 | N26: ROI 投资回报率 | O26: CVR 点击转化率 | P26: ASP 订单均价 | Q26: Cporder 订单成本 | R26: CPshopping cart 加购成本
A27: 明星店铺 | B27: =SUM(明星店铺!B514:B522) -> 496.42 | C27: =SUM(明星店铺!C514:C522) -> 670 | D27: =SUM(明星店铺!D514:D522) -> 180 | E27: =SUM(明星店铺!E514:E522) -> 3 | F27: =SUM(明星店铺!F514:F522) -> 3 | G27: =SUM(明星店铺!G514:G522) -> 38 | H27: =SUM(明星店铺!H514:H522) -> 8 | I27: =SUM(明星店铺!I514:I522) -> 6 | K27: =D27/C27 -> 0.26865672 | L27: =B27/D27 -> 2.7578889 | M27: =(B27/C27)*1000 -> 740.92537 | N27: =F27/B27 -> 0.0060432698 | O27: =E27/D27 -> 0.016666667 | P27: =F27/E27 -> 1 | Q27: =B27/E27 -> 165.47333 | R27: =B27/G27 -> 13.063684
A28: 直通车 | B28: =SUM(直通车!B514:B522) -> 8646.78 | C28: =SUM(直通车!C514:C522) -> 32943 | D28: =SUM(直通车!D514:D522) -> 2523 | E28: =SUM(直通车!E514:E522) -> 1 | F28: =SUM(直通车!F514:F522) -> 1 | G28: =SUM(直通车!G514:G522) -> 62 | H28: =SUM(直通车!H514:H522) -> 37 | I28: =SUM(直通车!I514:I522) -> 12 | K28: =D28/C28 -> 0.076586832 | L28: =B28/D28 -> 3.4271819 | M28: =(B28/C28)*1000 -> 262.47701 | N28: =F28/B28 -> 0.00011564999 | O28: =E28/D28 -> 0.00039635355 | P28: =F28/E28 -> 1 | Q28: =B28/E28 -> 8646.78 | R28: =B28/G28 -> 139.46419
A29: 引力魔方 | B29: =SUM(引力魔方!B413:B421) -> 4176.9 | C29: =SUM(引力魔方!C413:C421) -> 444197 | D29: =SUM(引力魔方!D413:D421) -> 2732 | E29: =SUM(引力魔方!E413:E421) -> 0 | F29: =SUM(引力魔方!F413:F421) -> 0 | G29: =SUM(引力魔方!G413:G421) -> 25 | H29: =SUM(引力魔方!H413:H421) -> 14 | I29: =SUM(引力魔方!I413:I421) -> 2 | K29: =D29/C29 -> 0.0061504242 | L29: =B29/D29 -> 1.5288799 | M29: =(B29/C29)*1000 -> 9.4032603 | N29: =F29/B29 -> 0 | O29: =E29/D29 -> 0 | P29: =F29/E29 -> #DIV/0! | Q29: =B29/E29 -> #DIV/0! | R29: =B29/G29 -> 167.076
